Workbook

Sheet Summary
A1: rAGMF & FHL Loans - Interest Paid vs Payable
A2: 800 Super GAEA (Cambodia) Co., Ltd. | Lender basis, reconciled to lender exposure calc 30/06/2026 and Amendment cl. 3.8 | USD
A3: Reporting date: | B3: =Inputs!B18 -> 46300 | C3: Default interest after 30/06/2026: | E3: =IF(Inputs!B20=1,"Continues","Stopped") -> Continues
A5: 1. Position at reporting date (accrual to day before reporting date)
A6: USD | B6: rAGMF | C6: FHL | D6: Total | E6: Note
A7: Principal outstanding | B7: =Inputs!B9-SUMIFS(Cash_Events!$G$6:$G$20,Cash_Events!$C$6:$C$20,"rAGMF",Cash_Events!$B$6:$B$20,"<"&Inputs!$B$18) -> 735000 | C7: =Inputs!C9-SUMIFS(Cash_Events!$G$6:$G$20,Cash_Events!$C$6:$C$20,"FHL",Cash_Events!$B$6:$B$20,"<"&Inputs!$B$18) -> 735000 | D7: =B7+C7 -> 1470000
A8: Regular interest payable | B8: =SUMIFS(Daily!$G$6:$G$2400,Daily!$A$6:$A$2400,"<"&Inputs!$B$18)-SUMIFS(Cash_Events!$H$6:$H$20,Cash_Events!$C$6:$C$20,"rAGMF",Cash_Events!$B$6:$B$20,"<"&Inputs!$B$18) -> 318304.07 | C8: =SUMIFS(Daily!$L$6:$L$2400,Daily!$A$6:$A$2400,"<"&Inputs!$B$18)-SUMIFS(Cash_Events!$H$6:$H$20,Cash_Events!$C$6:$C$20,"FHL",Cash_Events!$B$6:$B$20,"<"&Inputs!$B$18) -> 317678.41 | D8: =B8+C8 -> 635982.48
A9: Default interest payable | B9: =SUMIFS(Daily!$H$6:$H$2400,Daily!$A$6:$A$2400,"<"&Inputs!$B$18)-SUMIFS(Cash_Events!$I$6:$I$20,Cash_Events!$C$6:$C$20,"rAGMF",Cash_Events!$B$6:$B$20,"<"&Inputs!$B$18) -> 48556.257 | C9: =SUMIFS(Daily!$M$6:$M$2400,Daily!$A$6:$A$2400,"<"&Inputs!$B$18)-SUMIFS(Cash_Events!$I$6:$I$20,Cash_Events!$C$6:$C$20,"FHL",Cash_Events!$B$6:$B$20,"<"&Inputs!$B$18) -> 48438.75 | D9: =B9+C9 -> 96995.006
A10: Total interest payable | B10: =B8+B9 -> 366860.33 | C10: =C8+C9 -> 366117.16 | D10: =B10+C10 -> 732977.49 | E10: Overdue interest incl. default
A11: Total due to lender | B11: =B7+B10 -> 1101860.3 | C11: =C7+C10 -> 1101117.2 | D11: =B11+C11 -> 2202977.5
A13: 2. Lifetime interest bridge - drawdown 09/09/2022 to reporting date
A14: USD | B14: rAGMF | C14: FHL | D14: Total | E14: Note
A15: Regular interest charged | B15: =SUMIFS(Daily!$G$6:$G$2400,Daily!$A$6:$A$2400,"<"&Inputs!$B$18) -> 494429.94 | C15: =SUMIFS(Daily!$L$6:$L$2400,Daily!$A$6:$A$2400,"<"&Inputs!$B$18) -> 493868.66 | D15: =B15+C15 -> 988298.6 | E15: 6M Term SOFR + 6.75%, ACT/ACT
A16: Default interest charged | B16: =SUMIFS(Daily!$H$6:$H$2400,Daily!$A$6:$A$2400,"<"&Inputs!$B$18) -> 57244.157 | C16: =SUMIFS(Daily!$M$6:$M$2400,Daily!$A$6:$A$2400,"<"&Inputs!$B$18) -> 56915.39 | D16: =B16+C16 -> 114159.55 | E16: 2% on outstanding principal from first missed coupon
A17: Paid by JV (coupon 1, 07/03/2023) | B17: =SUMIFS(Cash_Events!$H$6:$H$20,Cash_Events!$C$6:$C$20,"rAGMF",Cash_Events!$D$6:$D$20,"JV",Cash_Events!$B$6:$B$20,"<"&Inputs!$B$18)+SUMIFS(Cash_Events!$I$6:$I$20,Cash_Events!$C$6:$C$20,"rAGMF",Cash_Events!$D$6:$D$20,"JV",Cash_Events!$B$6:$B$20,"<"&Inputs!$B$18) -> 75648.08 | C17: =SUMIFS(Cash_Events!$H$6:$H$20,Cash_Events!$C$6:$C$20,"FHL",Cash_Events!$D$6:$D$20,"JV",Cash_Events!$B$6:$B$20,"<"&Inputs!$B$18)+SUMIFS(Cash_Events!$I$6:$I$20,Cash_Events!$C$6:$C$20,"FHL",Cash_Events!$D$6:$D$20,"JV",Cash_Events!$B$6:$B$20,"<"&Inputs!$B$18) -> 78155.75 | D17: =B17+C17 -> 153803.83 | E17: Payment vouchers PV10 / PV12
A18: Paid by 800S on JV's behalf (June 2024) | B18: =SUMIFS(Cash_Events!$H$6:$H$20,Cash_Events!$C$6:$C$20,"rAGMF",Cash_Events!$D$6:$D$20,"800S",Cash_Events!$B$6:$B$20,"<"&Inputs!$B$18)+SUMIFS(Cash_Events!$I$6:$I$20,Cash_Events!$C$6:$C$20,"rAGMF",Cash_Events!$D$6:$D$20,"800S",Cash_Events!$B$6:$B$20,"<"&Inputs!$B$18) -> 109165.69 | C18: =SUMIFS(Cash_Events!$H$6:$H$20,Cash_Events!$C$6:$C$20,"FHL",Cash_Events!$D$6:$D$20,"800S",Cash_Events!$B$6:$B$20,"<"&Inputs!$B$18)+SUMIFS(Cash_Events!$I$6:$I$20,Cash_Events!$C$6:$C$20,"FHL",Cash_Events!$D$6:$D$20,"800S",Cash_Events!$B$6:$B$20,"<"&Inputs!$B$18) -> 106511.14 | D18: =B18+C18 -> 215676.83 | E18: Incl. USD 1,163.29 cross-allocation in principal remittances
A19: Total interest charged | B19: =B15+B16 -> 551674.1 | C19: =C15+C16 -> 550784.05 | D19: =D15+D16 -> 1102458.2
A20: Total interest paid | B20: =B17+B18 -> 184813.77 | C20: =C17+C18 -> 184666.89 | D20: =D17+D18 -> 369480.66 | E20: =IF(D19=0,0,D20/D19) -> 0.33514257
A21: Interest payable (= section 1) | B21: =B19-B20 -> 366860.33 | C21: =C19-C20 -> 366117.16 | D21: =D19-D20 -> 732977.49
A22: Check vs section 1 | B22: =ROUND(B21-B10,2) -> 0 | C22: =ROUND(C21-C10,2) -> 0 | D22: =ROUND(D21-D10,2) -> 0
A24: 3. Tie-out to lender and books
A25: USD | B25: rAGMF | C25: FHL | D25: Total | E25: Note
A26: Model at 30/06/2026 | B26: =Reconciliation!B9 -> 342674.23 | C26: =Reconciliation!E9 -> 341914.87 | D26: =B26+C26 -> 684589.1
A27: Lender Overdue Interest (Amendment cl. 3.8) | B27: =Inputs!B25 -> 342674.23 | C27: =Inputs!C25 -> 341914.87 | D27: =B27+C27 -> 684589.1
A28: Variance | B28: =ROUND(B26-B27,2) -> 0 | C28: =ROUND(C26-C27,2) -> 0 | D28: =ROUND(D26-D27,2) -> 0
A29: Accrued since lender cut-off (30/06/2026 to reporting date) | B29: =B10-B26 -> 24186.096 | C29: =C10-C26 -> 24202.289 | D29: =B29+C29 -> 48388.385
A30: Interest + default payable in JV books (13/03/2026 summary) | D30: =Reconciliation!D40 -> 519656.72 | E30: Equals lender position at 09/08/2025 (not updated since)
A31: Catch-up accrual required in JV books to 30/09/2026 | D31: =Reconciliation!D45 -> 210826.52
A32: Due to 800 Super WM Pte (subrogated principal + interest) | D32: =BS_View!H62 -> 1745676.8 | E32: Ties to JV books shareholder loan
A34: 4. Lender exposure projection - 31/03/2029 (no payments)
A35: USD | B35: rAGMF | C35: FHL | D35: Total | E35: Note
A36: Interest payable - this model | B36: =Reconciliation!B20 -> 593012.8 | C36: =Reconciliation!E20 -> 592421.04 | D36: =B36+C36 -> 1185433.8
A37: Interest payable - lender guarantee calc | B37: =Inputs!B28 -> 593262.14 | C37: =Inputs!C28 -> 592670.55 | D37: =B37+C37 -> 1185932.7
A38: Variance | B38: =B36-B37 -> -249.34161 | C38: =C36-C37 -> -249.50896 | D38: =D36-D37 -> -498.85057 | E38: Lender applies /365 to leap year 2028
A39: Total exposure incl. principal - this model | B39: =INDEX(rAGMF_Monthly!$U$7:$U$85,MATCH(Inputs!$B$21,rAGMF_Monthly!$A$7:$A$85,0)) -> 1328012.8 | C39: =INDEX(FHL_Monthly!$U$7:$U$85,MATCH(Inputs!$B$21,FHL_Monthly!$A$7:$A$85,0)) -> 1327421 | D39: =B39+C39 -> 2655433.8

Sheet Year_End_Totals
A1: Year-End Totals FY2022-FY2026 - Roll-forward for Audit
A2: 800 Super GAEA (Cambodia) Co., Ltd. | USD | Lender basis, reconciled to lender exposure calc 30/06/2026 | FY = calendar year
A4: USD | B4: FY2022 | C4: FY2023 | D4: FY2024 | E4: FY2025 | F4: FY2026
A5: Period start | B5: 44813 | C5: 44927 | D5: 45292 | E5: 45658 | F5: 46023
A6: Balance date | B6: 44926 | C6: 45291 | D6: 45657 | E6: 46022 | F6: 46387
A7: Basis | B7: =IF(B6<=EOMONTH(Inputs!$B$18,-1),"Actual","Actual to "&TEXT(EOMONTH(Inputs!$B$18,-1),"dd/mm/yyyy")&" + projection") -> Actual | C7: =IF(C6<=EOMONTH(Inputs!$B$18,-1),"Actual","Actual to "&TEXT(EOMONTH(Inputs!$B$18,-1),"dd/mm/yyyy")&" + projection") -> Actual | D7: =IF(D6<=EOMONTH(Inputs!$B$18,-1),"Actual","Actual to "&TEXT(EOMONTH(Inputs!$B$18,-1),"dd/mm/yyyy")&" + projection") -> Actual | E7: =IF(E6<=EOMONTH(Inputs!$B$18,-1),"Actual","Actual to "&TEXT(EOMONTH(Inputs!$B$18,-1),"dd/mm/yyyy")&" + projection") -> Actual | F7: =IF(F6<=EOMONTH(Inputs!$B$18,-1),"Actual","Actual to "&TEXT(EOMONTH(Inputs!$B$18,-1),"dd/mm/yyyy")&" + projection") -> Actual to 30/09/2026 + projection
A9: rAGMF
A10: Principal
A11: Opening principal | B11: 0 | C11: =B14 -> 1500000 | D11: =C14 -> 1500000 | E11: =D14 -> 735000 | F11: =E14 -> 735000
A12: Drawdown | B12: =IF(AND(Inputs!B8>=B$5,Inputs!B8<=B$6),Inputs!B9,0) -> 1500000 | C12: =IF(AND(Inputs!B8>=C$5,Inputs!B8<=C$6),Inputs!B9,0) -> 0 | D12: =IF(AND(Inputs!B8>=D$5,Inputs!B8<=D$6),Inputs!B9,0) -> 0 | E12: =IF(AND(Inputs!B8>=E$5,Inputs!B8<=E$6),Inputs!B9,0) -> 0 | F12: =IF(AND(Inputs!B8>=F$5,Inputs!B8<=F$6),Inputs!B9,0) -> 0
A13: Repaid (800S guarantor payment) | B13: =-SUMIFS(Cash_Events!$G$6:$G$20,Cash_Events!$C$6:$C$20,"rAGMF",Cash_Events!$B$6:$B$20,">="&B$5,Cash_Events!$B$6:$B$20,"<="&B$6) -> 0 | C13: =-SUMIFS(Cash_Events!$G$6:$G$20,Cash_Events!$C$6:$C$20,"rAGMF",Cash_Events!$B$6:$B$20,">="&C$5,Cash_Events!$B$6:$B$20,"<="&C$6) -> 0 | D13: =-SUMIFS(Cash_Events!$G$6:$G$20,Cash_Events!$C$6:$C$20,"rAGMF",Cash_Events!$B$6:$B$20,">="&D$5,Cash_Events!$B$6:$B$20,"<="&D$6) -> -765000 | E13: =-SUMIFS(Cash_Events!$G$6:$G$20,Cash_Events!$C$6:$C$20,"rAGMF",Cash_Events!$B$6:$B$20,">="&E$5,Cash_Events!$B$6:$B$20,"<="&E$6) -> 0 | F13: =-SUMIFS(Cash_Events!$G$6:$G$20,Cash_Events!$C$6:$C$20,"rAGMF",Cash_Events!$B$6:$B$20,">="&F$5,Cash_Events!$B$6:$B$20,"<="&F$6) -> 0
A14: Closing principal | B14: =B11+B12+B13 -> 1500000 | C14: =C11+C12+C13 -> 1500000 | D14: =D11+D12+D13 -> 735000 | E14: =E11+E12+E13 -> 735000 | F14: =F11+F12+F13 -> 735000
A15: Regular interest payable
A16: Opening regular interest payable | B16: 0 | C16: =B20 -> 47227.807 | D16: =C20 -> 147229.27 | E16: =D20 -> 179232.86 | F16: =E20 -> 259725.33
A17: Interest charged (6M SOFR + 6.75%) | B17: =SUMIFS(rAGMF_Monthly!$J$7:$J$85,rAGMF_Monthly!$A$7:$A$85,">="&B$5,rAGMF_Monthly!$A$7:$A$85,"<="&B$6) -> 47227.807 | C17: =SUMIFS(rAGMF_Monthly!$J$7:$J$85,rAGMF_Monthly!$A$7:$A$85,">="&C$5,rAGMF_Monthly!$A$7:$A$85,"<="&C$6) -> 175649.55 | D17: =SUMIFS(rAGMF_Monthly!$J$7:$J$85,rAGMF_Monthly!$A$7:$A$85,">="&D$5,rAGMF_Monthly!$A$7:$A$85,"<="&D$6) -> 132481.37 | E17: =SUMIFS(rAGMF_Monthly!$J$7:$J$85,rAGMF_Monthly!$A$7:$A$85,">="&E$5,rAGMF_Monthly!$A$7:$A$85,"<="&E$6) -> 80492.478 | F17: =SUMIFS(rAGMF_Monthly!$J$7:$J$85,rAGMF_Monthly!$A$7:$A$85,">="&F$5,rAGMF_Monthly!$A$7:$A$85,"<="&F$6) -> 76767.587
A18: Paid by JV | B18: =-SUMIFS(Cash_Events!$H$6:$H$20,Cash_Events!$C$6:$C$20,"rAGMF",Cash_Events!$D$6:$D$20,"JV",Cash_Events!$B$6:$B$20,">="&B$5,Cash_Events!$B$6:$B$20,"<="&B$6) -> 0 | C18: =-SUMIFS(Cash_Events!$H$6:$H$20,Cash_Events!$C$6:$C$20,"rAGMF",Cash_Events!$D$6:$D$20,"JV",Cash_Events!$B$6:$B$20,">="&C$5,Cash_Events!$B$6:$B$20,"<="&C$6) -> -75648.08 | D18: =-SUMIFS(Cash_Events!$H$6:$H$20,Cash_Events!$C$6:$C$20,"rAGMF",Cash_Events!$D$6:$D$20,"JV",Cash_Events!$B$6:$B$20,">="&D$5,Cash_Events!$B$6:$B$20,"<="&D$6) -> 0 | E18: =-SUMIFS(Cash_Events!$H$6:$H$20,Cash_Events!$C$6:$C$20,"rAGMF",Cash_Events!$D$6:$D$20,"JV",Cash_Events!$B$6:$B$20,">="&E$5,Cash_Events!$B$6:$B$20,"<="&E$6) -> 0 | F18: =-SUMIFS(Cash_Events!$H$6:$H$20,Cash_Events!$C$6:$C$20,"rAGMF",Cash_Events!$D$6:$D$20,"JV",Cash_Events!$B$6:$B$20,">="&F$5,Cash_Events!$B$6:$B$20,"<="&F$6) -> 0
A19: Paid by 800S on JV's behalf | B19: =-SUMIFS(Cash_Events!$H$6:$H$20,Cash_Events!$C$6:$C$20,"rAGMF",Cash_Events!$D$6:$D$20,"800S",Cash_Events!$B$6:$B$20,">="&B$5,Cash_Events!$B$6:$B$20,"<="&B$6) -> 0 | C19: =-SUMIFS(Cash_Events!$H$6:$H$20,Cash_Events!$C$6:$C$20,"rAGMF",Cash_Events!$D$6:$D$20,"800S",Cash_Events!$B$6:$B$20,">="&C$5,Cash_Events!$B$6:$B$20,"<="&C$6) -> 0 | D19: =-SUMIFS(Cash_Events!$H$6:$H$20,Cash_Events!$C$6:$C$20,"rAGMF",Cash_Events!$D$6:$D$20,"800S",Cash_Events!$B$6:$B$20,">="&D$5,Cash_Events!$B$6:$B$20,"<="&D$6) -> -100477.79 | E19: =-SUMIFS(Cash_Events!$H$6:$H$20,Cash_Events!$C$6:$C$20,"rAGMF",Cash_Events!$D$6:$D$20,"800S",Cash_Events!$B$6:$B$20,">="&E$5,Cash_Events!$B$6:$B$20,"<="&E$6) -> 0 | F19: =-SUMIFS(Cash_Events!$H$6:$H$20,Cash_Events!$C$6:$C$20,"rAGMF",Cash_Events!$D$6:$D$20,"800S",Cash_Events!$B$6:$B$20,">="&F$5,Cash_Events!$B$6:$B$20,"<="&F$6) -> 0
A20: Closing regular interest payable | B20: =B16+B17+B18+B19 -> 47227.807 | C20: =C16+C17+C18+C19 -> 147229.27 | D20: =D16+D17+D18+D19 -> 179232.86 | E20: =E16+E17+E18+E19 -> 259725.33 | F20: =F16+F17+F18+F19 -> 336492.92
A21: Default interest payable
A22: Opening default interest payable | B22: 0 | C22: =B26 -> 0 | D22: =C26 -> 9123.2877 | E22: =D26 -> 22660.202 | F22: =E26 -> 37360.092
A23: Default interest charged (2% on principal) | B23: =SUMIFS(rAGMF_Monthly!$K$7:$K$85,rAGMF_Monthly!$A$7:$A$85,">="&B$5,rAGMF_Monthly!$A$7:$A$85,"<="&B$6) -> 0 | C23: =SUMIFS(rAGMF_Monthly!$K$7:$K$85,rAGMF_Monthly!$A$7:$A$85,">="&C$5,rAGMF_Monthly!$A$7:$A$85,"<="&C$6) -> 9123.2877 | D23: =SUMIFS(rAGMF_Monthly!$K$7:$K$85,rAGMF_Monthly!$A$7:$A$85,">="&D$5,rAGMF_Monthly!$A$7:$A$85,"<="&D$6) -> 22224.815 | E23: =SUMIFS(rAGMF_Monthly!$K$7:$K$85,rAGMF_Monthly!$A$7:$A$85,">="&E$5,rAGMF_Monthly!$A$7:$A$85,"<="&E$6) -> 14699.89 | F23: =SUMIFS(rAGMF_Monthly!$K$7:$K$85,rAGMF_Monthly!$A$7:$A$85,">="&F$5,rAGMF_Monthly!$A$7:$A$85,"<="&F$6) -> 14700
A24: Paid by JV | B24: =-SUMIFS(Cash_Events!$I$6:$I$20,Cash_Events!$C$6:$C$20,"rAGMF",Cash_Events!$D$6:$D$20,"JV",Cash_Events!$B$6:$B$20,">="&B$5,Cash_Events!$B$6:$B$20,"<="&B$6) -> 0 | C24: =-SUMIFS(Cash_Events!$I$6:$I$20,Cash_Events!$C$6:$C$20,"rAGMF",Cash_Events!$D$6:$D$20,"JV",Cash_Events!$B$6:$B$20,">="&C$5,Cash_Events!$B$6:$B$20,"<="&C$6) -> 0 | D24: =-SUMIFS(Cash_Events!$I$6:$I$20,Cash_Events!$C$6:$C$20,"rAGMF",Cash_Events!$D$6:$D$20,"JV",Cash_Events!$B$6:$B$20,">="&D$5,Cash_Events!$B$6:$B$20,"<="&D$6) -> 0 | E24: =-SUMIFS(Cash_Events!$I$6:$I$20,Cash_Events!$C$6:$C$20,"rAGMF",Cash_Events!$D$6:$D$20,"JV",Cash_Events!$B$6:$B$20,">="&E$5,Cash_Events!$B$6:$B$20,"<="&E$6) -> 0 | F24: =-SUMIFS(Cash_Events!$I$6:$I$20,Cash_Events!$C$6:$C$20,"rAGMF",Cash_Events!$D$6:$D$20,"JV",Cash_Events!$B$6:$B$20,">="&F$5,Cash_Events!$B$6:$B$20,"<="&F$6) -> 0
A25: Paid by 800S on JV's behalf | B25: =-SUMIFS(Cash_Events!$I$6:$I$20,Cash_Events!$C$6:$C$20,"rAGMF",Cash_Events!$D$6:$D$20,"800S",Cash_Events!$B$6:$B$20,">="&B$5,Cash_Events!$B$6:$B$20,"<="&B$6) -> 0 | C25: =-SUMIFS(Cash_Events!$I$6:$I$20,Cash_Events!$C$6:$C$20,"rAGMF",Cash_Events!$D$6:$D$20,"800S",Cash_Events!$B$6:$B$20,">="&C$5,Cash_Events!$B$6:$B$20,"<="&C$6) -> 0 | D25: =-SUMIFS(Cash_Events!$I$6:$I$20,Cash_Events!$C$6:$C$20,"rAGMF",Cash_Events!$D$6:$D$20,"800S",Cash_Events!$B$6:$B$20,">="&D$5,Cash_Events!$B$6:$B$20,"<="&D$6) -> -8687.9 | E25: =-SUMIFS(Cash_Events!$I$6:$I$20,Cash_Events!$C$6:$C$20,"rAGMF",Cash_Events!$D$6:$D$20,"800S",Cash_Events!$B$6:$B$20,">="&E$5,Cash_Events!$B$6:$B$20,"<="&E$6) -> 0 | F25: =-SUMIFS(Cash_Events!$I$6:$I$20,Cash_Events!$C$6:$C$20,"rAGMF",Cash_Events!$D$6:$D$20,"800S",Cash_Events!$B$6:$B$20,">="&F$5,Cash_Events!$B$6:$B$20,"<="&F$6) -> 0
A26: Closing default interest payable | B26: =B22+B23+B24+B25 -> 0 | C26: =C22+C23+C24+C25 -> 9123.2877 | D26: =D22+D23+D24+D25 -> 22660.202 | E26: =E22+E23+E24+E25 -> 37360.092 | F26: =F22+F23+F24+F25 -> 52060.092
A27: Year-end summary
A28: Total interest payable to lender | B28: =B20+B26 -> 47227.807 | C28: =C20+C26 -> 156352.56 | D28: =D20+D26 -> 201893.06 | E28: =E20+E26 -> 297085.43 | F28: =F20+F26 -> 388553.01
A29: Total due to lender (principal + interest) | B29: =B14+B28 -> 1547227.8 | C29: =C14+C28 -> 1656352.6 | D29: =D14+D28 -> 936893.06 | E29: =E14+E28 -> 1032085.4 | F29: =F14+F28 -> 1123553
A30: Interest expense for the year (P&L) | B30: =B17+B23 -> 47227.807 | C30: =C17+C23 -> 184772.83 | D30: =D17+D23 -> 154706.19 | E30: =E17+E23 -> 95192.368 | F30: =F17+F23 -> 91467.587
A31: Interest paid in the year (all payers) | B31: =-(B18+B19+B24+B25) -> 0 | C31: =-(C18+C19+C24+C25) -> 75648.08 | D31: =-(D18+D19+D24+D25) -> 109165.69 | E31: =-(E18+E19+E24+E25) -> 0 | F31: =-(F18+F19+F24+F25) -> 0
A32: Check: closing vs monthly schedule (=0) | B32: =ROUND(B14-INDEX(rAGMF_Monthly!$G$7:$G$85,MATCH(B$6,rAGMF_Monthly!$A$7:$A$85,0)),2)+ROUND(B20-INDEX(rAGMF_Monthly!$P$7:$P$85,MATCH(B$6,rAGMF_Monthly!$A$7:$A$85,0)),2)+ROUND(B26-INDEX(rAGMF_Monthly!$S$7:$S$85,MATCH(B$6,rAGMF_Monthly!$A$7:$A$85,0)),2) -> 0 | C32: =ROUND(C14-INDEX(rAGMF_Monthly!$G$7:$G$85,MATCH(C$6,rAGMF_Monthly!$A$7:$A$85,0)),2)+ROUND(C20-INDEX(rAGMF_Monthly!$P$7:$P$85,MATCH(C$6,rAGMF_Monthly!$A$7:$A$85,0)),2)+ROUND(C26-INDEX(rAGMF_Monthly!$S$7:$S$85,MATCH(C$6,rAGMF_Monthly!$A$7:$A$85,0)),2) -> 0 | D32: =ROUND(D14-INDEX(rAGMF_Monthly!$G$7:$G$85,MATCH(D$6,rAGMF_Monthly!$A$7:$A$85,0)),2)+ROUND(D20-INDEX(rAGMF_Monthly!$P$7:$P$85,MATCH(D$6,rAGMF_Monthly!$A$7:$A$85,0)),2)+ROUND(D26-INDEX(rAGMF_Monthly!$S$7:$S$85,MATCH(D$6,rAGMF_Monthly!$A$7:$A$85,0)),2) -> 0 | E32: =ROUND(E14-INDEX(rAGMF_Monthly!$G$7:$G$85,MATCH(E$6,rAGMF_Monthly!$A$7:$A$85,0)),2)+ROUND(E20-INDEX(rAGMF_Monthly!$P$7:$P$85,MATCH(E$6,rAGMF_Monthly!$A$7:$A$85,0)),2)+ROUND(E26-INDEX(rAGMF_Monthly!$S$7:$S$85,MATCH(E$6,rAGMF_Monthly!$A$7:$A$85,0)),2) -> 0 | F32: =ROUND(F14-INDEX(rAGMF_Monthly!$G$7:$G$85,MATCH(F$6,rAGMF_Monthly!$A$7:$A$85,0)),2)+ROUND(F20-INDEX(rAGMF_Monthly!$P$7:$P$85,MATCH(F$6,rAGMF_Monthly!$A$7:$A$85,0)),2)+ROUND(F26-INDEX(rAGMF_Monthly!$S$7:$S$85,MATCH(F$6,rAGMF_Monthly!$A$7:$A$85,0)),2) -> 0
A34: FHL
A35: Principal
A36: Opening principal | B36: 0 | C36: =B39 -> 1500000 | D36: =C39 -> 1500000 | E36: =D39 -> 735000 | F36: =E39 -> 735000
A37: Drawdown | B37: =IF(AND(Inputs!C8>=B$5,Inputs!C8<=B$6),Inputs!C9,0) -> 1500000 | C37: =IF(AND(Inputs!C8>=C$5,Inputs!C8<=C$6),Inputs!C9,0) -> 0 | D37: =IF(AND(Inputs!C8>=D$5,Inputs!C8<=D$6),Inputs!C9,0) -> 0 | E37: =IF(AND(Inputs!C8>=E$5,Inputs!C8<=E$6),Inputs!C9,0) -> 0 | F37: =IF(AND(Inputs!C8>=F$5,Inputs!C8<=F$6),Inputs!C9,0) -> 0
A38: Repaid (800S guarantor payment) | B38: =-SUMIFS(Cash_Events!$G$6:$G$20,Cash_Events!$C$6:$C$20,"FHL",Cash_Events!$B$6:$B$20,">="&B$5,Cash_Events!$B$6:$B$20,"<="&B$6) -> 0 | C38: =-SUMIFS(Cash_Events!$G$6:$G$20,Cash_Events!$C$6:$C$20,"FHL",Cash_Events!$B$6:$B$20,">="&C$5,Cash_Events!$B$6:$B$20,"<="&C$6) -> 0 | D38: =-SUMIFS(Cash_Events!$G$6:$G$20,Cash_Events!$C$6:$C$20,"FHL",Cash_Events!$B$6:$B$20,">="&D$5,Cash_Events!$B$6:$B$20,"<="&D$6) -> -765000 | E38: =-SUMIFS(Cash_Events!$G$6:$G$20,Cash_Events!$C$6:$C$20,"FHL",Cash_Events!$B$6:$B$20,">="&E$5,Cash_Events!$B$6:$B$20,"<="&E$6) -> 0 | F38: =-SUMIFS(Cash_Events!$G$6:$G$20,Cash_Events!$C$6:$C$20,"FHL",Cash_Events!$B$6:$B$20,">="&F$5,Cash_Events!$B$6:$B$20,"<="&F$6) -> 0
A39: Closing principal | B39: =B36+B37+B38 -> 1500000 | C39: =C36+C37+C38 -> 1500000 | D39: =D36+D37+D38 -> 735000 | E39: =E36+E37+E38 -> 735000 | F39: =F36+F37+F38 -> 735000
A40: Regular interest payable
A41: Opening regular interest payable | B41: 0 | C41: =B45 -> 47227.806 | D41: =C45 -> 144279.65 | E41: =D45 -> 178839 | F41: =E45 -> 259173.33
A42: Interest charged (6M SOFR + 6.75%) | B42: =SUMIFS(FHL_Monthly!$J$7:$J$85,FHL_Monthly!$A$7:$A$85,">="&B$5,FHL_Monthly!$A$7:$A$85,"<="&B$6) -> 47227.806 | C42: =SUMIFS(FHL_Monthly!$J$7:$J$85,FHL_Monthly!$A$7:$A$85,">="&C$5,FHL_Monthly!$A$7:$A$85,"<="&C$6) -> 175207.59 | D42: =SUMIFS(FHL_Monthly!$J$7:$J$85,FHL_Monthly!$A$7:$A$85,">="&D$5,FHL_Monthly!$A$7:$A$85,"<="&D$6) -> 132593.85 | E42: =SUMIFS(FHL_Monthly!$J$7:$J$85,FHL_Monthly!$A$7:$A$85,">="&E$5,FHL_Monthly!$A$7:$A$85,"<="&E$6) -> 80334.332 | F42: =SUMIFS(FHL_Monthly!$J$7:$J$85,FHL_Monthly!$A$7:$A$85,">="&F$5,FHL_Monthly!$A$7:$A$85,"<="&F$6) -> 76708.453
A43: Paid by JV | B43: =-SUMIFS(Cash_Events!$H$6:$H$20,Cash_Events!$C$6:$C$20,"FHL",Cash_Events!$D$6:$D$20,"JV",Cash_Events!$B$6:$B$20,">="&B$5,Cash_Events!$B$6:$B$20,"<="&B$6) -> 0 | C43: =-SUMIFS(Cash_Events!$H$6:$H$20,Cash_Events!$C$6:$C$20,"FHL",Cash_Events!$D$6:$D$20,"JV",Cash_Events!$B$6:$B$20,">="&C$5,Cash_Events!$B$6:$B$20,"<="&C$6) -> -78155.75 | D43: =-SUMIFS(Cash_Events!$H$6:$H$20,Cash_Events!$C$6:$C$20,"FHL",Cash_Events!$D$6:$D$20,"JV",Cash_Events!$B$6:$B$20,">="&D$5,Cash_Events!$B$6:$B$20,"<="&D$6) -> 0 | E43: =-SUMIFS(Cash_Events!$H$6:$H$20,Cash_Events!$C$6:$C$20,"FHL",Cash_Events!$D$6:$D$20,"JV",Cash_Events!$B$6:$B$20,">="&E$5,Cash_Events!$B$6:$B$20,"<="&E$6) -> 0 | F43: =-SUMIFS(Cash_Events!$H$6:$H$20,Cash_Events!$C$6:$C$20,"FHL",Cash_Events!$D$6:$D$20,"JV",Cash_Events!$B$6:$B$20,">="&F$5,Cash_Events!$B$6:$B$20,"<="&F$6) -> 0
A44: Paid by 800S on JV's behalf | B44: =-SUMIFS(Cash_Events!$H$6:$H$20,Cash_Events!$C$6:$C$20,"FHL",Cash_Events!$D$6:$D$20,"800S",Cash_Events!$B$6:$B$20,">="&B$5,Cash_Events!$B$6:$B$20,"<="&B$6) -> 0 | C44: =-SUMIFS(Cash_Events!$H$6:$H$20,Cash_Events!$C$6:$C$20,"FHL",Cash_Events!$D$6:$D$20,"800S",Cash_Events!$B$6:$B$20,">="&C$5,Cash_Events!$B$6:$B$20,"<="&C$6) -> 0 | D44: =-SUMIFS(Cash_Events!$H$6:$H$20,Cash_Events!$C$6:$C$20,"FHL",Cash_Events!$D$6:$D$20,"800S",Cash_Events!$B$6:$B$20,">="&D$5,Cash_Events!$B$6:$B$20,"<="&D$6) -> -98034.5 | E44: =-SUMIFS(Cash_Events!$H$6:$H$20,Cash_Events!$C$6:$C$20,"FHL",Cash_Events!$D$6:$D$20,"800S",Cash_Events!$B$6:$B$20,">="&E$5,Cash_Events!$B$6:$B$20,"<="&E$6) -> 0 | F44: =-SUMIFS(Cash_Events!$H$6:$H$20,Cash_Events!$C$6:$C$20,"FHL",Cash_Events!$D$6:$D$20,"800S",Cash_Events!$B$6:$B$20,">="&F$5,Cash_Events!$B$6:$B$20,"<="&F$6) -> 0
A45: Closing regular interest payable | B45: =B41+B42+B43+B44 -> 47227.806 | C45: =C41+C42+C43+C44 -> 144279.65 | D45: =D41+D42+D43+D44 -> 178839 | E45: =E41+E42+E43+E44 -> 259173.33 | F45: =F41+F42+F43+F44 -> 335881.78
A46: Default interest payable
A47: Opening default interest payable | B47: 0 | C47: =B51 -> 0 | D47: =C51 -> 8794.5205 | E47: =D51 -> 22542.695 | F47: =E51 -> 37242.585
A48: Default interest charged (2% on principal) | B48: =SUMIFS(FHL_Monthly!$K$7:$K$85,FHL_Monthly!$A$7:$A$85,">="&B$5,FHL_Monthly!$A$7:$A$85,"<="&B$6) -> 0 | C48: =SUMIFS(FHL_Monthly!$K$7:$K$85,FHL_Monthly!$A$7:$A$85,">="&C$5,FHL_Monthly!$A$7:$A$85,"<="&C$6) -> 8794.5205 | D48: =SUMIFS(FHL_Monthly!$K$7:$K$85,FHL_Monthly!$A$7:$A$85,">="&D$5,FHL_Monthly!$A$7:$A$85,"<="&D$6) -> 22224.815 | E48: =SUMIFS(FHL_Monthly!$K$7:$K$85,FHL_Monthly!$A$7:$A$85,">="&E$5,FHL_Monthly!$A$7:$A$85,"<="&E$6) -> 14699.89 | F48: =SUMIFS(FHL_Monthly!$K$7:$K$85,FHL_Monthly!$A$7:$A$85,">="&F$5,FHL_Monthly!$A$7:$A$85,"<="&F$6) -> 14700
A49: Paid by JV | B49: =-SUMIFS(Cash_Events!$I$6:$I$20,Cash_Events!$C$6:$C$20,"FHL",Cash_Events!$D$6:$D$20,"JV",Cash_Events!$B$6:$B$20,">="&B$5,Cash_Events!$B$6:$B$20,"<="&B$6) -> 0 | C49: =-SUMIFS(Cash_Events!$I$6:$I$20,Cash_Events!$C$6:$C$20,"FHL",Cash_Events!$D$6:$D$20,"JV",Cash_Events!$B$6:$B$20,">="&C$5,Cash_Events!$B$6:$B$20,"<="&C$6) -> 0 | D49: =-SUMIFS(Cash_Events!$I$6:$I$20,Cash_Events!$C$6:$C$20,"FHL",Cash_Events!$D$6:$D$20,"JV",Cash_Events!$B$6:$B$20,">="&D$5,Cash_Events!$B$6:$B$20,"<="&D$6) -> 0 | E49: =-SUMIFS(Cash_Events!$I$6:$I$20,Cash_Events!$C$6:$C$20,"FHL",Cash_Events!$D$6:$D$20,"JV",Cash_Events!$B$6:$B$20,">="&E$5,Cash_Events!$B$6:$B$20,"<="&E$6) -> 0 | F49: =-SUMIFS(Cash_Events!$I$6:$I$20,Cash_Events!$C$6:$C$20,"FHL",Cash_Events!$D$6:$D$20,"JV",Cash_Events!$B$6:$B$20,">="&F$5,Cash_Events!$B$6:$B$20,"<="&F$6) -> 0
A50: Paid by 800S on JV's behalf | B50: =-SUMIFS(Cash_Events!$I$6:$I$20,Cash_Events!$C$6:$C$20,"FHL",Cash_Events!$D$6:$D$20,"800S",Cash_Events!$B$6:$B$20,">="&B$5,Cash_Events!$B$6:$B$20,"<="&B$6) -> 0 | C50: =-SUMIFS(Cash_Events!$I$6:$I$20,Cash_Events!$C$6:$C$20,"FHL",Cash_Events!$D$6:$D$20,"800S",Cash_Events!$B$6:$B$20,">="&C$5,Cash_Events!$B$6:$B$20,"<="&C$6) -> 0 | D50: =-SUMIFS(Cash_Events!$I$6:$I$20,Cash_Events!$C$6:$C$20,"FHL",Cash_Events!$D$6:$D$20,"800S",Cash_Events!$B$6:$B$20,">="&D$5,Cash_Events!$B$6:$B$20,"<="&D$6) -> -8476.64 | E50: =-SUMIFS(Cash_Events!$I$6:$I$20,Cash_Events!$C$6:$C$20,"FHL",Cash_Events!$D$6:$D$20,"800S",Cash_Events!$B$6:$B$20,">="&E$5,Cash_Events!$B$6:$B$20,"<="&E$6) -> 0 | F50: =-SUMIFS(Cash_Events!$I$6:$I$20,Cash_Events!$C$6:$C$20,"FHL",Cash_Events!$D$6:$D$20,"800S",Cash_Events!$B$6:$B$20,">="&F$5,Cash_Events!$B$6:$B$20,"<="&F$6) -> 0
A51: Closing default interest payable | B51: =B47+B48+B49+B50 -> 0 | C51: =C47+C48+C49+C50 -> 8794.5205 | D51: =D47+D48+D49+D50 -> 22542.695 | E51: =E47+E48+E49+E50 -> 37242.585 | F51: =F47+F48+F49+F50 -> 51942.585
A52: Year-end summary
A53: Total interest payable to lender | B53: =B45+B51 -> 47227.806 | C53: =C45+C51 -> 153074.17 | D53: =D45+D51 -> 201381.69 | E53: =E45+E51 -> 296415.91 | F53: =F45+F51 -> 387824.37
A54: Total due to lender (principal + interest) | B54: =B39+B53 -> 1547227.8 | C54: =C39+C53 -> 1653074.2 | D54: =D39+D53 -> 936381.69 | E54: =E39+E53 -> 1031415.9 | F54: =F39+F53 -> 1122824.4
A55: Interest expense for the year (P&L) | B55: =B42+B48 -> 47227.806 | C55: =C42+C48 -> 184002.11 | D55: =D42+D48 -> 154818.66 | E55: =E42+E48 -> 95034.222 | F55: =F42+F48 -> 91408.453
A56: Interest paid in the year (all payers) | B56: =-(B43+B44+B49+B50) -> 0 | C56: =-(C43+C44+C49+C50) -> 78155.75 | D56: =-(D43+D44+D49+D50) -> 106511.14 | E56: =-(E43+E44+E49+E50) -> 0 | F56: =-(F43+F44+F49+F50) -> 0
A57: Check: closing vs monthly schedule (=0) | B57: =ROUND(B39-INDEX(FHL_Monthly!$G$7:$G$85,MATCH(B$6,FHL_Monthly!$A$7:$A$85,0)),2)+ROUND(B45-INDEX(FHL_Monthly!$P$7:$P$85,MATCH(B$6,FHL_Monthly!$A$7:$A$85,0)),2)+ROUND(B51-INDEX(FHL_Monthly!$S$7:$S$85,MATCH(B$6,FHL_Monthly!$A$7:$A$85,0)),2) -> 0 | C57: =ROUND(C39-INDEX(FHL_Monthly!$G$7:$G$85,MATCH(C$6,FHL_Monthly!$A$7:$A$85,0)),2)+ROUND(C45-INDEX(FHL_Monthly!$P$7:$P$85,MATCH(C$6,FHL_Monthly!$A$7:$A$85,0)),2)+ROUND(C51-INDEX(FHL_Monthly!$S$7:$S$85,MATCH(C$6,FHL_Monthly!$A$7:$A$85,0)),2) -> 0 | D57: =ROUND(D39-INDEX(FHL_Monthly!$G$7:$G$85,MATCH(D$6,FHL_Monthly!$A$7:$A$85,0)),2)+ROUND(D45-INDEX(FHL_Monthly!$P$7:$P$85,MATCH(D$6,FHL_Monthly!$A$7:$A$85,0)),2)+ROUND(D51-INDEX(FHL_Monthly!$S$7:$S$85,MATCH(D$6,FHL_Monthly!$A$7:$A$85,0)),2) -> 0 | E57: =ROUND(E39-INDEX(FHL_Monthly!$G$7:$G$85,MATCH(E$6,FHL_Monthly!$A$7:$A$85,0)),2)+ROUND(E45-INDEX(FHL_Monthly!$P$7:$P$85,MATCH(E$6,FHL_Monthly!$A$7:$A$85,0)),2)+ROUND(E51-INDEX(FHL_Monthly!$S$7:$S$85,MATCH(E$6,FHL_Monthly!$A$7:$A$85,0)),2) -> 0 | F57: =ROUND(F39-INDEX(FHL_Monthly!$G$7:$G$85,MATCH(F$6,FHL_Monthly!$A$7:$A$85,0)),2)+ROUND(F45-INDEX(FHL_Monthly!$P$7:$P$85,MATCH(F$6,FHL_Monthly!$A$7:$A$85,0)),2)+ROUND(F51-INDEX(FHL_Monthly!$S$7:$S$85,MATCH(F$6,FHL_Monthly!$A$7:$A$85,0)),2) -> 0
A59: Combined (rAGMF + FHL)
A60: Closing principal | B60: =B14+B39 -> 3000000 | C60: =C14+C39 -> 3000000 | D60: =D14+D39 -> 1470000 | E60: =E14+E39 -> 1470000 | F60: =F14+F39 -> 1470000
A61: Closing regular interest payable | B61: =B20+B45 -> 94455.613 | C61: =C20+C45 -> 291508.92 | D61: =D20+D45 -> 358071.85 | E61: =E20+E45 -> 518898.66 | F61: =F20+F45 -> 672374.7
A62: Closing default interest payable | B62: =B26+B51 -> 0 | C62: =C26+C51 -> 17917.808 | D62: =D26+D51 -> 45202.898 | E62: =E26+E51 -> 74602.678 | F62: =F26+F51 -> 104002.68
A63: Total interest payable to lender | B63: =B28+B53 -> 94455.613 | C63: =C28+C53 -> 309426.73 | D63: =D28+D53 -> 403274.75 | E63: =E28+E53 -> 593501.34 | F63: =F28+F53 -> 776377.38
A64: Total due to lender (principal + interest) | B64: =B29+B54 -> 3094455.6 | C64: =C29+C54 -> 3309426.7 | D64: =D29+D54 -> 1873274.8 | E64: =E29+E54 -> 2063501.3 | F64: =F29+F54 -> 2246377.4
A65: Interest expense for the year (P&L) | B65: =B30+B55 -> 94455.613 | C65: =C30+C55 -> 368774.95 | D65: =D30+D55 -> 309524.85 | E65: =E30+E55 -> 190226.59 | F65: =F30+F55 -> 182876.04
A66: Interest paid in the year (all payers) | B66: =B31+B56 -> 0 | C66: =C31+C56 -> 153803.83 | D66: =D31+D56 -> 215676.83 | E66: =E31+E56 -> 0 | F66: =F31+F56 -> 0
A68: Due to 800 Super Waste Management Pte (subrogated guarantor payments)
A69: Opening balance | B69: 0 | C69: =B72 -> 0 | D69: =C72 -> 0 | E69: =D72 -> 1745676.8 | F69: =E72 -> 1745676.8
A70: Principal funded | B70: =SUMIFS(Cash_Events!$G$6:$G$20,Cash_Events!$D$6:$D$20,"800S",Cash_Events!$B$6:$B$20,">="&B$5,Cash_Events!$B$6:$B$20,"<="&B$6) -> 0 | C70: =SUMIFS(Cash_Events!$G$6:$G$20,Cash_Events!$D$6:$D$20,"800S",Cash_Events!$B$6:$B$20,">="&C$5,Cash_Events!$B$6:$B$20,"<="&C$6) -> 0 | D70: =SUMIFS(Cash_Events!$G$6:$G$20,Cash_Events!$D$6:$D$20,"800S",Cash_Events!$B$6:$B$20,">="&D$5,Cash_Events!$B$6:$B$20,"<="&D$6) -> 1530000 | E70: =SUMIFS(Cash_Events!$G$6:$G$20,Cash_Events!$D$6:$D$20,"800S",Cash_Events!$B$6:$B$20,">="&E$5,Cash_Events!$B$6:$B$20,"<="&E$6) -> 0 | F70: =SUMIFS(Cash_Events!$G$6:$G$20,Cash_Events!$D$6:$D$20,"800S",Cash_Events!$B$6:$B$20,">="&F$5,Cash_Events!$B$6:$B$20,"<="&F$6) -> 0
A71: Interest funded (regular + default) | B71: =SUMIFS(Cash_Events!$H$6:$H$20,Cash_Events!$D$6:$D$20,"800S",Cash_Events!$B$6:$B$20,">="&B$5,Cash_Events!$B$6:$B$20,"<="&B$6)+SUMIFS(Cash_Events!$I$6:$I$20,Cash_Events!$D$6:$D$20,"800S",Cash_Events!$B$6:$B$20,">="&B$5,Cash_Events!$B$6:$B$20,"<="&B$6) -> 0 | C71: =SUMIFS(Cash_Events!$H$6:$H$20,Cash_Events!$D$6:$D$20,"800S",Cash_Events!$B$6:$B$20,">="&C$5,Cash_Events!$B$6:$B$20,"<="&C$6)+SUMIFS(Cash_Events!$I$6:$I$20,Cash_Events!$D$6:$D$20,"800S",Cash_Events!$B$6:$B$20,">="&C$5,Cash_Events!$B$6:$B$20,"<="&C$6) -> 0 | D71: =SUMIFS(Cash_Events!$H$6:$H$20,Cash_Events!$D$6:$D$20,"800S",Cash_Events!$B$6:$B$20,">="&D$5,Cash_Events!$B$6:$B$20,"<="&D$6)+SUMIFS(Cash_Events!$I$6:$I$20,Cash_Events!$D$6:$D$20,"800S",Cash_Events!$B$6:$B$20,">="&D$5,Cash_Events!$B$6:$B$20,"<="&D$6) -> 215676.83 | E71: =SUMIFS(Cash_Events!$H$6:$H$20,Cash_Events!$D$6:$D$20,"800S",Cash_Events!$B$6:$B$20,">="&E$5,Cash_Events!$B$6:$B$20,"<="&E$6)+SUMIFS(Cash_Events!$I$6:$I$20,Cash_Events!$D$6:$D$20,"800S",Cash_Events!$B$6:$B$20,">="&E$5,Cash_Events!$B$6:$B$20,"<="&E$6) -> 0 | F71: =SUMIFS(Cash_Events!$H$6:$H$20,Cash_Events!$D$6:$D$20,"800S",Cash_Events!$B$6:$B$20,">="&F$5,Cash_Events!$B$6:$B$20,"<="&F$6)+SUMIFS(Cash_Events!$I$6:$I$20,Cash_Events!$D$6:$D$20,"800S",Cash_Events!$B$6:$B$20,">="&F$5,Cash_Events!$B$6:$B$20,"<="&F$6) -> 0
A72: Closing balance | B72: =SUM(B69:B71) -> 0 | C72: =SUM(C69:C71) -> 0 | D72: =SUM(D69:D71) -> 1745676.8 | E72: =SUM(E69:E71) -> 1745676.8 | F72: =SUM(F69:F71) -> 1745676.8
A74: Total lender-related liabilities at year-end
A75: Due to lenders | B75: =B64 -> 3094455.6 | C75: =C64 -> 3309426.7 | D75: =D64 -> 1873274.8 | E75: =E64 -> 2063501.3 | F75: =F64 -> 2246377.4
A76: Due to 800S | B76: =B72 -> 0 | C76: =C72 -> 0 | D76: =D72 -> 1745676.8 | E76: =E72 -> 1745676.8 | F76: =F72 -> 1745676.8
A77: Total | B77: =B75+B76 -> 3094455.6 | C77: =C75+C76 -> 3309426.7 | D77: =D75+D76 -> 3618951.6 | E77: =E75+E76 -> 3809178.2 | F77: =F75+F76 -> 3992054.2
A79: Balances follow the lender's day-count convention: interest at 31 December covers accrual days up to 30 December inclusive.
A80: 800S payments (June 2024) are interest and principal of the JV settled by the guarantor; the JV owes them to 800 Super (shareholder loan USD 1,745,676.83).
A81: FY2026 closing is actual to the last month-end before the reporting date, then projected with no further payments and default interest continuing (Inputs B20).
A82: Excludes the USD 15,000 approval fee withheld on rAGMF drawdown (financing fee).

Sheet Inputs
A1: Inputs & Assumptions
A2: 800 Super GAEA (Cambodia) Co., Ltd. - rAGMF and FHL loans (USD 1.5M each). Blue = hard input, black = formula, green = link, yellow = editable lever.
A4: A. Loan terms
A5: Parameter | B5: rAGMF | C5: FHL | D5: Source / note
A6: Lender | B6: responsAbility Global Micro & SME Finance Fund (M&G Luxembourg S.A.) | C6: Financing for Healthier Lives DAC | D6: Amendment Agreements (drafts 22/07/2026 rAGMF, 31/07/2026 FHL)
A7: Loan agreement date | B7: 44811 | C7: 44811 | D7: Amendment Agreements, Recital A
A8: Disbursement / interest start date | B8: 44813 | C8: 44813 | D8: Payment vouchers PV10/PV12 (07/03/2023): coupon 1 runs from 09-Sep-22
A9: Original principal | B9: 1500000 | C9: 1500000 | D9: Loan agreements; lender exposure calc Jun-26
A10: Margin over 6M Term SOFR | B10: 0.0675 | C10: 0.0675 | D10: Lender exposure calc Jun-26 (Spread)
A11: Default interest (on outstanding principal) | B11: 0.02 | C11: 0.02 | D11: Lender exposure calc Jun-26 (Penalty rate, applied to principal only, no compounding)
A12: Day count | B12: ACT/ACT | C12: ACT/ACT | D12: Lender exposure calc: /365, /366 in 2024
A13: Default interest start date (first missed coupon) | B13: 45180 | C13: 45184 | D13: Lender exposure calc Jun-26, sections 5) Penalty
A14: Net cash received at disbursement (JV books) | B14: 1485000 | C14: 1499970 | D14: JV GL 12/09/2022 (rA net of USD 15,000 approval fee; FHL net of USD 30 bank charge). Memo only
A16: B. Reporting date and scenario levers
A17: Parameter | B17: Value | D17: Source / note
A18: Reporting date (position computed for accrual days before this date) | B18: 46300 | D18: Today
A19: Lender cut-off date (Overdue Interest crystallised) | B19: 46203 | D19: Amendment Agreements cl. 3.8 / lender exposure calc 30/06/2026
A20: Default interest continues after cut-off date (1 = Yes, 0 = No) | B20: 1 | D20: 1 = no amendment effective / no cure (lender's own 2029 projection basis). Set 0 if amendment effective and default interest waived from 01/07/2026
A21: Projection end date | B21: 47208 | D21: Lender exposure calc - guarantee purpose (31/03/2029)
A23: C. Lender reference figures (used for reconciliation only, not in calculations)
A24: Item (USD) | B24: rAGMF | C24: FHL | D24: Source / note
A25: Overdue interest incl. default at 30/06/2026 | B25: 342674.23 | C25: 341914.87 | D25: Amendment Agreements cl. 3.8 (rAGMF draft 22/07/2026; FHL draft 31/07/2026)
A26: of which accrued interest at 30/06/2026 | B26: 298024.55 | C26: 297382.7 | D26: Lender exposure calc Jun-26, Summary row 6
A27: of which default interest at 30/06/2026 | B27: 44649.681 | C27: 44532.174 | D27: Lender exposure calc Jun-26, Summary row 7
A28: Projected overdue interest incl. default at 31/03/2029 | B28: 593262.14 | C28: 592670.55 | D28: Lender exposure calc - guarantee purpose, Summary row 10
A29: Lender's coupon 2 amount (settled by 800 Super) | B29: 91458.57 | C29: 90529.739 | D29: Lender exposure calc, section 1) 'Repaid by 800 Super'
A30: Lender credit applied to accrued interest (June 2024 remittances) | B30: 9019.22 | C30: 7504.76 | D30: Lender exposure calc, Summary row 6 deduction
A31: Lender credit applied to default interest (June 2024 remittances) | B31: 8687.9 | C31: 8476.64 | D31: Lender exposure calc, Summary row 7 deduction
A32: Prior model v5 checkpoint 31/03/2026 - accrued interest | B32: 278999 | C32: 278342 | D32: GAEA_Dual_Loan_2030_v5, Inputs C26:D26
A33: Prior model v5 checkpoint 31/03/2026 - default interest | B33: 40985 | C33: 40867 | D33: GAEA_Dual_Loan_2030_v5, Inputs C27:D27
A34: JV books - interest payable, both loans combined | B34: 456652.95 | D34: 800SUPERGAEA_BS_LOAN SUMMARY_CF_SG_FD_13032026, cell M12
A35: JV books - penalty payable, both loans combined | B35: 63003.77 | D35: 800SUPERGAEA_BS_LOAN SUMMARY_CF_SG_FD_13032026, cell M14
A36: JV books - shareholder loan 800 Super WM Pte | B36: 1745676.8 | D36: BS summary D24 / JV GL entry 31/10/2024 'New Shareholder Loan'
A38: D. 6M Term SOFR fixings by interest period (sorted; VLOOKUP returns the fixing in force on each accrual day)
A39: rAGMF period start | B39: 6M SOFR | C39: All-in rate | D39: Fixing / source | F39: FHL period start | G39: 6M SOFR | H39: All-in rate | I39: Fixing / source
A40: 44813 | B40: =Cash_Events!F6*365/(B9*(Cash_Events!L6-B8))-B10 -> 0.034199997 | C40: =B40+$B$10 -> 0.1017 | D40: Implied from coupon 1 voucher (USD 75,648.08, 181 days) | F40: 44813 | G40: =Cash_Events!F7*365/(C9*(Cash_Events!L7-C8))-C10 -> 0.034199996 | H40: =G40+$C$10 -> 0.1017 | I40: Implied from coupon 1 voucher (USD 78,155.75, 187 days)
A41: 44994 | B41: 0.0521501 | C41: =B41+$B$10 -> 0.1196501 | D41: T-2 07/03/2023 - lender calc | F41: 45000 | G41: 0.0522223 | H41: =G41+$C$10 -> 0.1197223 | I41: T-2 13/03/2023 - lender calc
A42: 45180 | B42: 0.0547601 | C42: =B42+$B$10 -> 0.1222601 | D42: T-2 07/09/2023 - lender calc | F42: 45184 | G42: 0.054735 | H42: =G42+$C$10 -> 0.122235 | I42: T-2 13/09/2023 - lender calc
A43: 45362 | B43: 0.0523565 | C43: =B43+$B$10 -> 0.1198565 | D43: T-2 07/03/2024 - lender calc | F43: 45366 | G43: 0.0525075 | H43: =G43+$C$10 -> 0.1200075 | I43: T-2 13/03/2024 - lender calc
A44: 45544 | B44: 0.0461541 | C44: =B44+$B$10 -> 0.1136541 | D44: T-2 05/09/2024 - lender calc | F44: 45551 | G44: 0.0457048 | H44: =G44+$C$10 -> 0.1132048 | I44: T-2 12/09/2024 - lender calc
A45: 45726 | B45: 0.0419027 | C45: =B45+$B$10 -> 0.1094027 | D45: Lender calc | F45: 45733 | G45: 0.0420238 | H45: =G45+$C$10 -> 0.1095238 | I45: Lender calc
A46: 45909 | B46: 0.0396676 | C46: =B46+$B$10 -> 0.1071676 | D46: Lender calc | F46: 45915 | G46: 0.0386433 | H46: =G46+$C$10 -> 0.1061433 | I46: Lender calc
A47: 46090 | B47: 0.0363225 | C47: =B47+$B$10 -> 0.1038225 | D47: Lender calc | F47: 46097 | G47: 0.0364054 | H47: =G47+$C$10 -> 0.1039054 | I47: Lender calc
A48: 46274 | B48: =B47 -> 0.0363225 | C48: =B48+$B$10 -> 0.1038225 | D48: Not yet notified - held flat (lender's own projection basis). Update with rate-fixing notice | F48: 46280 | G48: =G47 -> 0.0364054 | H48: =G48+$C$10 -> 0.1039054 | I48: Not yet notified - held flat (lender's own projection basis). Update with rate-fixing notice

Sheet Cash_Events
A1: Cash Events & Lender Allocation
A2: All cash paid to the lenders since drawdown. Allocation per lender exposure calc Jun-26. Add any new payment in the yellow rows (allocation: enter principal and default portions; regular interest = balance).
A3: Entry format: Loan = rAGMF or FHL; Payer = JV or 800S. Example: 15/09/2026 | rAGMF | JV | Amendment instalment | 16,000.00 | 0.00 | (auto) | 0.00
A5: # | B5: Value date | C5: Loan | D5: Payer | E5: Description | F5: Cash amount (USD) | G5: Principal | H5: Regular interest | I5: Default interest | J5: Check | K5: Bank ref / source | L5: Accrual cover end | M5: Month bucket
A6: 1 | B6: 44992 | C6: rAGMF | D6: JV | E6: Coupon 1 (09/09/2022-09/03/2023) | F6: 75648.08 | G6: 0 | H6: =F6-G6-I6 -> 75648.08 | I6: 0 | J6: =ROUND(F6-G6-H6-I6,2) -> 0 | K6: PV #10, 07-Mar-23, bank transfer USD | L6: 44994 | M6: =IF(B6="","",EOMONTH(B6,0)) -> 45016
A7: 2 | B7: 44992 | C7: FHL | D7: JV | E7: Coupon 1 (09/09/2022-15/03/2023) | F7: 78155.75 | G7: 0 | H7: =F7-G7-I7 -> 78155.75 | I7: 0 | J7: =ROUND(F7-G7-H7-I7,2) -> 0 | K7: PV #12, 07-Mar-23, bank transfer USD | L7: 45000 | M7: =IF(B7="","",EOMONTH(B7,0)) -> 45016
A8: 3 | B8: 45456 | C8: rAGMF | D8: 800S | E8: Accrued and defaulted interest payment (800 Super WM Pte, OCBC SGD a/c) | F8: 108002.4 | G8: 0 | H8: =F8-G8-I8 -> 99314.5 | I8: =Inputs!B31 -> 8687.9 | J8: =ROUND(F8-G8-H8-I8,2) -> 0 | K8: OCBC TT created 12/06/2024, value 13/06/2024 | M8: =IF(B8="","",EOMONTH(B8,0)) -> 45473
A9: 4 | B9: 45456 | C9: FHL | D9: 800S | E9: Accrued and defaulted interest payment (800 Super WM Pte, OCBC SGD a/c) | F9: 107674.43 | G9: 0 | H9: =F9-G9-I9 -> 99197.79 | I9: =Inputs!C31 -> 8476.64 | J9: =ROUND(F9-G9-H9-I9,2) -> 0 | K9: OCBC TT created 12/06/2024, value 13/06/2024 | M9: =IF(B9="","",EOMONTH(B9,0)) -> 45473
A10: 5 | B10: 45471 | C10: rAGMF | D10: 800S | E10: Principal repayment 51% (guarantor payment); USD 1,163.29 above USD 765,000 applied to interest | F10: 766163.29 | G10: 765000 | H10: =F10-G10-I10 -> 1163.29 | I10: 0 | J10: =ROUND(F10-G10-H10-I10,2) -> 0 | K10: UOB FT24060327092395, value 28/06/2024 | M10: =IF(B10="","",EOMONTH(B10,0)) -> 45473
A11: 6 | B11: 45471 | C11: FHL | D11: 800S | E11: Principal repayment 51% (guarantor payment); USD 1,163.29 shortfall vs USD 765,000 met from interest remittance | F11: 763836.71 | G11: 765000 | H11: =F11-G11-I11 -> -1163.29 | I11: 0 | J11: =ROUND(F11-G11-H11-I11,2) -> 0 | K11: UOB FT24060327079586, value 28/06/2024 | M11: =IF(B11="","",EOMONTH(B11,0)) -> 45473
A12: 7 | H12: =IF(F12="",0,F12-G12-I12) -> 0 | J12: =IF(F12="",0,ROUND(F12-G12-H12-I12,2)) -> 0 | M12: =IF(B12="","",EOMONTH(B12,0))
A13: 8 | H13: =IF(F13="",0,F13-G13-I13) -> 0 | J13: =IF(F13="",0,ROUND(F13-G13-H13-I13,2)) -> 0 | M13: =IF(B13="","",EOMONTH(B13,0))
A14: 9 | H14: =IF(F14="",0,F14-G14-I14) -> 0 | J14: =IF(F14="",0,ROUND(F14-G14-H14-I14,2)) -> 0 | M14: =IF(B14="","",EOMONTH(B14,0))
A15: 10 | H15: =IF(F15="",0,F15-G15-I15) -> 0 | J15: =IF(F15="",0,ROUND(F15-G15-H15-I15,2)) -> 0 | M15: =IF(B15="","",EOMONTH(B15,0))
A16: 11 | H16: =IF(F16="",0,F16-G16-I16) -> 0 | J16: =IF(F16="",0,ROUND(F16-G16-H16-I16,2)) -> 0 | M16: =IF(B16="","",EOMONTH(B16,0))
A17: 12 | H17: =IF(F17="",0,F17-G17-I17) -> 0 | J17: =IF(F17="",0,ROUND(F17-G17-H17-I17,2)) -> 0 | M17: =IF(B17="","",EOMONTH(B17,0))
A18: 13 | H18: =IF(F18="",0,F18-G18-I18) -> 0 | J18: =IF(F18="",0,ROUND(F18-G18-H18-I18,2)) -> 0 | M18: =IF(B18="","",EOMONTH(B18,0))
A19: 14 | H19: =IF(F19="",0,F19-G19-I19) -> 0 | J19: =IF(F19="",0,ROUND(F19-G19-H19-I19,2)) -> 0 | M19: =IF(B19="","",EOMONTH(B19,0))
A20: 15 | H20: =IF(F20="",0,F20-G20-I20) -> 0 | J20: =IF(F20="",0,ROUND(F20-G20-H20-I20,2)) -> 0 | M20: =IF(B20="","",EOMONTH(B20,0))
A22: Total | F22: =SUM(F6:F20) -> 1899480.7 | G22: =SUM(G6:G20) -> 1530000 | H22: =SUM(H6:H20) -> 352316.12 | I22: =SUM(I6:I20) -> 17164.54 | J22: =SUM(J6:J20) -> 0
A24: Summary by payer
B25: Payer | C25: Loan | F25: Cash | G25: Principal | H25: Regular interest | I25: Default interest | J25: Interest total
B26: JV | C26: rAGMF | F26: =SUMIFS(F$6:F$20,$D$6:$D$20,$B26,$C$6:$C$20,$C26) -> 75648.08 | G26: =SUMIFS(G$6:G$20,$D$6:$D$20,$B26,$C$6:$C$20,$C26) -> 0 | H26: =SUMIFS(H$6:H$20,$D$6:$D$20,$B26,$C$6:$C$20,$C26) -> 75648.08 | I26: =SUMIFS(I$6:I$20,$D$6:$D$20,$B26,$C$6:$C$20,$C26) -> 0 | J26: =H26+I26 -> 75648.08
B27: JV | C27: FHL | F27: =SUMIFS(F$6:F$20,$D$6:$D$20,$B27,$C$6:$C$20,$C27) -> 78155.75 | G27: =SUMIFS(G$6:G$20,$D$6:$D$20,$B27,$C$6:$C$20,$C27) -> 0 | H27: =SUMIFS(H$6:H$20,$D$6:$D$20,$B27,$C$6:$C$20,$C27) -> 78155.75 | I27: =SUMIFS(I$6:I$20,$D$6:$D$20,$B27,$C$6:$C$20,$C27) -> 0 | J27: =H27+I27 -> 78155.75
B28: 800S | C28: rAGMF | F28: =SUMIFS(F$6:F$20,$D$6:$D$20,$B28,$C$6:$C$20,$C28) -> 874165.69 | G28: =SUMIFS(G$6:G$20,$D$6:$D$20,$B28,$C$6:$C$20,$C28) -> 765000 | H28: =SUMIFS(H$6:H$20,$D$6:$D$20,$B28,$C$6:$C$20,$C28) -> 100477.79 | I28: =SUMIFS(I$6:I$20,$D$6:$D$20,$B28,$C$6:$C$20,$C28) -> 8687.9 | J28: =H28+I28 -> 109165.69
B29: 800S | C29: FHL | F29: =SUMIFS(F$6:F$20,$D$6:$D$20,$B29,$C$6:$C$20,$C29) -> 871511.14 | G29: =SUMIFS(G$6:G$20,$D$6:$D$20,$B29,$C$6:$C$20,$C29) -> 765000 | H29: =SUMIFS(H$6:H$20,$D$6:$D$20,$B29,$C$6:$C$20,$C29) -> 98034.5 | I29: =SUMIFS(I$6:I$20,$D$6:$D$20,$B29,$C$6:$C$20,$C29) -> 8476.64 | J29: =H29+I29 -> 106511.14
B30: Total | F30: =SUM(F26:F29) -> 1899480.7 | G30: =SUM(G26:G29) -> 1530000 | H30: =SUM(H26:H29) -> 352316.12 | I30: =SUM(I26:I29) -> 17164.54 | J30: =SUM(J26:J29) -> 369480.66

Sheet Daily
A1: Daily Accrual Engine
A2: One row per accrual day (interest for day d accrues from d to d+1). Month bucket = month-end boundary convention used by the lender (e.g. 'to 30/06/2026' excludes 30 June).
A5: Accrual day | B5: Month bucket | C5: Year basis | D5: rAGMF principal | E5: rAGMF 6M SOFR | F5: rAGMF all-in | G5: rAGMF regular interest | H5: rAGMF default interest | I5: FHL principal | J5: FHL 6M SOFR | K5: FHL all-in | L5: FHL regular interest | M5: FHL default interest
A6: =Inputs!B8 -> 44813 | B6: =EOMONTH(A6+1,0) -> 44834 | C6: =IF(MOD(YEAR(A6),4)=0,366,365) -> 365 | D6: =Inputs!$B$9-SUMIFS(Cash_Events!$G$6:$G$20,Cash_Events!$C$6:$C$20,"rAGMF",Cash_Events!$B$6:$B$20,"<="&A6) -> 1500000 | E6: =VLOOKUP(A6,Inputs!$A$40:$B$48,2,TRUE()) -> 0.034199997 | F6: =E6+Inputs!$B$10 -> 0.1017 | G6: =D6*F6/C6 -> 417.94519 | H6: =IF(AND(A6>=Inputs!$B$13,OR(A6<Inputs!$B$19,Inputs!$B$20=1)),D6*Inputs!$B$11/C6,0) -> 0 | I6: =Inputs!$C$9-SUMIFS(Cash_Events!$G$6:$G$20,Cash_Events!$C$6:$C$20,"FHL",Cash_Events!$B$6:$B$20,"<="&A6) -> 1500000 | J6: =VLOOKUP(A6,Inputs!$F$40:$G$48,2,TRUE()) -> 0.034199996 | K6: =J6+Inputs!$C$10 -> 0.1017 | L6: =I6*K6/C6 -> 417.94519 | M6: =IF(AND(A6>=Inputs!$C$13,OR(A6<Inputs!$B$19,Inputs!$B$20=1)),I6*Inputs!$C$11/C6,0) -> 0
A7: =A6+1 -> 44814 | B7: =EOMONTH(A7+1,0) -> 44834 | C7: =IF(MOD(YEAR(A7),4)=0,366,365) -> 365 | D7: =Inputs!$B$9-SUMIFS(Cash_Events!$G$6:$G$20,Cash_Events!$C$6:$C$20,"rAGMF",Cash_Events!$B$6:$B$20,"<="&A7) -> 1500000 | E7: =VLOOKUP(A7,Inputs!$A$40:$B$48,2,TRUE()) -> 0.034199997 | F7: =E7+Inputs!$B$10 -> 0.1017 | G7: =D7*F7/C7 -> 417.94519 | H7: =IF(AND(A7>=Inputs!$B$13,OR(A7<Inputs!$B$19,Inputs!$B$20=1)),D7*Inputs!$B$11/C7,0) -> 0 | I7: =Inputs!$C$9-SUMIFS(Cash_Events!$G$6:$G$20,Cash_Events!$C$6:$C$20,"FHL",Cash_Events!$B$6:$B$20,"<="&A7) -> 1500000 | J7: =VLOOKUP(A7,Inputs!$F$40:$G$48,2,TRUE()) -> 0.034199996 | K7: =J7+Inputs!$C$10 -> 0.1017 | L7: =I7*K7/C7 -> 417.94519 | M7: =IF(AND(A7>=Inputs!$C$13,OR(A7<Inputs!$B$19,Inputs!$B$20=1)),I7*Inputs!$C$11/C7,0) -> 0
A8: =A7+1 -> 44815 | B8: =EOMONTH(A8+1,0) -> 44834 | C8: =IF(MOD(YEAR(A8),4)=0,366,365) -> 365 | D8: =Inputs!$B$9-SUMIFS(Cash_Events!$G$6:$G$20,Cash_Events!$C$6:$C$20,"rAGMF",Cash_Events!$B$6:$B$20,"<="&A8) -> 1500000 | E8: =VLOOKUP(A8,Inputs!$A$40:$B$48,2,TRUE()) -> 0.034199997 | F8: =E8+Inputs!$B$10 -> 0.1017 | G8: =D8*F8/C8 -> 417.94519 | H8: =IF(AND(A8>=Inputs!$B$13,OR(A8<Inputs!$B$19,Inputs!$B$20=1)),D8*Inputs!$B$11/C8,0) -> 0 | I8: =Inputs!$C$9-SUMIFS(Cash_Events!$G$6:$G$20,Cash_Events!$C$6:$C$20,"FHL",Cash_Events!$B$6:$B$20,"<="&A8) -> 1500000 | J8: =VLOOKUP(A8,Inputs!$F$40:$G$48,2,TRUE()) -> 0.034199996 | K8: =J8+Inputs!$C$10 -> 0.1017 | L8: =I8*K8/C8 -> 417.94519 | M8: =IF(AND(A8>=Inputs!$C$13,OR(A8<Inputs!$B$19,Inputs!$B$20=1)),I8*Inputs!$C$11/C8,0) -> 0
A9: =A8+1 -> 44816 | B9: =EOMONTH(A9+1,0) -> 44834 | C9: =IF(MOD(YEAR(A9),4)=0,366,365) -> 365 | D9: =Inputs!$B$9-SUMIFS(Cash_Events!$G$6:$G$20,Cash_Events!$C$6:$C$20,"rAGMF",Cash_Events!$B$6:$B$20,"<="&A9) -> 1500000 | E9: =VLOOKUP(A9,Inputs!$A$40:$B$48,2,TRUE()) -> 0.034199997 | F9: =E9+Inputs!$B$10 -> 0.1017 | G9: =D9*F9/C9 -> 417.94519 | H9: =IF(AND(A9>=Inputs!$B$13,OR(A9<Inputs!$B$19,Inputs!$B$20=1)),D9*Inputs!$B$11/C9,0) -> 0 | I9: =Inputs!$C$9-SUMIFS(Cash_Events!$G$6:$G$20,Cash_Events!$C$6:$C$20,"FHL",Cash_Events!$B$6:$B$20,"<="&A9) -> 1500000 | J9: =VLOOKUP(A9,Inputs!$F$40:$G$48,2,TRUE()) -> 0.034199996 | K9: =J9+Inputs!$C$10 -> 0.1017 | L9: =I9*K9/C9 -> 417.94519 | M9: =IF(AND(A9>=Inputs!$C$13,OR(A9<Inputs!$B$19,Inputs!$B$20=1)),I9*Inputs!$C$11/C9,0) -> 0
A10: =A9+1 -> 44817 | B10: =EOMONTH(A10+1,0) -> 44834 | C10: =IF(MOD(YEAR(A10),4)=0,366,365) -> 365 | D10: =Inputs!$B$9-SUMIFS(Cash_Events!$G$6:$G$20,Cash_Events!$C$6:$C$20,"rAGMF",Cash_Events!$B$6:$B$20,"<="&A10) -> 1500000 | E10: =VLOOKUP(A10,Inputs!$A$40:$B$48,2,TRUE()) -> 0.034199997 | F10: =E10+Inputs!$B$10 -> 0.1017 | G10: =D10*F10/C10 -> 417.94519 | H10: =IF(AND(A10>=Inputs!$B$13,OR(A10<Inputs!$B$19,Inputs!$B$20=1)),D10*Inputs!$B$11/C10,0) -> 0 | I10: =Inputs!$C$9-SUMIFS(Cash_Events!$G$6:$G$20,Cash_Events!$C$6:$C$20,"FHL",Cash_Events!$B$6:$B$20,"<="&A10) -> 1500000 | J10: =VLOOKUP(A10,Inputs!$F$40:$G$48,2,TRUE()) -> 0.034199996 | K10: =J10+Inputs!$C$10 -> 0.1017 | L10: =I10*K10/C10 -> 417.94519 | M10: =IF(AND(A10>=Inputs!$C$13,OR(A10<Inputs!$B$19,Inputs!$B$20=1)),I10*Inputs!$C$11/C10,0) -> 0
A11: =A10+1 -> 44818 | B11: =EOMONTH(A11+1,0) -> 44834 | C11: =IF(MOD(YEAR(A11),4)=0,366,365) -> 365 | D11: =Inputs!$B$9-SUMIFS(Cash_Events!$G$6:$G$20,Cash_Events!$C$6:$C$20,"rAGMF",Cash_Events!$B$6:$B$20,"<="&A11) -> 1500000 | E11: =VLOOKUP(A11,Inputs!$A$40:$B$48,2,TRUE()) -> 0.034199997 | F11: =E11+Inputs!$B$10 -> 0.1017 | G11: =D11*F11/C11 -> 417.94519 | H11: =IF(AND(A11>=Inputs!$B$13,OR(A11<Inputs!$B$19,Inputs!$B$20=1)),D11*Inputs!$B$11/C11,0) -> 0 | I11: =Inputs!$C$9-SUMIFS(Cash_Events!$G$6:$G$20,Cash_Events!$C$6:$C$20,"FHL",Cash_Events!$B$6:$B$20,"<="&A11) -> 1500000 | J11: =VLOOKUP(A11,Inputs!$F$40:$G$48,2,TRUE()) -> 0.034199996 | K11: =J11+Inputs!$C$10 -> 0.1017 | L11: =I11*K11/C11 -> 417.94519 | M11: =IF(AND(A11>=Inputs!$C$13,OR(A11<Inputs!$B$19,Inputs!$B$20=1)),I11*Inputs!$C$11/C11,0) -> 0
A12: =A11+1 -> 44819 | B12: =EOMONTH(A12+1,0) -> 44834 | C12: =IF(MOD(YEAR(A12),4)=0,366,365) -> 365 | D12: =Inputs!$B$9-SUMIFS(Cash_Events!$G$6:$G$20,Cash_Events!$C$6:$C$20,"rAGMF",Cash_Events!$B$6:$B$20,"<="&A12) -> 1500000 | E12: =VLOOKUP(A12,Inputs!$A$40:$B$48,2,TRUE()) -> 0.034199997 | F12: =E12+Inputs!$B$10 -> 0.1017 | G12: =D12*F12/C12 -> 417.94519 | H12: =IF(AND(A12>=Inputs!$B$13,OR(A12<Inputs!$B$19,Inputs!$B$20=1)),D12*Inputs!$B$11/C12,0) -> 0 | I12: =Inputs!$C$9-SUMIFS(Cash_Events!$G$6:$G$20,Cash_Events!$C$6:$C$20,"FHL",Cash_Events!$B$6:$B$20,"<="&A12) -> 1500000 | J12: =VLOOKUP(A12,Inputs!$F$40:$G$48,2,TRUE()) -> 0.034199996 | K12: =J12+Inputs!$C$10 -> 0.1017 | L12: =I12*K12/C12 -> 417.94519 | M12: =IF(AND(A12>=Inputs!$C$13,OR(A12<Inputs!$B$19,Inputs!$B$20=1)),I12*Inputs!$C$11/C12,0) -> 0
A13: =A12+1 -> 44820 | B13: =EOMONTH(A13+1,0) -> 44834 | C13: =IF(MOD(YEAR(A13),4)=0,366,365) -> 365 | D13: =Inputs!$B$9-SUMIFS(Cash_Events!$G$6:$G$20,Cash_Events!$C$6:$C$20,"rAGMF",Cash_Events!$B$6:$B$20,"<="&A13) -> 1500000 | E13: =VLOOKUP(A13,Inputs!$A$40:$B$48,2,TRUE()) -> 0.034199997 | F13: =E13+Inputs!$B$10 -> 0.1017 | G13: =D13*F13/C13 -> 417.94519 | H13: =IF(AND(A13>=Inputs!$B$13,OR(A13<Inputs!$B$19,Inputs!$B$20=1)),D13*Inputs!$B$11/C13,0) -> 0 | I13: =Inputs!$C$9-SUMIFS(Cash_Events!$G$6:$G$20,Cash_Events!$C$6:$C$20,"FHL",Cash_Events!$B$6:$B$20,"<="&A13) -> 1500000 | J13: =VLOOKUP(A13,Inputs!$F$40:$G$48,2,TRUE()) -> 0.034199996 | K13: =J13+Inputs!$C$10 -> 0.1017 | L13: =I13*K13/C13 -> 417.94519 | M13: =IF(AND(A13>=Inputs!$C$13,OR(A13<Inputs!$B$19,Inputs!$B$20=1)),I13*Inputs!$C$11/C13,0) -> 0
A14: =A13+1 -> 44821 | B14: =EOMONTH(A14+1,0) -> 44834 | C14: =IF(MOD(YEAR(A14),4)=0,366,365) -> 365 | D14: =Inputs!$B$9-SUMIFS(Cash_Events!$G$6:$G$20,Cash_Events!$C$6:$C$20,"rAGMF",Cash_Events!$B$6:$B$20,"<="&A14) -> 1500000 | E14: =VLOOKUP(A14,Inputs!$A$40:$B$48,2,TRUE()) -> 0.034199997 | F14: =E14+Inputs!$B$10 -> 0.1017 | G14: =D14*F14/C14 -> 417.94519 | H14: =IF(AND(A14>=Inputs!$B$13,OR(A14<Inputs!$B$19,Inputs!$B$20=1)),D14*Inputs!$B$11/C14,0) -> 0 | I14: =Inputs!$C$9-SUMIFS(Cash_Events!$G$6:$G$20,Cash_Events!$C$6:$C$20,"FHL",Cash_Events!$B$6:$B$20,"<="&A14) -> 1500000 | J14: =VLOOKUP(A14,Inputs!$F$40:$G$48,2,TRUE()) -> 0.034199996 | K14: =J14+Inputs!$C$10 -> 0.1017 | L14: =I14*K14/C14 -> 417.94519 | M14: =IF(AND(A14>=Inputs!$C$13,OR(A14<Inputs!$B$19,Inputs!$B$20=1)),I14*Inputs!$C$11/C14,0) -> 0
A15: =A14+1 -> 44822 | B15: =EOMONTH(A15+1,0) -> 44834 | C15: =IF(MOD(YEAR(A15),4)=0,366,365) -> 365 | D15: =Inputs!$B$9-SUMIFS(Cash_Events!$G$6:$G$20,Cash_Events!$C$6:$C$20,"rAGMF",Cash_Events!$B$6:$B$20,"<="&A15) -> 1500000 | E15: =VLOOKUP(A15,Inputs!$A$40:$B$48,2,TRUE()) -> 0.034199997 | F15: =E15+Inputs!$B$10 -> 0.1017 | G15: =D15*F15/C15 -> 417.94519 | H15: =IF(AND(A15>=Inputs!$B$13,OR(A15<Inputs!$B$19,Inputs!$B$20=1)),D15*Inputs!$B$11/C15,0) -> 0 | I15: =Inputs!$C$9-SUMIFS(Cash_Events!$G$6:$G$20,Cash_Events!$C$6:$C$20,"FHL",Cash_Events!$B$6:$B$20,"<="&A15) -> 1500000 | J15: =VLOOKUP(A15,Inputs!$F$40:$G$48,2,TRUE()) -> 0.034199996 | K15: =J15+Inputs!$C$10 -> 0.1017 | L15: =I15*K15/C15 -> 417.94519 | M15: =IF(AND(A15>=Inputs!$C$13,OR(A15<Inputs!$B$19,Inputs!$B$20=1)),I15*Inputs!$C$11/C15,0) -> 0
A16: =A15+1 -> 44823 | B16: =EOMONTH(A16+1,0) -> 44834 | C16: =IF(MOD(YEAR(A16),4)=0,366,365) -> 365 | D16: =Inputs!$B$9-SUMIFS(Cash_Events!$G$6:$G$20,Cash_Events!$C$6:$C$20,"rAGMF",Cash_Events!$B$6:$B$20,"<="&A16) -> 1500000 | E16: =VLOOKUP(A16,Inputs!$A$40:$B$48,2,TRUE()) -> 0.034199997 | F16: =E16+Inputs!$B$10 -> 0.1017 | G16: =D16*F16/C16 -> 417.94519 | H16: =IF(AND(A16>=Inputs!$B$13,OR(A16<Inputs!$B$19,Inputs!$B$20=1)),D16*Inputs!$B$11/C16,0) -> 0 | I16: =Inputs!$C$9-SUMIFS(Cash_Events!$G$6:$G$20,Cash_Events!$C$6:$C$20,"FHL",Cash_Events!$B$6:$B$20,"<="&A16) -> 1500000 | J16: =VLOOKUP(A16,Inputs!$F$40:$G$48,2,TRUE()) -> 0.034199996 | K16: =J16+Inputs!$C$10 -> 0.1017 | L16: =I16*K16/C16 -> 417.94519 | M16: =IF(AND(A16>=Inputs!$C$13,OR(A16<Inputs!$B$19,Inputs!$B$20=1)),I16*Inputs!$C$11/C16,0) -> 0
A17: =A16+1 -> 44824 | B17: =EOMONTH(A17+1,0) -> 44834 | C17: =IF(MOD(YEAR(A17),4)=0,366,365) -> 365 | D17: =Inputs!$B$9-SUMIFS(Cash_Events!$G$6:$G$20,Cash_Events!$C$6:$C$20,"rAGMF",Cash_Events!$B$6:$B$20,"<="&A17) -> 1500000 | E17: =VLOOKUP(A17,Inputs!$A$40:$B$48,2,TRUE()) -> 0.034199997 | F17: =E17+Inputs!$B$10 -> 0.1017 | G17: =D17*F17/C17 -> 417.94519 | H17: =IF(AND(A17>=Inputs!$B$13,OR(A17<Inputs!$B$19,Inputs!$B$20=1)),D17*Inputs!$B$11/C17,0) -> 0 | I17: =Inputs!$C$9-SUMIFS(Cash_Events!$G$6:$G$20,Cash_Events!$C$6:$C$20,"FHL",Cash_Events!$B$6:$B$20,"<="&A17) -> 1500000 | J17: =VLOOKUP(A17,Inputs!$F$40:$G$48,2,TRUE()) -> 0.034199996 | K17: =J17+Inputs!$C$10 -> 0.1017 | L17: =I17*K17/C17 -> 417.94519 | M17: =IF(AND(A17>=Inputs!$C$13,OR(A17<Inputs!$B$19,Inputs!$B$20=1)),I17*Inputs!$C$11/C17,0) -> 0
A18: =A17+1 -> 44825 | B18: =EOMONTH(A18+1,0) -> 44834 | C18: =IF(MOD(YEAR(A18),4)=0,366,365) -> 365 | D18: =Inputs!$B$9-SUMIFS(Cash_Events!$G$6:$G$20,Cash_Events!$C$6:$C$20,"rAGMF",Cash_Events!$B$6:$B$20,"<="&A18) -> 1500000 | E18: =VLOOKUP(A18,Inputs!$A$40:$B$48,2,TRUE()) -> 0.034199997 | F18: =E18+Inputs!$B$10 -> 0.1017 | G18: =D18*F18/C18 -> 417.94519 | H18: =IF(AND(A18>=Inputs!$B$13,OR(A18<Inputs!$B$19,Inputs!$B$20=1)),D18*Inputs!$B$11/C18,0) -> 0 | I18: =Inputs!$C$9-SUMIFS(Cash_Events!$G$6:$G$20,Cash_Events!$C$6:$C$20,"FHL",Cash_Events!$B$6:$B$20,"<="&A18) -> 1500000 | J18: =VLOOKUP(A18,Inputs!$F$40:$G$48,2,TRUE()) -> 0.034199996 | K18: =J18+Inputs!$C$10 -> 0.1017 | L18: =I18*K18/C18 -> 417.94519 | M18: =IF(AND(A18>=Inputs!$C$13,OR(A18<Inputs!$B$19,Inputs!$B$20=1)),I18*Inputs!$C$11/C18,0) -> 0
... A2400: =A2399+1 -> 47207 | B2400: =EOMONTH(A2400+1,0) -> 47208 | C2400: =IF(MOD(YEAR(A2400),4)=0,366,365) -> 365 | D2400: =Inputs!$B$9-SUMIFS(Cash_Events!$G$6:$G$20,Cash_Events!$C$6:$C$20,"rAGMF",Cash_Events!$B$6:$B$20,"<="&A2400) -> 735000 | E2400: =VLOOKUP(A2400,Inputs!$A$40:$B$48,2,TRUE()) -> 0.0363225 | F2400: =E2400+Inputs!$B$10 -> 0.1038225 | G2400: =D2400*F2400/C2400 -> 209.06723 | H2400: =IF(AND(A2400>=Inputs!$B$13,OR(A2400<Inputs!$B$19,Inputs!$B$20=1)),D2400*Inputs!$B$11/C2400,0) -> 40.273973 | I2400: =Inputs!$C$9-SUMIFS(Cash_Events!$G$6:$G$20,Cash_Events!$C$6:$C$20,"FHL",Cash_Events!$B$6:$B$20,"<="&A2400) -> 735000 | J2400: =VLOOKUP(A2400,Inputs!$F$40:$G$48,2,TRUE()) -> 0.0364054 | K2400: =J2400+Inputs!$C$10 -> 0.1039054 | L2400: =I2400*K2400/C2400 -> 209.23416 | M2400: =IF(AND(A2400>=Inputs!$C$13,OR(A2400<Inputs!$B$19,Inputs!$B$20=1)),I2400*Inputs!$C$11/C2400,0) -> 40.273973

Sheet rAGMF_Monthly
A1: rAGMF - Monthly Loan Life (drawdown 09/09/2022 to 31/03/2029)
A2: Actual = reconstructed to last month-end before reporting date; Projection = no further payments, lender method. Interest payable = lender's view of overdue amounts.
A4: Lender: | B4: =Inputs!B6 -> responsAbility Global Micro & SME Finance Fund (M&G Luxembourg S.A.)
A5: Shaded rows = projection. Blue band = lender cut-off 30/06/2026.
A6: Month end | B6: Accrual from | C6: Days | D6: Status | E6: Opening principal | F6: Principal repaid | G6: Closing principal | H6: 6M SOFR (period end) | I6: All-in rate | J6: Regular interest accrued | K6: Default interest accrued | L6: Total interest charge | M6: Opening regular interest payable | N6: Regular paid by JV | O6: Regular paid by 800S | P6: Closing regular interest payable | Q6: Opening default payable | R6: Default paid | S6: Closing default payable | T6: TOTAL INTEREST PAYABLE | U6: TOTAL EXPOSURE (principal + interest) | V6: Cumulative interest charged | W6: Cumulative interest paid | X6: Check (=0) | Y6: Events
A7: 44834 | B7: =Inputs!B8 -> 44813 | C7: =A7-B7 -> 21 | D7: =IF(A7<=EOMONTH(Inputs!$B$18,-1),"Actual","Projection") -> Actual | E7: =Inputs!B9 -> 1500000 | F7: =SUMIFS(Cash_Events!$G$6:$G$20,Cash_Events!$C$6:$C$20,"rAGMF",Cash_Events!$M$6:$M$20,A7) -> 0 | G7: =E7-F7 -> 1500000 | H7: =VLOOKUP(A7-1,Inputs!$A$40:$B$48,2,TRUE()) -> 0.034199997 | I7: =H7+Inputs!B10 -> 0.1017 | J7: =SUMIFS(Daily!$G$6:$G$2400,Daily!$B$6:$B$2400,A7) -> 8776.8491 | K7: =SUMIFS(Daily!$H$6:$H$2400,Daily!$B$6:$B$2400,A7) -> 0 | L7: =J7+K7 -> 8776.8491 | M7: 0 | N7: =SUMIFS(Cash_Events!$H$6:$H$20,Cash_Events!$C$6:$C$20,"rAGMF",Cash_Events!$D$6:$D$20,"JV",Cash_Events!$M$6:$M$20,A7) -> 0 | O7: =SUMIFS(Cash_Events!$H$6:$H$20,Cash_Events!$C$6:$C$20,"rAGMF",Cash_Events!$D$6:$D$20,"800S",Cash_Events!$M$6:$M$20,A7) -> 0 | P7: =M7+J7-N7-O7 -> 8776.8491 | Q7: 0 | R7: =SUMIFS(Cash_Events!$I$6:$I$20,Cash_Events!$C$6:$C$20,"rAGMF",Cash_Events!$M$6:$M$20,A7) -> 0 | S7: =Q7+K7-R7 -> 0 | T7: =P7+S7 -> 8776.8491 | U7: =G7+T7 -> 1508776.8 | V7: =L7 -> 8776.8491 | W7: =N7+O7+R7 -> 0 | X7: =ROUND(V7-W7-T7,2) -> 0 | Y7: Drawdown 09/09/2022
A8: =EOMONTH(A7,1) -> 44865 | B8: =A7 -> 44834 | C8: =A8-B8 -> 31 | D8: =IF(A8<=EOMONTH(Inputs!$B$18,-1),"Actual","Projection") -> Actual | E8: =G7 -> 1500000 | F8: =SUMIFS(Cash_Events!$G$6:$G$20,Cash_Events!$C$6:$C$20,"rAGMF",Cash_Events!$M$6:$M$20,A8) -> 0 | G8: =E8-F8 -> 1500000 | H8: =VLOOKUP(A8-1,Inputs!$A$40:$B$48,2,TRUE()) -> 0.034199997 | I8: =H8+Inputs!B10 -> 0.1017 | J8: =SUMIFS(Daily!$G$6:$G$2400,Daily!$B$6:$B$2400,A8) -> 12956.301 | K8: =SUMIFS(Daily!$H$6:$H$2400,Daily!$B$6:$B$2400,A8) -> 0 | L8: =J8+K8 -> 12956.301 | M8: =P7 -> 8776.8491 | N8: =SUMIFS(Cash_Events!$H$6:$H$20,Cash_Events!$C$6:$C$20,"rAGMF",Cash_Events!$D$6:$D$20,"JV",Cash_Events!$M$6:$M$20,A8) -> 0 | O8: =SUMIFS(Cash_Events!$H$6:$H$20,Cash_Events!$C$6:$C$20,"rAGMF",Cash_Events!$D$6:$D$20,"800S",Cash_Events!$M$6:$M$20,A8) -> 0 | P8: =M8+J8-N8-O8 -> 21733.15 | Q8: =S7 -> 0 | R8: =SUMIFS(Cash_Events!$I$6:$I$20,Cash_Events!$C$6:$C$20,"rAGMF",Cash_Events!$M$6:$M$20,A8) -> 0 | S8: =Q8+K8-R8 -> 0 | T8: =P8+S8 -> 21733.15 | U8: =G8+T8 -> 1521733.2 | V8: =V7+L8 -> 21733.15 | W8: =W7+N8+O8+R8 -> 0 | X8: =ROUND(V8-W8-T8,2) -> 0
A9: =EOMONTH(A8,1) -> 44895 | B9: =A8 -> 44865 | C9: =A9-B9 -> 30 | D9: =IF(A9<=EOMONTH(Inputs!$B$18,-1),"Actual","Projection") -> Actual | E9: =G8 -> 1500000 | F9: =SUMIFS(Cash_Events!$G$6:$G$20,Cash_Events!$C$6:$C$20,"rAGMF",Cash_Events!$M$6:$M$20,A9) -> 0 | G9: =E9-F9 -> 1500000 | H9: =VLOOKUP(A9-1,Inputs!$A$40:$B$48,2,TRUE()) -> 0.034199997 | I9: =H9+Inputs!B10 -> 0.1017 | J9: =SUMIFS(Daily!$G$6:$G$2400,Daily!$B$6:$B$2400,A9) -> 12538.356 | K9: =SUMIFS(Daily!$H$6:$H$2400,Daily!$B$6:$B$2400,A9) -> 0 | L9: =J9+K9 -> 12538.356 | M9: =P8 -> 21733.15 | N9: =SUMIFS(Cash_Events!$H$6:$H$20,Cash_Events!$C$6:$C$20,"rAGMF",Cash_Events!$D$6:$D$20,"JV",Cash_Events!$M$6:$M$20,A9) -> 0 | O9: =SUMIFS(Cash_Events!$H$6:$H$20,Cash_Events!$C$6:$C$20,"rAGMF",Cash_Events!$D$6:$D$20,"800S",Cash_Events!$M$6:$M$20,A9) -> 0 | P9: =M9+J9-N9-O9 -> 34271.506 | Q9: =S8 -> 0 | R9: =SUMIFS(Cash_Events!$I$6:$I$20,Cash_Events!$C$6:$C$20,"rAGMF",Cash_Events!$M$6:$M$20,A9) -> 0 | S9: =Q9+K9-R9 -> 0 | T9: =P9+S9 -> 34271.506 | U9: =G9+T9 -> 1534271.5 | V9: =V8+L9 -> 34271.506 | W9: =W8+N9+O9+R9 -> 0 | X9: =ROUND(V9-W9-T9,2) -> 0
A10: =EOMONTH(A9,1) -> 44926 | B10: =A9 -> 44895 | C10: =A10-B10 -> 31 | D10: =IF(A10<=EOMONTH(Inputs!$B$18,-1),"Actual","Projection") -> Actual | E10: =G9 -> 1500000 | F10: =SUMIFS(Cash_Events!$G$6:$G$20,Cash_Events!$C$6:$C$20,"rAGMF",Cash_Events!$M$6:$M$20,A10) -> 0 | G10: =E10-F10 -> 1500000 | H10: =VLOOKUP(A10-1,Inputs!$A$40:$B$48,2,TRUE()) -> 0.034199997 | I10: =H10+Inputs!B10 -> 0.1017 | J10: =SUMIFS(Daily!$G$6:$G$2400,Daily!$B$6:$B$2400,A10) -> 12956.301 | K10: =SUMIFS(Daily!$H$6:$H$2400,Daily!$B$6:$B$2400,A10) -> 0 | L10: =J10+K10 -> 12956.301 | M10: =P9 -> 34271.506 | N10: =SUMIFS(Cash_Events!$H$6:$H$20,Cash_Events!$C$6:$C$20,"rAGMF",Cash_Events!$D$6:$D$20,"JV",Cash_Events!$M$6:$M$20,A10) -> 0 | O10: =SUMIFS(Cash_Events!$H$6:$H$20,Cash_Events!$C$6:$C$20,"rAGMF",Cash_Events!$D$6:$D$20,"800S",Cash_Events!$M$6:$M$20,A10) -> 0 | P10: =M10+J10-N10-O10 -> 47227.807 | Q10: =S9 -> 0 | R10: =SUMIFS(Cash_Events!$I$6:$I$20,Cash_Events!$C$6:$C$20,"rAGMF",Cash_Events!$M$6:$M$20,A10) -> 0 | S10: =Q10+K10-R10 -> 0 | T10: =P10+S10 -> 47227.807 | U10: =G10+T10 -> 1547227.8 | V10: =V9+L10 -> 47227.807 | W10: =W9+N10+O10+R10 -> 0 | X10: =ROUND(V10-W10-T10,2) -> 0
A11: =EOMONTH(A10,1) -> 44957 | B11: =A10 -> 44926 | C11: =A11-B11 -> 31 | D11: =IF(A11<=EOMONTH(Inputs!$B$18,-1),"Actual","Projection") -> Actual | E11: =G10 -> 1500000 | F11: =SUMIFS(Cash_Events!$G$6:$G$20,Cash_Events!$C$6:$C$20,"rAGMF",Cash_Events!$M$6:$M$20,A11) -> 0 | G11: =E11-F11 -> 1500000 | H11: =VLOOKUP(A11-1,Inputs!$A$40:$B$48,2,TRUE()) -> 0.034199997 | I11: =H11+Inputs!B10 -> 0.1017 | J11: =SUMIFS(Daily!$G$6:$G$2400,Daily!$B$6:$B$2400,A11) -> 12956.301 | K11: =SUMIFS(Daily!$H$6:$H$2400,Daily!$B$6:$B$2400,A11) -> 0 | L11: =J11+K11 -> 12956.301 | M11: =P10 -> 47227.807 | N11: =SUMIFS(Cash_Events!$H$6:$H$20,Cash_Events!$C$6:$C$20,"rAGMF",Cash_Events!$D$6:$D$20,"JV",Cash_Events!$M$6:$M$20,A11) -> 0 | O11: =SUMIFS(Cash_Events!$H$6:$H$20,Cash_Events!$C$6:$C$20,"rAGMF",Cash_Events!$D$6:$D$20,"800S",Cash_Events!$M$6:$M$20,A11) -> 0 | P11: =M11+J11-N11-O11 -> 60184.108 | Q11: =S10 -> 0 | R11: =SUMIFS(Cash_Events!$I$6:$I$20,Cash_Events!$C$6:$C$20,"rAGMF",Cash_Events!$M$6:$M$20,A11) -> 0 | S11: =Q11+K11-R11 -> 0 | T11: =P11+S11 -> 60184.108 | U11: =G11+T11 -> 1560184.1 | V11: =V10+L11 -> 60184.108 | W11: =W10+N11+O11+R11 -> 0 | X11: =ROUND(V11-W11-T11,2) -> 0
A12: =EOMONTH(A11,1) -> 44985 | B12: =A11 -> 44957 | C12: =A12-B12 -> 28 | D12: =IF(A12<=EOMONTH(Inputs!$B$18,-1),"Actual","Projection") -> Actual | E12: =G11 -> 1500000 | F12: =SUMIFS(Cash_Events!$G$6:$G$20,Cash_Events!$C$6:$C$20,"rAGMF",Cash_Events!$M$6:$M$20,A12) -> 0 | G12: =E12-F12 -> 1500000 | H12: =VLOOKUP(A12-1,Inputs!$A$40:$B$48,2,TRUE()) -> 0.034199997 | I12: =H12+Inputs!B10 -> 0.1017 | J12: =SUMIFS(Daily!$G$6:$G$2400,Daily!$B$6:$B$2400,A12) -> 11702.465 | K12: =SUMIFS(Daily!$H$6:$H$2400,Daily!$B$6:$B$2400,A12) -> 0 | L12: =J12+K12 -> 11702.465 | M12: =P11 -> 60184.108 | N12: =SUMIFS(Cash_Events!$H$6:$H$20,Cash_Events!$C$6:$C$20,"rAGMF",Cash_Events!$D$6:$D$20,"JV",Cash_Events!$M$6:$M$20,A12) -> 0 | O12: =SUMIFS(Cash_Events!$H$6:$H$20,Cash_Events!$C$6:$C$20,"rAGMF",Cash_Events!$D$6:$D$20,"800S",Cash_Events!$M$6:$M$20,A12) -> 0 | P12: =M12+J12-N12-O12 -> 71886.573 | Q12: =S11 -> 0 | R12: =SUMIFS(Cash_Events!$I$6:$I$20,Cash_Events!$C$6:$C$20,"rAGMF",Cash_Events!$M$6:$M$20,A12) -> 0 | S12: =Q12+K12-R12 -> 0 | T12: =P12+S12 -> 71886.573 | U12: =G12+T12 -> 1571886.6 | V12: =V11+L12 -> 71886.573 | W12: =W11+N12+O12+R12 -> 0 | X12: =ROUND(V12-W12-T12,2) -> 0
A13: =EOMONTH(A12,1) -> 45016 | B13: =A12 -> 44985 | C13: =A13-B13 -> 31 | D13: =IF(A13<=EOMONTH(Inputs!$B$18,-1),"Actual","Projection") -> Actual | E13: =G12 -> 1500000 | F13: =SUMIFS(Cash_Events!$G$6:$G$20,Cash_Events!$C$6:$C$20,"rAGMF",Cash_Events!$M$6:$M$20,A13) -> 0 | G13: =E13-F13 -> 1500000 | H13: =VLOOKUP(A13-1,Inputs!$A$40:$B$48,2,TRUE()) -> 0.0521501 | I13: =H13+Inputs!B10 -> 0.1196501 | J13: =SUMIFS(Daily!$G$6:$G$2400,Daily!$B$6:$B$2400,A13) -> 14579.187 | K13: =SUMIFS(Daily!$H$6:$H$2400,Daily!$B$6:$B$2400,A13) -> 0 | L13: =J13+K13 -> 14579.187 | M13: =P12 -> 71886.573 | N13: =SUMIFS(Cash_Events!$H$6:$H$20,Cash_Events!$C$6:$C$20,"rAGMF",Cash_Events!$D$6:$D$20,"JV",Cash_Events!$M$6:$M$20,A13) -> 75648.08 | O13: =SUMIFS(Cash_Events!$H$6:$H$20,Cash_Events!$C$6:$C$20,"rAGMF",Cash_Events!$D$6:$D$20,"800S",Cash_Events!$M$6:$M$20,A13) -> 0 | P13: =M13+J13-N13-O13 -> 10817.68 | Q13: =S12 -> 0 | R13: =SUMIFS(Cash_Events!$I$6:$I$20,Cash_Events!$C$6:$C$20,"rAGMF",Cash_Events!$M$6:$M$20,A13) -> 0 | S13: =Q13+K13-R13 -> 0 | T13: =P13+S13 -> 10817.68 | U13: =G13+T13 -> 1510817.7 | V13: =V12+L13 -> 86465.76 | W13: =W12+N13+O13+R13 -> 75648.08 | X13: =ROUND(V13-W13-T13,2) -> 0 | Y13: Coupon 1 paid by JV 07/03/2023; reset 09/03
A14: =EOMONTH(A13,1) -> 45046 | B14: =A13 -> 45016 | C14: =A14-B14 -> 30 | D14: =IF(A14<=EOMONTH(Inputs!$B$18,-1),"Actual","Projection") -> Actual | E14: =G13 -> 1500000 | F14: =SUMIFS(Cash_Events!$G$6:$G$20,Cash_Events!$C$6:$C$20,"rAGMF",Cash_Events!$M$6:$M$20,A14) -> 0 | G14: =E14-F14 -> 1500000 | H14: =VLOOKUP(A14-1,Inputs!$A$40:$B$48,2,TRUE()) -> 0.0521501 | I14: =H14+Inputs!B10 -> 0.1196501 | J14: =SUMIFS(Daily!$G$6:$G$2400,Daily!$B$6:$B$2400,A14) -> 14751.382 | K14: =SUMIFS(Daily!$H$6:$H$2400,Daily!$B$6:$B$2400,A14) -> 0 | L14: =J14+K14 -> 14751.382 | M14: =P13 -> 10817.68 | N14: =SUMIFS(Cash_Events!$H$6:$H$20,Cash_Events!$C$6:$C$20,"rAGMF",Cash_Events!$D$6:$D$20,"JV",Cash_Events!$M$6:$M$20,A14) -> 0 | O14: =SUMIFS(Cash_Events!$H$6:$H$20,Cash_Events!$C$6:$C$20,"rAGMF",Cash_Events!$D$6:$D$20,"800S",Cash_Events!$M$6:$M$20,A14) -> 0 | P14: =M14+J14-N14-O14 -> 25569.062 | Q14: =S13 -> 0 | R14: =SUMIFS(Cash_Events!$I$6:$I$20,Cash_Events!$C$6:$C$20,"rAGMF",Cash_Events!$M$6:$M$20,A14) -> 0 | S14: =Q14+K14-R14 -> 0 | T14: =P14+S14 -> 25569.062 | U14: =G14+T14 -> 1525569.1 | V14: =V13+L14 -> 101217.14 | W14: =W13+N14+O14+R14 -> 75648.08 | X14: =ROUND(V14-W14-T14,2) -> 0
A15: =EOMONTH(A14,1) -> 45077 | B15: =A14 -> 45046 | C15: =A15-B15 -> 31 | D15: =IF(A15<=EOMONTH(Inputs!$B$18,-1),"Actual","Projection") -> Actual | E15: =G14 -> 1500000 | F15: =SUMIFS(Cash_Events!$G$6:$G$20,Cash_Events!$C$6:$C$20,"rAGMF",Cash_Events!$M$6:$M$20,A15) -> 0 | G15: =E15-F15 -> 1500000 | H15: =VLOOKUP(A15-1,Inputs!$A$40:$B$48,2,TRUE()) -> 0.0521501 | I15: =H15+Inputs!B10 -> 0.1196501 | J15: =SUMIFS(Daily!$G$6:$G$2400,Daily!$B$6:$B$2400,A15) -> 15243.095 | K15: =SUMIFS(Daily!$H$6:$H$2400,Daily!$B$6:$B$2400,A15) -> 0 | L15: =J15+K15 -> 15243.095 | M15: =P14 -> 25569.062 | N15: =SUMIFS(Cash_Events!$H$6:$H$20,Cash_Events!$C$6:$C$20,"rAGMF",Cash_Events!$D$6:$D$20,"JV",Cash_Events!$M$6:$M$20,A15) -> 0 | O15: =SUMIFS(Cash_Events!$H$6:$H$20,Cash_Events!$C$6:$C$20,"rAGMF",Cash_Events!$D$6:$D$20,"800S",Cash_Events!$M$6:$M$20,A15) -> 0 | P15: =M15+J15-N15-O15 -> 40812.157 | Q15: =S14 -> 0 | R15: =SUMIFS(Cash_Events!$I$6:$I$20,Cash_Events!$C$6:$C$20,"rAGMF",Cash_Events!$M$6:$M$20,A15) -> 0 | S15: =Q15+K15-R15 -> 0 | T15: =P15+S15 -> 40812.157 | U15: =G15+T15 -> 1540812.2 | V15: =V14+L15 -> 116460.24 | W15: =W14+N15+O15+R15 -> 75648.08 | X15: =ROUND(V15-W15-T15,2) -> 0
A16: =EOMONTH(A15,1) -> 45107 | B16: =A15 -> 45077 | C16: =A16-B16 -> 30 | D16: =IF(A16<=EOMONTH(Inputs!$B$18,-1),"Actual","Projection") -> Actual | E16: =G15 -> 1500000 | F16: =SUMIFS(Cash_Events!$G$6:$G$20,Cash_Events!$C$6:$C$20,"rAGMF",Cash_Events!$M$6:$M$20,A16) -> 0 | G16: =E16-F16 -> 1500000 | H16: =VLOOKUP(A16-1,Inputs!$A$40:$B$48,2,TRUE()) -> 0.0521501 | I16: =H16+Inputs!B10 -> 0.1196501 | J16: =SUMIFS(Daily!$G$6:$G$2400,Daily!$B$6:$B$2400,A16) -> 14751.382 | K16: =SUMIFS(Daily!$H$6:$H$2400,Daily!$B$6:$B$2400,A16) -> 0 | L16: =J16+K16 -> 14751.382 | M16: =P15 -> 40812.157 | N16: =SUMIFS(Cash_Events!$H$6:$H$20,Cash_Events!$C$6:$C$20,"rAGMF",Cash_Events!$D$6:$D$20,"JV",Cash_Events!$M$6:$M$20,A16) -> 0 | O16: =SUMIFS(Cash_Events!$H$6:$H$20,Cash_Events!$C$6:$C$20,"rAGMF",Cash_Events!$D$6:$D$20,"800S",Cash_Events!$M$6:$M$20,A16) -> 0 | P16: =M16+J16-N16-O16 -> 55563.54 | Q16: =S15 -> 0 | R16: =SUMIFS(Cash_Events!$I$6:$I$20,Cash_Events!$C$6:$C$20,"rAGMF",Cash_Events!$M$6:$M$20,A16) -> 0 | S16: =Q16+K16-R16 -> 0 | T16: =P16+S16 -> 55563.54 | U16: =G16+T16 -> 1555563.5 | V16: =V15+L16 -> 131211.62 | W16: =W15+N16+O16+R16 -> 75648.08 | X16: =ROUND(V16-W16-T16,2) -> 0
A17: =EOMONTH(A16,1) -> 45138 | B17: =A16 -> 45107 | C17: =A17-B17 -> 31 | D17: =IF(A17<=EOMONTH(Inputs!$B$18,-1),"Actual","Projection") -> Actual | E17: =G16 -> 1500000 | F17: =SUMIFS(Cash_Events!$G$6:$G$20,Cash_Events!$C$6:$C$20,"rAGMF",Cash_Events!$M$6:$M$20,A17) -> 0 | G17: =E17-F17 -> 1500000 | H17: =VLOOKUP(A17-1,Inputs!$A$40:$B$48,2,TRUE()) -> 0.0521501 | I17: =H17+Inputs!B10 -> 0.1196501 | J17: =SUMIFS(Daily!$G$6:$G$2400,Daily!$B$6:$B$2400,A17) -> 15243.095 | K17: =SUMIFS(Daily!$H$6:$H$2400,Daily!$B$6:$B$2400,A17) -> 0 | L17: =J17+K17 -> 15243.095 | M17: =P16 -> 55563.54 | N17: =SUMIFS(Cash_Events!$H$6:$H$20,Cash_Events!$C$6:$C$20,"rAGMF",Cash_Events!$D$6:$D$20,"JV",Cash_Events!$M$6:$M$20,A17) -> 0 | O17: =SUMIFS(Cash_Events!$H$6:$H$20,Cash_Events!$C$6:$C$20,"rAGMF",Cash_Events!$D$6:$D$20,"800S",Cash_Events!$M$6:$M$20,A17) -> 0 | P17: =M17+J17-N17-O17 -> 70806.635 | Q17: =S16 -> 0 | R17: =SUMIFS(Cash_Events!$I$6:$I$20,Cash_Events!$C$6:$C$20,"rAGMF",Cash_Events!$M$6:$M$20,A17) -> 0 | S17: =Q17+K17-R17 -> 0 | T17: =P17+S17 -> 70806.635 | U17: =G17+T17 -> 1570806.6 | V17: =V16+L17 -> 146454.71 | W17: =W16+N17+O17+R17 -> 75648.08 | X17: =ROUND(V17-W17-T17,2) -> 0
A18: =EOMONTH(A17,1) -> 45169 | B18: =A17 -> 45138 | C18: =A18-B18 -> 31 | D18: =IF(A18<=EOMONTH(Inputs!$B$18,-1),"Actual","Projection") -> Actual | E18: =G17 -> 1500000 | F18: =SUMIFS(Cash_Events!$G$6:$G$20,Cash_Events!$C$6:$C$20,"rAGMF",Cash_Events!$M$6:$M$20,A18) -> 0 | G18: =E18-F18 -> 1500000 | H18: =VLOOKUP(A18-1,Inputs!$A$40:$B$48,2,TRUE()) -> 0.0521501 | I18: =H18+Inputs!B10 -> 0.1196501 | J18: =SUMIFS(Daily!$G$6:$G$2400,Daily!$B$6:$B$2400,A18) -> 15243.095 | K18: =SUMIFS(Daily!$H$6:$H$2400,Daily!$B$6:$B$2400,A18) -> 0 | L18: =J18+K18 -> 15243.095 | M18: =P17 -> 70806.635 | N18: =SUMIFS(Cash_Events!$H$6:$H$20,Cash_Events!$C$6:$C$20,"rAGMF",Cash_Events!$D$6:$D$20,"JV",Cash_Events!$M$6:$M$20,A18) -> 0 | O18: =SUMIFS(Cash_Events!$H$6:$H$20,Cash_Events!$C$6:$C$20,"rAGMF",Cash_Events!$D$6:$D$20,"800S",Cash_Events!$M$6:$M$20,A18) -> 0 | P18: =M18+J18-N18-O18 -> 86049.729 | Q18: =S17 -> 0 | R18: =SUMIFS(Cash_Events!$I$6:$I$20,Cash_Events!$C$6:$C$20,"rAGMF",Cash_Events!$M$6:$M$20,A18) -> 0 | S18: =Q18+K18-R18 -> 0 | T18: =P18+S18 -> 86049.729 | U18: =G18+T18 -> 1586049.7 | V18: =V17+L18 -> 161697.81 | W18: =W17+N18+O18+R18 -> 75648.08 | X18: =ROUND(V18-W18-T18,2) -> 0
A19: =EOMONTH(A18,1) -> 45199 | B19: =A18 -> 45169 | C19: =A19-B19 -> 30 | D19: =IF(A19<=EOMONTH(Inputs!$B$18,-1),"Actual","Projection") -> Actual | E19: =G18 -> 1500000 | F19: =SUMIFS(Cash_Events!$G$6:$G$20,Cash_Events!$C$6:$C$20,"rAGMF",Cash_Events!$M$6:$M$20,A19) -> 0 | G19: =E19-F19 -> 1500000 | H19: =VLOOKUP(A19-1,Inputs!$A$40:$B$48,2,TRUE()) -> 0.0547601 | I19: =H19+Inputs!B10 -> 0.1222601 | J19: =SUMIFS(Daily!$G$6:$G$2400,Daily!$B$6:$B$2400,A19) -> 14955.177 | K19: =SUMIFS(Daily!$H$6:$H$2400,Daily!$B$6:$B$2400,A19) -> 1561.6438 | L19: =J19+K19 -> 16516.821 | M19: =P18 -> 86049.729 | N19: =SUMIFS(Cash_Events!$H$6:$H$20,Cash_Events!$C$6:$C$20,"rAGMF",Cash_Events!$D$6:$D$20,"JV",Cash_Events!$M$6:$M$20,A19) -> 0 | O19: =SUMIFS(Cash_Events!$H$6:$H$20,Cash_Events!$C$6:$C$20,"rAGMF",Cash_Events!$D$6:$D$20,"800S",Cash_Events!$M$6:$M$20,A19) -> 0 | P19: =M19+J19-N19-O19 -> 101004.91 | Q19: =S18 -> 0 | R19: =SUMIFS(Cash_Events!$I$6:$I$20,Cash_Events!$C$6:$C$20,"rAGMF",Cash_Events!$M$6:$M$20,A19) -> 0 | S19: =Q19+K19-R19 -> 1561.6438 | T19: =P19+S19 -> 102566.55 | U19: =G19+T19 -> 1602566.6 | V19: =V18+L19 -> 178214.63 | W19: =W18+N19+O19+R19 -> 75648.08 | X19: =ROUND(V19-W19-T19,2) -> 0 | Y19: Coupon 2 missed 11/09/2023 - default interest starts
A20: =EOMONTH(A19,1) -> 45230 | B20: =A19 -> 45199 | C20: =A20-B20 -> 31 | D20: =IF(A20<=EOMONTH(Inputs!$B$18,-1),"Actual","Projection") -> Actual | E20: =G19 -> 1500000 | F20: =SUMIFS(Cash_Events!$G$6:$G$20,Cash_Events!$C$6:$C$20,"rAGMF",Cash_Events!$M$6:$M$20,A20) -> 0 | G20: =E20-F20 -> 1500000 | H20: =VLOOKUP(A20-1,Inputs!$A$40:$B$48,2,TRUE()) -> 0.0547601 | I20: =H20+Inputs!B10 -> 0.1222601 | J20: =SUMIFS(Daily!$G$6:$G$2400,Daily!$B$6:$B$2400,A20) -> 15575.602 | K20: =SUMIFS(Daily!$H$6:$H$2400,Daily!$B$6:$B$2400,A20) -> 2547.9452 | L20: =J20+K20 -> 18123.547 | M20: =P19 -> 101004.91 | N20: =SUMIFS(Cash_Events!$H$6:$H$20,Cash_Events!$C$6:$C$20,"rAGMF",Cash_Events!$D$6:$D$20,"JV",Cash_Events!$M$6:$M$20,A20) -> 0 | O20: =SUMIFS(Cash_Events!$H$6:$H$20,Cash_Events!$C$6:$C$20,"rAGMF",Cash_Events!$D$6:$D$20,"800S",Cash_Events!$M$6:$M$20,A20) -> 0 | P20: =M20+J20-N20-O20 -> 116580.51 | Q20: =S19 -> 1561.6438 | R20: =SUMIFS(Cash_Events!$I$6:$I$20,Cash_Events!$C$6:$C$20,"rAGMF",Cash_Events!$M$6:$M$20,A20) -> 0 | S20: =Q20+K20-R20 -> 4109.589 | T20: =P20+S20 -> 120690.1 | U20: =G20+T20 -> 1620690.1 | V20: =V19+L20 -> 196338.18 | W20: =W19+N20+O20+R20 -> 75648.08 | X20: =ROUND(V20-W20-T20,2) -> 0
A21: =EOMONTH(A20,1) -> 45260 | B21: =A20 -> 45230 | C21: =A21-B21 -> 30 | D21: =IF(A21<=EOMONTH(Inputs!$B$18,-1),"Actual","Projection") -> Actual | E21: =G20 -> 1500000 | F21: =SUMIFS(Cash_Events!$G$6:$G$20,Cash_Events!$C$6:$C$20,"rAGMF",Cash_Events!$M$6:$M$20,A21) -> 0 | G21: =E21-F21 -> 1500000 | H21: =VLOOKUP(A21-1,Inputs!$A$40:$B$48,2,TRUE()) -> 0.0547601 | I21: =H21+Inputs!B10 -> 0.1222601 | J21: =SUMIFS(Daily!$G$6:$G$2400,Daily!$B$6:$B$2400,A21) -> 15073.163 | K21: =SUMIFS(Daily!$H$6:$H$2400,Daily!$B$6:$B$2400,A21) -> 2465.7534 | L21: =J21+K21 -> 17538.916 | M21: =P20 -> 116580.51 | N21: =SUMIFS(Cash_Events!$H$6:$H$20,Cash_Events!$C$6:$C$20,"rAGMF",Cash_Events!$D$6:$D$20,"JV",Cash_Events!$M$6:$M$20,A21) -> 0 | O21: =SUMIFS(Cash_Events!$H$6:$H$20,Cash_Events!$C$6:$C$20,"rAGMF",Cash_Events!$D$6:$D$20,"800S",Cash_Events!$M$6:$M$20,A21) -> 0 | P21: =M21+J21-N21-O21 -> 131653.67 | Q21: =S20 -> 4109.589 | R21: =SUMIFS(Cash_Events!$I$6:$I$20,Cash_Events!$C$6:$C$20,"rAGMF",Cash_Events!$M$6:$M$20,A21) -> 0 | S21: =Q21+K21-R21 -> 6575.3425 | T21: =P21+S21 -> 138229.01 | U21: =G21+T21 -> 1638229 | V21: =V20+L21 -> 213877.09 | W21: =W20+N21+O21+R21 -> 75648.08 | X21: =ROUND(V21-W21-T21,2) -> 0
A22: =EOMONTH(A21,1) -> 45291 | B22: =A21 -> 45260 | C22: =A22-B22 -> 31 | D22: =IF(A22<=EOMONTH(Inputs!$B$18,-1),"Actual","Projection") -> Actual | E22: =G21 -> 1500000 | F22: =SUMIFS(Cash_Events!$G$6:$G$20,Cash_Events!$C$6:$C$20,"rAGMF",Cash_Events!$M$6:$M$20,A22) -> 0 | G22: =E22-F22 -> 1500000 | H22: =VLOOKUP(A22-1,Inputs!$A$40:$B$48,2,TRUE()) -> 0.0547601 | I22: =H22+Inputs!B10 -> 0.1222601 | J22: =SUMIFS(Daily!$G$6:$G$2400,Daily!$B$6:$B$2400,A22) -> 15575.602 | K22: =SUMIFS(Daily!$H$6:$H$2400,Daily!$B$6:$B$2400,A22) -> 2547.9452 | L22: =J22+K22 -> 18123.547 | M22: =P21 -> 131653.67 | N22: =SUMIFS(Cash_Events!$H$6:$H$20,Cash_Events!$C$6:$C$20,"rAGMF",Cash_Events!$D$6:$D$20,"JV",Cash_Events!$M$6:$M$20,A22) -> 0 | O22: =SUMIFS(Cash_Events!$H$6:$H$20,Cash_Events!$C$6:$C$20,"rAGMF",Cash_Events!$D$6:$D$20,"800S",Cash_Events!$M$6:$M$20,A22) -> 0 | P22: =M22+J22-N22-O22 -> 147229.27 | Q22: =S21 -> 6575.3425 | R22: =SUMIFS(Cash_Events!$I$6:$I$20,Cash_Events!$C$6:$C$20,"rAGMF",Cash_Events!$M$6:$M$20,A22) -> 0 | S22: =Q22+K22-R22 -> 9123.2877 | T22: =P22+S22 -> 156352.56 | U22: =G22+T22 -> 1656352.6 | V22: =V21+L22 -> 232000.64 | W22: =W21+N22+O22+R22 -> 75648.08 | X22: =ROUND(V22-W22-T22,2) -> 0
A23: =EOMONTH(A22,1) -> 45322 | B23: =A22 -> 45291 | C23: =A23-B23 -> 31 | D23: =IF(A23<=EOMONTH(Inputs!$B$18,-1),"Actual","Projection") -> Actual | E23: =G22 -> 1500000 | F23: =SUMIFS(Cash_Events!$G$6:$G$20,Cash_Events!$C$6:$C$20,"rAGMF",Cash_Events!$M$6:$M$20,A23) -> 0 | G23: =E23-F23 -> 1500000 | H23: =VLOOKUP(A23-1,Inputs!$A$40:$B$48,2,TRUE()) -> 0.0547601 | I23: =H23+Inputs!B10 -> 0.1222601 | J23: =SUMIFS(Daily!$G$6:$G$2400,Daily!$B$6:$B$2400,A23) -> 15534.418 | K23: =SUMIFS(Daily!$H$6:$H$2400,Daily!$B$6:$B$2400,A23) -> 2541.2082 | L23: =J23+K23 -> 18075.626 | M23: =P22 -> 147229.27 | N23: =SUMIFS(Cash_Events!$H$6:$H$20,Cash_Events!$C$6:$C$20,"rAGMF",Cash_Events!$D$6:$D$20,"JV",Cash_Events!$M$6:$M$20,A23) -> 0 | O23: =SUMIFS(Cash_Events!$H$6:$H$20,Cash_Events!$C$6:$C$20,"rAGMF",Cash_Events!$D$6:$D$20,"800S",Cash_Events!$M$6:$M$20,A23) -> 0 | P23: =M23+J23-N23-O23 -> 162763.69 | Q23: =S22 -> 9123.2877 | R23: =SUMIFS(Cash_Events!$I$6:$I$20,Cash_Events!$C$6:$C$20,"rAGMF",Cash_Events!$M$6:$M$20,A23) -> 0 | S23: =Q23+K23-R23 -> 11664.496 | T23: =P23+S23 -> 174428.19 | U23: =G23+T23 -> 1674428.2 | V23: =V22+L23 -> 250076.27 | W23: =W22+N23+O23+R23 -> 75648.08 | X23: =ROUND(V23-W23-T23,2) -> 0
A24: =EOMONTH(A23,1) -> 45351 | B24: =A23 -> 45322 | C24: =A24-B24 -> 29 | D24: =IF(A24<=EOMONTH(Inputs!$B$18,-1),"Actual","Projection") -> Actual | E24: =G23 -> 1500000 | F24: =SUMIFS(Cash_Events!$G$6:$G$20,Cash_Events!$C$6:$C$20,"rAGMF",Cash_Events!$M$6:$M$20,A24) -> 0 | G24: =E24-F24 -> 1500000 | H24: =VLOOKUP(A24-1,Inputs!$A$40:$B$48,2,TRUE()) -> 0.0547601 | I24: =H24+Inputs!B10 -> 0.1222601 | J24: =SUMIFS(Daily!$G$6:$G$2400,Daily!$B$6:$B$2400,A24) -> 14530.914 | K24: =SUMIFS(Daily!$H$6:$H$2400,Daily!$B$6:$B$2400,A24) -> 2377.0492 | L24: =J24+K24 -> 16907.963 | M24: =P23 -> 162763.69 | N24: =SUMIFS(Cash_Events!$H$6:$H$20,Cash_Events!$C$6:$C$20,"rAGMF",Cash_Events!$D$6:$D$20,"JV",Cash_Events!$M$6:$M$20,A24) -> 0 | O24: =SUMIFS(Cash_Events!$H$6:$H$20,Cash_Events!$C$6:$C$20,"rAGMF",Cash_Events!$D$6:$D$20,"800S",Cash_Events!$M$6:$M$20,A24) -> 0 | P24: =M24+J24-N24-O24 -> 177294.6 | Q24: =S23 -> 11664.496 | R24: =SUMIFS(Cash_Events!$I$6:$I$20,Cash_Events!$C$6:$C$20,"rAGMF",Cash_Events!$M$6:$M$20,A24) -> 0 | S24: =Q24+K24-R24 -> 14041.545 | T24: =P24+S24 -> 191336.15 | U24: =G24+T24 -> 1691336.1 | V24: =V23+L24 -> 266984.23 | W24: =W23+N24+O24+R24 -> 75648.08 | X24: =ROUND(V24-W24-T24,2) -> 0
A25: =EOMONTH(A24,1) -> 45382 | B25: =A24 -> 45351 | C25: =A25-B25 -> 31 | D25: =IF(A25<=EOMONTH(Inputs!$B$18,-1),"Actual","Projection") -> Actual | E25: =G24 -> 1500000 | F25: =SUMIFS(Cash_Events!$G$6:$G$20,Cash_Events!$C$6:$C$20,"rAGMF",Cash_Events!$M$6:$M$20,A25) -> 0 | G25: =E25-F25 -> 1500000 | H25: =VLOOKUP(A25-1,Inputs!$A$40:$B$48,2,TRUE()) -> 0.0523565 | I25: =H25+Inputs!B10 -> 0.1198565 | J25: =SUMIFS(Daily!$G$6:$G$2400,Daily!$B$6:$B$2400,A25) -> 15336.029 | K25: =SUMIFS(Daily!$H$6:$H$2400,Daily!$B$6:$B$2400,A25) -> 2540.9836 | L25: =J25+K25 -> 17877.013 | M25: =P24 -> 177294.6 | N25: =SUMIFS(Cash_Events!$H$6:$H$20,Cash_Events!$C$6:$C$20,"rAGMF",Cash_Events!$D$6:$D$20,"JV",Cash_Events!$M$6:$M$20,A25) -> 0 | O25: =SUMIFS(Cash_Events!$H$6:$H$20,Cash_Events!$C$6:$C$20,"rAGMF",Cash_Events!$D$6:$D$20,"800S",Cash_Events!$M$6:$M$20,A25) -> 0 | P25: =M25+J25-N25-O25 -> 192630.63 | Q25: =S24 -> 14041.545 | R25: =SUMIFS(Cash_Events!$I$6:$I$20,Cash_Events!$C$6:$C$20,"rAGMF",Cash_Events!$M$6:$M$20,A25) -> 0 | S25: =Q25+K25-R25 -> 16582.529 | T25: =P25+S25 -> 209213.16 | U25: =G25+T25 -> 1709213.2 | V25: =V24+L25 -> 284861.24 | W25: =W24+N25+O25+R25 -> 75648.08 | X25: =ROUND(V25-W25-T25,2) -> 0 | Y25: Coupon 3 missed 11/03/2024
A26: =EOMONTH(A25,1) -> 45412 | B26: =A25 -> 45382 | C26: =A26-B26 -> 30 | D26: =IF(A26<=EOMONTH(Inputs!$B$18,-1),"Actual","Projection") -> Actual | E26: =G25 -> 1500000 | F26: =SUMIFS(Cash_Events!$G$6:$G$20,Cash_Events!$C$6:$C$20,"rAGMF",Cash_Events!$M$6:$M$20,A26) -> 0 | G26: =E26-F26 -> 1500000 | H26: =VLOOKUP(A26-1,Inputs!$A$40:$B$48,2,TRUE()) -> 0.0523565 | I26: =H26+Inputs!B10 -> 0.1198565 | J26: =SUMIFS(Daily!$G$6:$G$2400,Daily!$B$6:$B$2400,A26) -> 14736.455 | K26: =SUMIFS(Daily!$H$6:$H$2400,Daily!$B$6:$B$2400,A26) -> 2459.0164 | L26: =J26+K26 -> 17195.471 | M26: =P25 -> 192630.63 | N26: =SUMIFS(Cash_Events!$H$6:$H$20,Cash_Events!$C$6:$C$20,"rAGMF",Cash_Events!$D$6:$D$20,"JV",Cash_Events!$M$6:$M$20,A26) -> 0 | O26: =SUMIFS(Cash_Events!$H$6:$H$20,Cash_Events!$C$6:$C$20,"rAGMF",Cash_Events!$D$6:$D$20,"800S",Cash_Events!$M$6:$M$20,A26) -> 0 | P26: =M26+J26-N26-O26 -> 207367.09 | Q26: =S25 -> 16582.529 | R26: =SUMIFS(Cash_Events!$I$6:$I$20,Cash_Events!$C$6:$C$20,"rAGMF",Cash_Events!$M$6:$M$20,A26) -> 0 | S26: =Q26+K26-R26 -> 19041.545 | T26: =P26+S26 -> 226408.63 | U26: =G26+T26 -> 1726408.6 | V26: =V25+L26 -> 302056.71 | W26: =W25+N26+O26+R26 -> 75648.08 | X26: =ROUND(V26-W26-T26,2) -> 0
A27: =EOMONTH(A26,1) -> 45443 | B27: =A26 -> 45412 | C27: =A27-B27 -> 31 | D27: =IF(A27<=EOMONTH(Inputs!$B$18,-1),"Actual","Projection") -> Actual | E27: =G26 -> 1500000 | F27: =SUMIFS(Cash_Events!$G$6:$G$20,Cash_Events!$C$6:$C$20,"rAGMF",Cash_Events!$M$6:$M$20,A27) -> 0 | G27: =E27-F27 -> 1500000 | H27: =VLOOKUP(A27-1,Inputs!$A$40:$B$48,2,TRUE()) -> 0.0523565 | I27: =H27+Inputs!B10 -> 0.1198565 | J27: =SUMIFS(Daily!$G$6:$G$2400,Daily!$B$6:$B$2400,A27) -> 15227.67 | K27: =SUMIFS(Daily!$H$6:$H$2400,Daily!$B$6:$B$2400,A27) -> 2540.9836 | L27: =J27+K27 -> 17768.654 | M27: =P26 -> 207367.09 | N27: =SUMIFS(Cash_Events!$H$6:$H$20,Cash_Events!$C$6:$C$20,"rAGMF",Cash_Events!$D$6:$D$20,"JV",Cash_Events!$M$6:$M$20,A27) -> 0 | O27: =SUMIFS(Cash_Events!$H$6:$H$20,Cash_Events!$C$6:$C$20,"rAGMF",Cash_Events!$D$6:$D$20,"800S",Cash_Events!$M$6:$M$20,A27) -> 0 | P27: =M27+J27-N27-O27 -> 222594.76 | Q27: =S26 -> 19041.545 | R27: =SUMIFS(Cash_Events!$I$6:$I$20,Cash_Events!$C$6:$C$20,"rAGMF",Cash_Events!$M$6:$M$20,A27) -> 0 | S27: =Q27+K27-R27 -> 21582.529 | T27: =P27+S27 -> 244177.29 | U27: =G27+T27 -> 1744177.3 | V27: =V26+L27 -> 319825.37 | W27: =W26+N27+O27+R27 -> 75648.08 | X27: =ROUND(V27-W27-T27,2) -> 0
A28: =EOMONTH(A27,1) -> 45473 | B28: =A27 -> 45443 | C28: =A28-B28 -> 30 | D28: =IF(A28<=EOMONTH(Inputs!$B$18,-1),"Actual","Projection") -> Actual | E28: =G27 -> 1500000 | F28: =SUMIFS(Cash_Events!$G$6:$G$20,Cash_Events!$C$6:$C$20,"rAGMF",Cash_Events!$M$6:$M$20,A28) -> 765000 | G28: =E28-F28 -> 735000 | H28: =VLOOKUP(A28-1,Inputs!$A$40:$B$48,2,TRUE()) -> 0.0523565 | I28: =H28+Inputs!B10 -> 0.1198565 | J28: =SUMIFS(Daily!$G$6:$G$2400,Daily!$B$6:$B$2400,A28) -> 14235.415 | K28: =SUMIFS(Daily!$H$6:$H$2400,Daily!$B$6:$B$2400,A28) -> 2375.4098 | L28: =J28+K28 -> 16610.825 | M28: =P27 -> 222594.76 | N28: =SUMIFS(Cash_Events!$H$6:$H$20,Cash_Events!$C$6:$C$20,"rAGMF",Cash_Events!$D$6:$D$20,"JV",Cash_Events!$M$6:$M$20,A28) -> 0 | O28: =SUMIFS(Cash_Events!$H$6:$H$20,Cash_Events!$C$6:$C$20,"rAGMF",Cash_Events!$D$6:$D$20,"800S",Cash_Events!$M$6:$M$20,A28) -> 100477.79 | P28: =M28+J28-N28-O28 -> 136352.38 | Q28: =S27 -> 21582.529 | R28: =SUMIFS(Cash_Events!$I$6:$I$20,Cash_Events!$C$6:$C$20,"rAGMF",Cash_Events!$M$6:$M$20,A28) -> 8687.9 | S28: =Q28+K28-R28 -> 15270.038 | T28: =P28+S28 -> 151622.42 | U28: =G28+T28 -> 886622.42 | V28: =V27+L28 -> 336436.19 | W28: =W27+N28+O28+R28 -> 184813.77 | X28: =ROUND(V28-W28-T28,2) -> 0 | Y28: 800S: interest 13/06 + principal 28/06/2024 (51%)
A29: =EOMONTH(A28,1) -> 45504 | B29: =A28 -> 45473 | C29: =A29-B29 -> 31 | D29: =IF(A29<=EOMONTH(Inputs!$B$18,-1),"Actual","Projection") -> Actual | E29: =G28 -> 735000 | F29: =SUMIFS(Cash_Events!$G$6:$G$20,Cash_Events!$C$6:$C$20,"rAGMF",Cash_Events!$M$6:$M$20,A29) -> 0 | G29: =E29-F29 -> 735000 | H29: =VLOOKUP(A29-1,Inputs!$A$40:$B$48,2,TRUE()) -> 0.0523565 | I29: =H29+Inputs!B10 -> 0.1198565 | J29: =SUMIFS(Daily!$G$6:$G$2400,Daily!$B$6:$B$2400,A29) -> 7461.5583 | K29: =SUMIFS(Daily!$H$6:$H$2400,Daily!$B$6:$B$2400,A29) -> 1245.082 | L29: =J29+K29 -> 8706.6403 | M29: =P28 -> 136352.38 | N29: =SUMIFS(Cash_Events!$H$6:$H$20,Cash_Events!$C$6:$C$20,"rAGMF",Cash_Events!$D$6:$D$20,"JV",Cash_Events!$M$6:$M$20,A29) -> 0 | O29: =SUMIFS(Cash_Events!$H$6:$H$20,Cash_Events!$C$6:$C$20,"rAGMF",Cash_Events!$D$6:$D$20,"800S",Cash_Events!$M$6:$M$20,A29) -> 0 | P29: =M29+J29-N29-O29 -> 143813.94 | Q29: =S28 -> 15270.038 | R29: =SUMIFS(Cash_Events!$I$6:$I$20,Cash_Events!$C$6:$C$20,"rAGMF",Cash_Events!$M$6:$M$20,A29) -> 0 | S29: =Q29+K29-R29 -> 16515.12 | T29: =P29+S29 -> 160329.06 | U29: =G29+T29 -> 895329.06 | V29: =V28+L29 -> 345142.83 | W29: =W28+N29+O29+R29 -> 184813.77 | X29: =ROUND(V29-W29-T29,2) -> 0
A30: =EOMONTH(A29,1) -> 45535 | B30: =A29 -> 45504 | C30: =A30-B30 -> 31 | D30: =IF(A30<=EOMONTH(Inputs!$B$18,-1),"Actual","Projection") -> Actual | E30: =G29 -> 735000 | F30: =SUMIFS(Cash_Events!$G$6:$G$20,Cash_Events!$C$6:$C$20,"rAGMF",Cash_Events!$M$6:$M$20,A30) -> 0 | G30: =E30-F30 -> 735000 | H30: =VLOOKUP(A30-1,Inputs!$A$40:$B$48,2,TRUE()) -> 0.0523565 | I30: =H30+Inputs!B10 -> 0.1198565 | J30: =SUMIFS(Daily!$G$6:$G$2400,Daily!$B$6:$B$2400,A30) -> 7461.5583 | K30: =SUMIFS(Daily!$H$6:$H$2400,Daily!$B$6:$B$2400,A30) -> 1245.082 | L30: =J30+K30 -> 8706.6403 | M30: =P29 -> 143813.94 | N30: =SUMIFS(Cash_Events!$H$6:$H$20,Cash_Events!$C$6:$C$20,"rAGMF",Cash_Events!$D$6:$D$20,"JV",Cash_Events!$M$6:$M$20,A30) -> 0 | O30: =SUMIFS(Cash_Events!$H$6:$H$20,Cash_Events!$C$6:$C$20,"rAGMF",Cash_Events!$D$6:$D$20,"800S",Cash_Events!$M$6:$M$20,A30) -> 0 | P30: =M30+J30-N30-O30 -> 151275.5 | Q30: =S29 -> 16515.12 | R30: =SUMIFS(Cash_Events!$I$6:$I$20,Cash_Events!$C$6:$C$20,"rAGMF",Cash_Events!$M$6:$M$20,A30) -> 0 | S30: =Q30+K30-R30 -> 17760.202 | T30: =P30+S30 -> 169035.7 | U30: =G30+T30 -> 904035.7 | V30: =V29+L30 -> 353849.47 | W30: =W29+N30+O30+R30 -> 184813.77 | X30: =ROUND(V30-W30-T30,2) -> 0
A31: =EOMONTH(A30,1) -> 45565 | B31: =A30 -> 45535 | C31: =A31-B31 -> 30 | D31: =IF(A31<=EOMONTH(Inputs!$B$18,-1),"Actual","Projection") -> Actual | E31: =G30 -> 735000 | F31: =SUMIFS(Cash_Events!$G$6:$G$20,Cash_Events!$C$6:$C$20,"rAGMF",Cash_Events!$M$6:$M$20,A31) -> 0 | G31: =E31-F31 -> 735000 | H31: =VLOOKUP(A31-1,Inputs!$A$40:$B$48,2,TRUE()) -> 0.0461541 | I31: =H31+Inputs!B10 -> 0.1136541 | J31: =SUMIFS(Daily!$G$6:$G$2400,Daily!$B$6:$B$2400,A31) -> 6959.2945 | K31: =SUMIFS(Daily!$H$6:$H$2400,Daily!$B$6:$B$2400,A31) -> 1204.918 | L31: =J31+K31 -> 8164.2125 | M31: =P30 -> 151275.5 | N31: =SUMIFS(Cash_Events!$H$6:$H$20,Cash_Events!$C$6:$C$20,"rAGMF",Cash_Events!$D$6:$D$20,"JV",Cash_Events!$M$6:$M$20,A31) -> 0 | O31: =SUMIFS(Cash_Events!$H$6:$H$20,Cash_Events!$C$6:$C$20,"rAGMF",Cash_Events!$D$6:$D$20,"800S",Cash_Events!$M$6:$M$20,A31) -> 0 | P31: =M31+J31-N31-O31 -> 158234.8 | Q31: =S30 -> 17760.202 | R31: =SUMIFS(Cash_Events!$I$6:$I$20,Cash_Events!$C$6:$C$20,"rAGMF",Cash_Events!$M$6:$M$20,A31) -> 0 | S31: =Q31+K31-R31 -> 18965.12 | T31: =P31+S31 -> 177199.92 | U31: =G31+T31 -> 912199.92 | V31: =V30+L31 -> 362013.69 | W31: =W30+N31+O31+R31 -> 184813.77 | X31: =ROUND(V31-W31-T31,2) -> 0 | Y31: Coupon missed 09/09/2024
A32: =EOMONTH(A31,1) -> 45596 | B32: =A31 -> 45565 | C32: =A32-B32 -> 31 | D32: =IF(A32<=EOMONTH(Inputs!$B$18,-1),"Actual","Projection") -> Actual | E32: =G31 -> 735000 | F32: =SUMIFS(Cash_Events!$G$6:$G$20,Cash_Events!$C$6:$C$20,"rAGMF",Cash_Events!$M$6:$M$20,A32) -> 0 | G32: =E32-F32 -> 735000 | H32: =VLOOKUP(A32-1,Inputs!$A$40:$B$48,2,TRUE()) -> 0.0461541 | I32: =H32+Inputs!B10 -> 0.1136541 | J32: =SUMIFS(Daily!$G$6:$G$2400,Daily!$B$6:$B$2400,A32) -> 7075.4335 | K32: =SUMIFS(Daily!$H$6:$H$2400,Daily!$B$6:$B$2400,A32) -> 1245.082 | L32: =J32+K32 -> 8320.5155 | M32: =P31 -> 158234.8 | N32: =SUMIFS(Cash_Events!$H$6:$H$20,Cash_Events!$C$6:$C$20,"rAGMF",Cash_Events!$D$6:$D$20,"JV",Cash_Events!$M$6:$M$20,A32) -> 0 | O32: =SUMIFS(Cash_Events!$H$6:$H$20,Cash_Events!$C$6:$C$20,"rAGMF",Cash_Events!$D$6:$D$20,"800S",Cash_Events!$M$6:$M$20,A32) -> 0 | P32: =M32+J32-N32-O32 -> 165310.23 | Q32: =S31 -> 18965.12 | R32: =SUMIFS(Cash_Events!$I$6:$I$20,Cash_Events!$C$6:$C$20,"rAGMF",Cash_Events!$M$6:$M$20,A32) -> 0 | S32: =Q32+K32-R32 -> 20210.202 | T32: =P32+S32 -> 185520.43 | U32: =G32+T32 -> 920520.43 | V32: =V31+L32 -> 370334.2 | W32: =W31+N32+O32+R32 -> 184813.77 | X32: =ROUND(V32-W32-T32,2) -> 0
A33: =EOMONTH(A32,1) -> 45626 | B33: =A32 -> 45596 | C33: =A33-B33 -> 30 | D33: =IF(A33<=EOMONTH(Inputs!$B$18,-1),"Actual","Projection") -> Actual | E33: =G32 -> 735000 | F33: =SUMIFS(Cash_Events!$G$6:$G$20,Cash_Events!$C$6:$C$20,"rAGMF",Cash_Events!$M$6:$M$20,A33) -> 0 | G33: =E33-F33 -> 735000 | H33: =VLOOKUP(A33-1,Inputs!$A$40:$B$48,2,TRUE()) -> 0.0461541 | I33: =H33+Inputs!B10 -> 0.1136541 | J33: =SUMIFS(Daily!$G$6:$G$2400,Daily!$B$6:$B$2400,A33) -> 6847.1937 | K33: =SUMIFS(Daily!$H$6:$H$2400,Daily!$B$6:$B$2400,A33) -> 1204.918 | L33: =J33+K33 -> 8052.1118 | M33: =P32 -> 165310.23 | N33: =SUMIFS(Cash_Events!$H$6:$H$20,Cash_Events!$C$6:$C$20,"rAGMF",Cash_Events!$D$6:$D$20,"JV",Cash_Events!$M$6:$M$20,A33) -> 0 | O33: =SUMIFS(Cash_Events!$H$6:$H$20,Cash_Events!$C$6:$C$20,"rAGMF",Cash_Events!$D$6:$D$20,"800S",Cash_Events!$M$6:$M$20,A33) -> 0 | P33: =M33+J33-N33-O33 -> 172157.42 | Q33: =S32 -> 20210.202 | R33: =SUMIFS(Cash_Events!$I$6:$I$20,Cash_Events!$C$6:$C$20,"rAGMF",Cash_Events!$M$6:$M$20,A33) -> 0 | S33: =Q33+K33-R33 -> 21415.12 | T33: =P33+S33 -> 193572.54 | U33: =G33+T33 -> 928572.54 | V33: =V32+L33 -> 378386.31 | W33: =W32+N33+O33+R33 -> 184813.77 | X33: =ROUND(V33-W33-T33,2) -> 0
A34: =EOMONTH(A33,1) -> 45657 | B34: =A33 -> 45626 | C34: =A34-B34 -> 31 | D34: =IF(A34<=EOMONTH(Inputs!$B$18,-1),"Actual","Projection") -> Actual | E34: =G33 -> 735000 | F34: =SUMIFS(Cash_Events!$G$6:$G$20,Cash_Events!$C$6:$C$20,"rAGMF",Cash_Events!$M$6:$M$20,A34) -> 0 | G34: =E34-F34 -> 735000 | H34: =VLOOKUP(A34-1,Inputs!$A$40:$B$48,2,TRUE()) -> 0.0461541 | I34: =H34+Inputs!B10 -> 0.1136541 | J34: =SUMIFS(Daily!$G$6:$G$2400,Daily!$B$6:$B$2400,A34) -> 7075.4335 | K34: =SUMIFS(Daily!$H$6:$H$2400,Daily!$B$6:$B$2400,A34) -> 1245.082 | L34: =J34+K34 -> 8320.5155 | M34: =P33 -> 172157.42 | N34: =SUMIFS(Cash_Events!$H$6:$H$20,Cash_Events!$C$6:$C$20,"rAGMF",Cash_Events!$D$6:$D$20,"JV",Cash_Events!$M$6:$M$20,A34) -> 0 | O34: =SUMIFS(Cash_Events!$H$6:$H$20,Cash_Events!$C$6:$C$20,"rAGMF",Cash_Events!$D$6:$D$20,"800S",Cash_Events!$M$6:$M$20,A34) -> 0 | P34: =M34+J34-N34-O34 -> 179232.86 | Q34: =S33 -> 21415.12 | R34: =SUMIFS(Cash_Events!$I$6:$I$20,Cash_Events!$C$6:$C$20,"rAGMF",Cash_Events!$M$6:$M$20,A34) -> 0 | S34: =Q34+K34-R34 -> 22660.202 | T34: =P34+S34 -> 201893.06 | U34: =G34+T34 -> 936893.06 | V34: =V33+L34 -> 386706.83 | W34: =W33+N34+O34+R34 -> 184813.77 | X34: =ROUND(V34-W34-T34,2) -> 0
A35: =EOMONTH(A34,1) -> 45688 | B35: =A34 -> 45657 | C35: =A35-B35 -> 31 | D35: =IF(A35<=EOMONTH(Inputs!$B$18,-1),"Actual","Projection") -> Actual | E35: =G34 -> 735000 | F35: =SUMIFS(Cash_Events!$G$6:$G$20,Cash_Events!$C$6:$C$20,"rAGMF",Cash_Events!$M$6:$M$20,A35) -> 0 | G35: =E35-F35 -> 735000 | H35: =VLOOKUP(A35-1,Inputs!$A$40:$B$48,2,TRUE()) -> 0.0461541 | I35: =H35+Inputs!B10 -> 0.1136541 | J35: =SUMIFS(Daily!$G$6:$G$2400,Daily!$B$6:$B$2400,A35) -> 7094.193 | K35: =SUMIFS(Daily!$H$6:$H$2400,Daily!$B$6:$B$2400,A35) -> 1248.3831 | L35: =J35+K35 -> 8342.5761 | M35: =P34 -> 179232.86 | N35: =SUMIFS(Cash_Events!$H$6:$H$20,Cash_Events!$C$6:$C$20,"rAGMF",Cash_Events!$D$6:$D$20,"JV",Cash_Events!$M$6:$M$20,A35) -> 0 | O35: =SUMIFS(Cash_Events!$H$6:$H$20,Cash_Events!$C$6:$C$20,"rAGMF",Cash_Events!$D$6:$D$20,"800S",Cash_Events!$M$6:$M$20,A35) -> 0 | P35: =M35+J35-N35-O35 -> 186327.05 | Q35: =S34 -> 22660.202 | R35: =SUMIFS(Cash_Events!$I$6:$I$20,Cash_Events!$C$6:$C$20,"rAGMF",Cash_Events!$M$6:$M$20,A35) -> 0 | S35: =Q35+K35-R35 -> 23908.586 | T35: =P35+S35 -> 210235.63 | U35: =G35+T35 -> 945235.63 | V35: =V34+L35 -> 395049.4 | W35: =W34+N35+O35+R35 -> 184813.77 | X35: =ROUND(V35-W35-T35,2) -> 0
A36: =EOMONTH(A35,1) -> 45716 | B36: =A35 -> 45688 | C36: =A36-B36 -> 28 | D36: =IF(A36<=EOMONTH(Inputs!$B$18,-1),"Actual","Projection") -> Actual | E36: =G35 -> 735000 | F36: =SUMIFS(Cash_Events!$G$6:$G$20,Cash_Events!$C$6:$C$20,"rAGMF",Cash_Events!$M$6:$M$20,A36) -> 0 | G36: =E36-F36 -> 735000 | H36: =VLOOKUP(A36-1,Inputs!$A$40:$B$48,2,TRUE()) -> 0.0461541 | I36: =H36+Inputs!B10 -> 0.1136541 | J36: =SUMIFS(Daily!$G$6:$G$2400,Daily!$B$6:$B$2400,A36) -> 6408.223 | K36: =SUMIFS(Daily!$H$6:$H$2400,Daily!$B$6:$B$2400,A36) -> 1127.6712 | L36: =J36+K36 -> 7535.8942 | M36: =P35 -> 186327.05 | N36: =SUMIFS(Cash_Events!$H$6:$H$20,Cash_Events!$C$6:$C$20,"rAGMF",Cash_Events!$D$6:$D$20,"JV",Cash_Events!$M$6:$M$20,A36) -> 0 | O36: =SUMIFS(Cash_Events!$H$6:$H$20,Cash_Events!$C$6:$C$20,"rAGMF",Cash_Events!$D$6:$D$20,"800S",Cash_Events!$M$6:$M$20,A36) -> 0 | P36: =M36+J36-N36-O36 -> 192735.27 | Q36: =S35 -> 23908.586 | R36: =SUMIFS(Cash_Events!$I$6:$I$20,Cash_Events!$C$6:$C$20,"rAGMF",Cash_Events!$M$6:$M$20,A36) -> 0 | S36: =Q36+K36-R36 -> 25036.257 | T36: =P36+S36 -> 217771.53 | U36: =G36+T36 -> 952771.53 | V36: =V35+L36 -> 402585.3 | W36: =W35+N36+O36+R36 -> 184813.77 | X36: =ROUND(V36-W36-T36,2) -> 0
A37: =EOMONTH(A36,1) -> 45747 | B37: =A36 -> 45716 | C37: =A37-B37 -> 31 | D37: =IF(A37<=EOMONTH(Inputs!$B$18,-1),"Actual","Projection") -> Actual | E37: =G36 -> 735000 | F37: =SUMIFS(Cash_Events!$G$6:$G$20,Cash_Events!$C$6:$C$20,"rAGMF",Cash_Events!$M$6:$M$20,A37) -> 0 | G37: =E37-F37 -> 735000 | H37: =VLOOKUP(A37-1,Inputs!$A$40:$B$48,2,TRUE()) -> 0.0419027 | I37: =H37+Inputs!B10 -> 0.1094027 | J37: =SUMIFS(Daily!$G$6:$G$2400,Daily!$B$6:$B$2400,A37) -> 6915.0365 | K37: =SUMIFS(Daily!$H$6:$H$2400,Daily!$B$6:$B$2400,A37) -> 1248.4932 | L37: =J37+K37 -> 8163.5296 | M37: =P36 -> 192735.27 | N37: =SUMIFS(Cash_Events!$H$6:$H$20,Cash_Events!$C$6:$C$20,"rAGMF",Cash_Events!$D$6:$D$20,"JV",Cash_Events!$M$6:$M$20,A37) -> 0 | O37: =SUMIFS(Cash_Events!$H$6:$H$20,Cash_Events!$C$6:$C$20,"rAGMF",Cash_Events!$D$6:$D$20,"800S",Cash_Events!$M$6:$M$20,A37) -> 0 | P37: =M37+J37-N37-O37 -> 199650.31 | Q37: =S36 -> 25036.257 | R37: =SUMIFS(Cash_Events!$I$6:$I$20,Cash_Events!$C$6:$C$20,"rAGMF",Cash_Events!$M$6:$M$20,A37) -> 0 | S37: =Q37+K37-R37 -> 26284.75 | T37: =P37+S37 -> 225935.06 | U37: =G37+T37 -> 960935.06 | V37: =V36+L37 -> 410748.83 | W37: =W36+N37+O37+R37 -> 184813.77 | X37: =ROUND(V37-W37-T37,2) -> 0 | Y37: Coupon missed 10/03/2025
A38: =EOMONTH(A37,1) -> 45777 | B38: =A37 -> 45747 | C38: =A38-B38 -> 30 | D38: =IF(A38<=EOMONTH(Inputs!$B$18,-1),"Actual","Projection") -> Actual | E38: =G37 -> 735000 | F38: =SUMIFS(Cash_Events!$G$6:$G$20,Cash_Events!$C$6:$C$20,"rAGMF",Cash_Events!$M$6:$M$20,A38) -> 0 | G38: =E38-F38 -> 735000 | H38: =VLOOKUP(A38-1,Inputs!$A$40:$B$48,2,TRUE()) -> 0.0419027 | I38: =H38+Inputs!B10 -> 0.1094027 | J38: =SUMIFS(Daily!$G$6:$G$2400,Daily!$B$6:$B$2400,A38) -> 6609.122 | K38: =SUMIFS(Daily!$H$6:$H$2400,Daily!$B$6:$B$2400,A38) -> 1208.2192 | L38: =J38+K38 -> 7817.3412 | M38: =P37 -> 199650.31 | N38: =SUMIFS(Cash_Events!$H$6:$H$20,Cash_Events!$C$6:$C$20,"rAGMF",Cash_Events!$D$6:$D$20,"JV",Cash_Events!$M$6:$M$20,A38) -> 0 | O38: =SUMIFS(Cash_Events!$H$6:$H$20,Cash_Events!$C$6:$C$20,"rAGMF",Cash_Events!$D$6:$D$20,"800S",Cash_Events!$M$6:$M$20,A38) -> 0 | P38: =M38+J38-N38-O38 -> 206259.43 | Q38: =S37 -> 26284.75 | R38: =SUMIFS(Cash_Events!$I$6:$I$20,Cash_Events!$C$6:$C$20,"rAGMF",Cash_Events!$M$6:$M$20,A38) -> 0 | S38: =Q38+K38-R38 -> 27492.969 | T38: =P38+S38 -> 233752.4 | U38: =G38+T38 -> 968752.4 | V38: =V37+L38 -> 418566.17 | W38: =W37+N38+O38+R38 -> 184813.77 | X38: =ROUND(V38-W38-T38,2) -> 0
A39: =EOMONTH(A38,1) -> 45808 | B39: =A38 -> 45777 | C39: =A39-B39 -> 31 | D39: =IF(A39<=EOMONTH(Inputs!$B$18,-1),"Actual","Projection") -> Actual | E39: =G38 -> 735000 | F39: =SUMIFS(Cash_Events!$G$6:$G$20,Cash_Events!$C$6:$C$20,"rAGMF",Cash_Events!$M$6:$M$20,A39) -> 0 | G39: =E39-F39 -> 735000 | H39: =VLOOKUP(A39-1,Inputs!$A$40:$B$48,2,TRUE()) -> 0.0419027 | I39: =H39+Inputs!B10 -> 0.1094027 | J39: =SUMIFS(Daily!$G$6:$G$2400,Daily!$B$6:$B$2400,A39) -> 6829.4261 | K39: =SUMIFS(Daily!$H$6:$H$2400,Daily!$B$6:$B$2400,A39) -> 1248.4932 | L39: =J39+K39 -> 8077.9192 | M39: =P38 -> 206259.43 | N39: =SUMIFS(Cash_Events!$H$6:$H$20,Cash_Events!$C$6:$C$20,"rAGMF",Cash_Events!$D$6:$D$20,"JV",Cash_Events!$M$6:$M$20,A39) -> 0 | O39: =SUMIFS(Cash_Events!$H$6:$H$20,Cash_Events!$C$6:$C$20,"rAGMF",Cash_Events!$D$6:$D$20,"800S",Cash_Events!$M$6:$M$20,A39) -> 0 | P39: =M39+J39-N39-O39 -> 213088.86 | Q39: =S38 -> 27492.969 | R39: =SUMIFS(Cash_Events!$I$6:$I$20,Cash_Events!$C$6:$C$20,"rAGMF",Cash_Events!$M$6:$M$20,A39) -> 0 | S39: =Q39+K39-R39 -> 28741.462 | T39: =P39+S39 -> 241830.32 | U39: =G39+T39 -> 976830.32 | V39: =V38+L39 -> 426644.09 | W39: =W38+N39+O39+R39 -> 184813.77 | X39: =ROUND(V39-W39-T39,2) -> 0
A40: =EOMONTH(A39,1) -> 45838 | B40: =A39 -> 45808 | C40: =A40-B40 -> 30 | D40: =IF(A40<=EOMONTH(Inputs!$B$18,-1),"Actual","Projection") -> Actual | E40: =G39 -> 735000 | F40: =SUMIFS(Cash_Events!$G$6:$G$20,Cash_Events!$C$6:$C$20,"rAGMF",Cash_Events!$M$6:$M$20,A40) -> 0 | G40: =E40-F40 -> 735000 | H40: =VLOOKUP(A40-1,Inputs!$A$40:$B$48,2,TRUE()) -> 0.0419027 | I40: =H40+Inputs!B10 -> 0.1094027 | J40: =SUMIFS(Daily!$G$6:$G$2400,Daily!$B$6:$B$2400,A40) -> 6609.122 | K40: =SUMIFS(Daily!$H$6:$H$2400,Daily!$B$6:$B$2400,A40) -> 1208.2192 | L40: =J40+K40 -> 7817.3412 | M40: =P39 -> 213088.86 | N40: =SUMIFS(Cash_Events!$H$6:$H$20,Cash_Events!$C$6:$C$20,"rAGMF",Cash_Events!$D$6:$D$20,"JV",Cash_Events!$M$6:$M$20,A40) -> 0 | O40: =SUMIFS(Cash_Events!$H$6:$H$20,Cash_Events!$C$6:$C$20,"rAGMF",Cash_Events!$D$6:$D$20,"800S",Cash_Events!$M$6:$M$20,A40) -> 0 | P40: =M40+J40-N40-O40 -> 219697.98 | Q40: =S39 -> 28741.462 | R40: =SUMIFS(Cash_Events!$I$6:$I$20,Cash_Events!$C$6:$C$20,"rAGMF",Cash_Events!$M$6:$M$20,A40) -> 0 | S40: =Q40+K40-R40 -> 29949.681 | T40: =P40+S40 -> 249647.66 | U40: =G40+T40 -> 984647.66 | V40: =V39+L40 -> 434461.43 | W40: =W39+N40+O40+R40 -> 184813.77 | X40: =ROUND(V40-W40-T40,2) -> 0
A41: =EOMONTH(A40,1) -> 45869 | B41: =A40 -> 45838 | C41: =A41-B41 -> 31 | D41: =IF(A41<=EOMONTH(Inputs!$B$18,-1),"Actual","Projection") -> Actual | E41: =G40 -> 735000 | F41: =SUMIFS(Cash_Events!$G$6:$G$20,Cash_Events!$C$6:$C$20,"rAGMF",Cash_Events!$M$6:$M$20,A41) -> 0 | G41: =E41-F41 -> 735000 | H41: =VLOOKUP(A41-1,Inputs!$A$40:$B$48,2,TRUE()) -> 0.0419027 | I41: =H41+Inputs!B10 -> 0.1094027 | J41: =SUMIFS(Daily!$G$6:$G$2400,Daily!$B$6:$B$2400,A41) -> 6829.4261 | K41: =SUMIFS(Daily!$H$6:$H$2400,Daily!$B$6:$B$2400,A41) -> 1248.4932 | L41: =J41+K41 -> 8077.9192 | M41: =P40 -> 219697.98 | N41: =SUMIFS(Cash_Events!$H$6:$H$20,Cash_Events!$C$6:$C$20,"rAGMF",Cash_Events!$D$6:$D$20,"JV",Cash_Events!$M$6:$M$20,A41) -> 0 | O41: =SUMIFS(Cash_Events!$H$6:$H$20,Cash_Events!$C$6:$C$20,"rAGMF",Cash_Events!$D$6:$D$20,"800S",Cash_Events!$M$6:$M$20,A41) -> 0 | P41: =M41+J41-N41-O41 -> 226527.4 | Q41: =S40 -> 29949.681 | R41: =SUMIFS(Cash_Events!$I$6:$I$20,Cash_Events!$C$6:$C$20,"rAGMF",Cash_Events!$M$6:$M$20,A41) -> 0 | S41: =Q41+K41-R41 -> 31198.175 | T41: =P41+S41 -> 257725.58 | U41: =G41+T41 -> 992725.58 | V41: =V40+L41 -> 442539.35 | W41: =W40+N41+O41+R41 -> 184813.77 | X41: =ROUND(V41-W41-T41,2) -> 0
A42: =EOMONTH(A41,1) -> 45900 | B42: =A41 -> 45869 | C42: =A42-B42 -> 31 | D42: =IF(A42<=EOMONTH(Inputs!$B$18,-1),"Actual","Projection") -> Actual | E42: =G41 -> 735000 | F42: =SUMIFS(Cash_Events!$G$6:$G$20,Cash_Events!$C$6:$C$20,"rAGMF",Cash_Events!$M$6:$M$20,A42) -> 0 | G42: =E42-F42 -> 735000 | H42: =VLOOKUP(A42-1,Inputs!$A$40:$B$48,2,TRUE()) -> 0.0419027 | I42: =H42+Inputs!B10 -> 0.1094027 | J42: =SUMIFS(Daily!$G$6:$G$2400,Daily!$B$6:$B$2400,A42) -> 6829.4261 | K42: =SUMIFS(Daily!$H$6:$H$2400,Daily!$B$6:$B$2400,A42) -> 1248.4932 | L42: =J42+K42 -> 8077.9192 | M42: =P41 -> 226527.4 | N42: =SUMIFS(Cash_Events!$H$6:$H$20,Cash_Events!$C$6:$C$20,"rAGMF",Cash_Events!$D$6:$D$20,"JV",Cash_Events!$M$6:$M$20,A42) -> 0 | O42: =SUMIFS(Cash_Events!$H$6:$H$20,Cash_Events!$C$6:$C$20,"rAGMF",Cash_Events!$D$6:$D$20,"800S",Cash_Events!$M$6:$M$20,A42) -> 0 | P42: =M42+J42-N42-O42 -> 233356.83 | Q42: =S41 -> 31198.175 | R42: =SUMIFS(Cash_Events!$I$6:$I$20,Cash_Events!$C$6:$C$20,"rAGMF",Cash_Events!$M$6:$M$20,A42) -> 0 | S42: =Q42+K42-R42 -> 32446.668 | T42: =P42+S42 -> 265803.5 | U42: =G42+T42 -> 1000803.5 | V42: =V41+L42 -> 450617.27 | W42: =W41+N42+O42+R42 -> 184813.77 | X42: =ROUND(V42-W42-T42,2) -> 0
A43: =EOMONTH(A42,1) -> 45930 | B43: =A42 -> 45900 | C43: =A43-B43 -> 30 | D43: =IF(A43<=EOMONTH(Inputs!$B$18,-1),"Actual","Projection") -> Actual | E43: =G42 -> 735000 | F43: =SUMIFS(Cash_Events!$G$6:$G$20,Cash_Events!$C$6:$C$20,"rAGMF",Cash_Events!$M$6:$M$20,A43) -> 0 | G43: =E43-F43 -> 735000 | H43: =VLOOKUP(A43-1,Inputs!$A$40:$B$48,2,TRUE()) -> 0.0396676 | I43: =H43+Inputs!B10 -> 0.1071676 | J43: =SUMIFS(Daily!$G$6:$G$2400,Daily!$B$6:$B$2400,A43) -> 6514.6048 | K43: =SUMIFS(Daily!$H$6:$H$2400,Daily!$B$6:$B$2400,A43) -> 1208.2192 | L43: =J43+K43 -> 7722.824 | M43: =P42 -> 233356.83 | N43: =SUMIFS(Cash_Events!$H$6:$H$20,Cash_Events!$C$6:$C$20,"rAGMF",Cash_Events!$D$6:$D$20,"JV",Cash_Events!$M$6:$M$20,A43) -> 0 | O43: =SUMIFS(Cash_Events!$H$6:$H$20,Cash_Events!$C$6:$C$20,"rAGMF",Cash_Events!$D$6:$D$20,"800S",Cash_Events!$M$6:$M$20,A43) -> 0 | P43: =M43+J43-N43-O43 -> 239871.44 | Q43: =S42 -> 32446.668 | R43: =SUMIFS(Cash_Events!$I$6:$I$20,Cash_Events!$C$6:$C$20,"rAGMF",Cash_Events!$M$6:$M$20,A43) -> 0 | S43: =Q43+K43-R43 -> 33654.887 | T43: =P43+S43 -> 273526.32 | U43: =G43+T43 -> 1008526.3 | V43: =V42+L43 -> 458340.09 | W43: =W42+N43+O43+R43 -> 184813.77 | X43: =ROUND(V43-W43-T43,2) -> 0 | Y43: Coupon missed 09/09/2025
A44: =EOMONTH(A43,1) -> 45961 | B44: =A43 -> 45930 | C44: =A44-B44 -> 31 | D44: =IF(A44<=EOMONTH(Inputs!$B$18,-1),"Actual","Projection") -> Actual | E44: =G43 -> 735000 | F44: =SUMIFS(Cash_Events!$G$6:$G$20,Cash_Events!$C$6:$C$20,"rAGMF",Cash_Events!$M$6:$M$20,A44) -> 0 | G44: =E44-F44 -> 735000 | H44: =VLOOKUP(A44-1,Inputs!$A$40:$B$48,2,TRUE()) -> 0.0396676 | I44: =H44+Inputs!B10 -> 0.1071676 | J44: =SUMIFS(Daily!$G$6:$G$2400,Daily!$B$6:$B$2400,A44) -> 6689.9007 | K44: =SUMIFS(Daily!$H$6:$H$2400,Daily!$B$6:$B$2400,A44) -> 1248.4932 | L44: =J44+K44 -> 7938.3939 | M44: =P43 -> 239871.44 | N44: =SUMIFS(Cash_Events!$H$6:$H$20,Cash_Events!$C$6:$C$20,"rAGMF",Cash_Events!$D$6:$D$20,"JV",Cash_Events!$M$6:$M$20,A44) -> 0 | O44: =SUMIFS(Cash_Events!$H$6:$H$20,Cash_Events!$C$6:$C$20,"rAGMF",Cash_Events!$D$6:$D$20,"800S",Cash_Events!$M$6:$M$20,A44) -> 0 | P44: =M44+J44-N44-O44 -> 246561.34 | Q44: =S43 -> 33654.887 | R44: =SUMIFS(Cash_Events!$I$6:$I$20,Cash_Events!$C$6:$C$20,"rAGMF",Cash_Events!$M$6:$M$20,A44) -> 0 | S44: =Q44+K44-R44 -> 34903.38 | T44: =P44+S44 -> 281464.72 | U44: =G44+T44 -> 1016464.7 | V44: =V43+L44 -> 466278.49 | W44: =W43+N44+O44+R44 -> 184813.77 | X44: =ROUND(V44-W44-T44,2) -> 0
A45: =EOMONTH(A44,1) -> 45991 | B45: =A44 -> 45961 | C45: =A45-B45 -> 30 | D45: =IF(A45<=EOMONTH(Inputs!$B$18,-1),"Actual","Projection") -> Actual | E45: =G44 -> 735000 | F45: =SUMIFS(Cash_Events!$G$6:$G$20,Cash_Events!$C$6:$C$20,"rAGMF",Cash_Events!$M$6:$M$20,A45) -> 0 | G45: =E45-F45 -> 735000 | H45: =VLOOKUP(A45-1,Inputs!$A$40:$B$48,2,TRUE()) -> 0.0396676 | I45: =H45+Inputs!B10 -> 0.1071676 | J45: =SUMIFS(Daily!$G$6:$G$2400,Daily!$B$6:$B$2400,A45) -> 6474.0975 | K45: =SUMIFS(Daily!$H$6:$H$2400,Daily!$B$6:$B$2400,A45) -> 1208.2192 | L45: =J45+K45 -> 7682.3167 | M45: =P44 -> 246561.34 | N45: =SUMIFS(Cash_Events!$H$6:$H$20,Cash_Events!$C$6:$C$20,"rAGMF",Cash_Events!$D$6:$D$20,"JV",Cash_Events!$M$6:$M$20,A45) -> 0 | O45: =SUMIFS(Cash_Events!$H$6:$H$20,Cash_Events!$C$6:$C$20,"rAGMF",Cash_Events!$D$6:$D$20,"800S",Cash_Events!$M$6:$M$20,A45) -> 0 | P45: =M45+J45-N45-O45 -> 253035.43 | Q45: =S44 -> 34903.38 | R45: =SUMIFS(Cash_Events!$I$6:$I$20,Cash_Events!$C$6:$C$20,"rAGMF",Cash_Events!$M$6:$M$20,A45) -> 0 | S45: =Q45+K45-R45 -> 36111.599 | T45: =P45+S45 -> 289147.03 | U45: =G45+T45 -> 1024147 | V45: =V44+L45 -> 473960.8 | W45: =W44+N45+O45+R45 -> 184813.77 | X45: =ROUND(V45-W45-T45,2) -> 0
A46: =EOMONTH(A45,1) -> 46022 | B46: =A45 -> 45991 | C46: =A46-B46 -> 31 | D46: =IF(A46<=EOMONTH(Inputs!$B$18,-1),"Actual","Projection") -> Actual | E46: =G45 -> 735000 | F46: =SUMIFS(Cash_Events!$G$6:$G$20,Cash_Events!$C$6:$C$20,"rAGMF",Cash_Events!$M$6:$M$20,A46) -> 0 | G46: =E46-F46 -> 735000 | H46: =VLOOKUP(A46-1,Inputs!$A$40:$B$48,2,TRUE()) -> 0.0396676 | I46: =H46+Inputs!B10 -> 0.1071676 | J46: =SUMIFS(Daily!$G$6:$G$2400,Daily!$B$6:$B$2400,A46) -> 6689.9007 | K46: =SUMIFS(Daily!$H$6:$H$2400,Daily!$B$6:$B$2400,A46) -> 1248.4932 | L46: =J46+K46 -> 7938.3939 | M46: =P45 -> 253035.43 | N46: =SUMIFS(Cash_Events!$H$6:$H$20,Cash_Events!$C$6:$C$20,"rAGMF",Cash_Events!$D$6:$D$20,"JV",Cash_Events!$M$6:$M$20,A46) -> 0 | O46: =SUMIFS(Cash_Events!$H$6:$H$20,Cash_Events!$C$6:$C$20,"rAGMF",Cash_Events!$D$6:$D$20,"800S",Cash_Events!$M$6:$M$20,A46) -> 0 | P46: =M46+J46-N46-O46 -> 259725.33 | Q46: =S45 -> 36111.599 | R46: =SUMIFS(Cash_Events!$I$6:$I$20,Cash_Events!$C$6:$C$20,"rAGMF",Cash_Events!$M$6:$M$20,A46) -> 0 | S46: =Q46+K46-R46 -> 37360.092 | T46: =P46+S46 -> 297085.43 | U46: =G46+T46 -> 1032085.4 | V46: =V45+L46 -> 481899.2 | W46: =W45+N46+O46+R46 -> 184813.77 | X46: =ROUND(V46-W46-T46,2) -> 0
A47: =EOMONTH(A46,1) -> 46053 | B47: =A46 -> 46022 | C47: =A47-B47 -> 31 | D47: =IF(A47<=EOMONTH(Inputs!$B$18,-1),"Actual","Projection") -> Actual | E47: =G46 -> 735000 | F47: =SUMIFS(Cash_Events!$G$6:$G$20,Cash_Events!$C$6:$C$20,"rAGMF",Cash_Events!$M$6:$M$20,A47) -> 0 | G47: =E47-F47 -> 735000 | H47: =VLOOKUP(A47-1,Inputs!$A$40:$B$48,2,TRUE()) -> 0.0396676 | I47: =H47+Inputs!B10 -> 0.1071676 | J47: =SUMIFS(Daily!$G$6:$G$2400,Daily!$B$6:$B$2400,A47) -> 6689.9007 | K47: =SUMIFS(Daily!$H$6:$H$2400,Daily!$B$6:$B$2400,A47) -> 1248.4932 | L47: =J47+K47 -> 7938.3939 | M47: =P46 -> 259725.33 | N47: =SUMIFS(Cash_Events!$H$6:$H$20,Cash_Events!$C$6:$C$20,"rAGMF",Cash_Events!$D$6:$D$20,"JV",Cash_Events!$M$6:$M$20,A47) -> 0 | O47: =SUMIFS(Cash_Events!$H$6:$H$20,Cash_Events!$C$6:$C$20,"rAGMF",Cash_Events!$D$6:$D$20,"800S",Cash_Events!$M$6:$M$20,A47) -> 0 | P47: =M47+J47-N47-O47 -> 266415.24 | Q47: =S46 -> 37360.092 | R47: =SUMIFS(Cash_Events!$I$6:$I$20,Cash_Events!$C$6:$C$20,"rAGMF",Cash_Events!$M$6:$M$20,A47) -> 0 | S47: =Q47+K47-R47 -> 38608.586 | T47: =P47+S47 -> 305023.82 | U47: =G47+T47 -> 1040023.8 | V47: =V46+L47 -> 489837.59 | W47: =W46+N47+O47+R47 -> 184813.77 | X47: =ROUND(V47-W47-T47,2) -> 0
A48: =EOMONTH(A47,1) -> 46081 | B48: =A47 -> 46053 | C48: =A48-B48 -> 28 | D48: =IF(A48<=EOMONTH(Inputs!$B$18,-1),"Actual","Projection") -> Actual | E48: =G47 -> 735000 | F48: =SUMIFS(Cash_Events!$G$6:$G$20,Cash_Events!$C$6:$C$20,"rAGMF",Cash_Events!$M$6:$M$20,A48) -> 0 | G48: =E48-F48 -> 735000 | H48: =VLOOKUP(A48-1,Inputs!$A$40:$B$48,2,TRUE()) -> 0.0396676 | I48: =H48+Inputs!B10 -> 0.1071676 | J48: =SUMIFS(Daily!$G$6:$G$2400,Daily!$B$6:$B$2400,A48) -> 6042.491 | K48: =SUMIFS(Daily!$H$6:$H$2400,Daily!$B$6:$B$2400,A48) -> 1127.6712 | L48: =J48+K48 -> 7170.1622 | M48: =P47 -> 266415.24 | N48: =SUMIFS(Cash_Events!$H$6:$H$20,Cash_Events!$C$6:$C$20,"rAGMF",Cash_Events!$D$6:$D$20,"JV",Cash_Events!$M$6:$M$20,A48) -> 0 | O48: =SUMIFS(Cash_Events!$H$6:$H$20,Cash_Events!$C$6:$C$20,"rAGMF",Cash_Events!$D$6:$D$20,"800S",Cash_Events!$M$6:$M$20,A48) -> 0 | P48: =M48+J48-N48-O48 -> 272457.73 | Q48: =S47 -> 38608.586 | R48: =SUMIFS(Cash_Events!$I$6:$I$20,Cash_Events!$C$6:$C$20,"rAGMF",Cash_Events!$M$6:$M$20,A48) -> 0 | S48: =Q48+K48-R48 -> 39736.257 | T48: =P48+S48 -> 312193.98 | U48: =G48+T48 -> 1047194 | V48: =V47+L48 -> 497007.75 | W48: =W47+N48+O48+R48 -> 184813.77 | X48: =ROUND(V48-W48-T48,2) -> 0
A49: =EOMONTH(A48,1) -> 46112 | B49: =A48 -> 46081 | C49: =A49-B49 -> 31 | D49: =IF(A49<=EOMONTH(Inputs!$B$18,-1),"Actual","Projection") -> Actual | E49: =G48 -> 735000 | F49: =SUMIFS(Cash_Events!$G$6:$G$20,Cash_Events!$C$6:$C$20,"rAGMF",Cash_Events!$M$6:$M$20,A49) -> 0 | G49: =E49-F49 -> 735000 | H49: =VLOOKUP(A49-1,Inputs!$A$40:$B$48,2,TRUE()) -> 0.0363225 | I49: =H49+Inputs!B10 -> 0.1038225 | J49: =SUMIFS(Daily!$G$6:$G$2400,Daily!$B$6:$B$2400,A49) -> 6541.7082 | K49: =SUMIFS(Daily!$H$6:$H$2400,Daily!$B$6:$B$2400,A49) -> 1248.4932 | L49: =J49+K49 -> 7790.2014 | M49: =P48 -> 272457.73 | N49: =SUMIFS(Cash_Events!$H$6:$H$20,Cash_Events!$C$6:$C$20,"rAGMF",Cash_Events!$D$6:$D$20,"JV",Cash_Events!$M$6:$M$20,A49) -> 0 | O49: =SUMIFS(Cash_Events!$H$6:$H$20,Cash_Events!$C$6:$C$20,"rAGMF",Cash_Events!$D$6:$D$20,"800S",Cash_Events!$M$6:$M$20,A49) -> 0 | P49: =M49+J49-N49-O49 -> 278999.43 | Q49: =S48 -> 39736.257 | R49: =SUMIFS(Cash_Events!$I$6:$I$20,Cash_Events!$C$6:$C$20,"rAGMF",Cash_Events!$M$6:$M$20,A49) -> 0 | S49: =Q49+K49-R49 -> 40984.75 | T49: =P49+S49 -> 319984.18 | U49: =G49+T49 -> 1054984.2 | V49: =V48+L49 -> 504797.95 | W49: =W48+N49+O49+R49 -> 184813.77 | X49: =ROUND(V49-W49-T49,2) -> 0 | Y49: Coupon missed 09/03/2026
A50: =EOMONTH(A49,1) -> 46142 | B50: =A49 -> 46112 | C50: =A50-B50 -> 30 | D50: =IF(A50<=EOMONTH(Inputs!$B$18,-1),"Actual","Projection") -> Actual | E50: =G49 -> 735000 | F50: =SUMIFS(Cash_Events!$G$6:$G$20,Cash_Events!$C$6:$C$20,"rAGMF",Cash_Events!$M$6:$M$20,A50) -> 0 | G50: =E50-F50 -> 735000 | H50: =VLOOKUP(A50-1,Inputs!$A$40:$B$48,2,TRUE()) -> 0.0363225 | I50: =H50+Inputs!B10 -> 0.1038225 | J50: =SUMIFS(Daily!$G$6:$G$2400,Daily!$B$6:$B$2400,A50) -> 6272.0168 | K50: =SUMIFS(Daily!$H$6:$H$2400,Daily!$B$6:$B$2400,A50) -> 1208.2192 | L50: =J50+K50 -> 7480.236 | M50: =P49 -> 278999.43 | N50: =SUMIFS(Cash_Events!$H$6:$H$20,Cash_Events!$C$6:$C$20,"rAGMF",Cash_Events!$D$6:$D$20,"JV",Cash_Events!$M$6:$M$20,A50) -> 0 | O50: =SUMIFS(Cash_Events!$H$6:$H$20,Cash_Events!$C$6:$C$20,"rAGMF",Cash_Events!$D$6:$D$20,"800S",Cash_Events!$M$6:$M$20,A50) -> 0 | P50: =M50+J50-N50-O50 -> 285271.45 | Q50: =S49 -> 40984.75 | R50: =SUMIFS(Cash_Events!$I$6:$I$20,Cash_Events!$C$6:$C$20,"rAGMF",Cash_Events!$M$6:$M$20,A50) -> 0 | S50: =Q50+K50-R50 -> 42192.969 | T50: =P50+S50 -> 327464.42 | U50: =G50+T50 -> 1062464.4 | V50: =V49+L50 -> 512278.19 | W50: =W49+N50+O50+R50 -> 184813.77 | X50: =ROUND(V50-W50-T50,2) -> 0
A51: =EOMONTH(A50,1) -> 46173 | B51: =A50 -> 46142 | C51: =A51-B51 -> 31 | D51: =IF(A51<=EOMONTH(Inputs!$B$18,-1),"Actual","Projection") -> Actual | E51: =G50 -> 735000 | F51: =SUMIFS(Cash_Events!$G$6:$G$20,Cash_Events!$C$6:$C$20,"rAGMF",Cash_Events!$M$6:$M$20,A51) -> 0 | G51: =E51-F51 -> 735000 | H51: =VLOOKUP(A51-1,Inputs!$A$40:$B$48,2,TRUE()) -> 0.0363225 | I51: =H51+Inputs!B10 -> 0.1038225 | J51: =SUMIFS(Daily!$G$6:$G$2400,Daily!$B$6:$B$2400,A51) -> 6481.084 | K51: =SUMIFS(Daily!$H$6:$H$2400,Daily!$B$6:$B$2400,A51) -> 1248.4932 | L51: =J51+K51 -> 7729.5772 | M51: =P50 -> 285271.45 | N51: =SUMIFS(Cash_Events!$H$6:$H$20,Cash_Events!$C$6:$C$20,"rAGMF",Cash_Events!$D$6:$D$20,"JV",Cash_Events!$M$6:$M$20,A51) -> 0 | O51: =SUMIFS(Cash_Events!$H$6:$H$20,Cash_Events!$C$6:$C$20,"rAGMF",Cash_Events!$D$6:$D$20,"800S",Cash_Events!$M$6:$M$20,A51) -> 0 | P51: =M51+J51-N51-O51 -> 291752.54 | Q51: =S50 -> 42192.969 | R51: =SUMIFS(Cash_Events!$I$6:$I$20,Cash_Events!$C$6:$C$20,"rAGMF",Cash_Events!$M$6:$M$20,A51) -> 0 | S51: =Q51+K51-R51 -> 43441.462 | T51: =P51+S51 -> 335194 | U51: =G51+T51 -> 1070194 | V51: =V50+L51 -> 520007.77 | W51: =W50+N51+O51+R51 -> 184813.77 | X51: =ROUND(V51-W51-T51,2) -> 0
A52: =EOMONTH(A51,1) -> 46203 | B52: =A51 -> 46173 | C52: =A52-B52 -> 30 | D52: =IF(A52<=EOMONTH(Inputs!$B$18,-1),"Actual","Projection") -> Actual | E52: =G51 -> 735000 | F52: =SUMIFS(Cash_Events!$G$6:$G$20,Cash_Events!$C$6:$C$20,"rAGMF",Cash_Events!$M$6:$M$20,A52) -> 0 | G52: =E52-F52 -> 735000 | H52: =VLOOKUP(A52-1,Inputs!$A$40:$B$48,2,TRUE()) -> 0.0363225 | I52: =H52+Inputs!B10 -> 0.1038225 | J52: =SUMIFS(Daily!$G$6:$G$2400,Daily!$B$6:$B$2400,A52) -> 6272.0168 | K52: =SUMIFS(Daily!$H$6:$H$2400,Daily!$B$6:$B$2400,A52) -> 1208.2192 | L52: =J52+K52 -> 7480.236 | M52: =P51 -> 291752.54 | N52: =SUMIFS(Cash_Events!$H$6:$H$20,Cash_Events!$C$6:$C$20,"rAGMF",Cash_Events!$D$6:$D$20,"JV",Cash_Events!$M$6:$M$20,A52) -> 0 | O52: =SUMIFS(Cash_Events!$H$6:$H$20,Cash_Events!$C$6:$C$20,"rAGMF",Cash_Events!$D$6:$D$20,"800S",Cash_Events!$M$6:$M$20,A52) -> 0 | P52: =M52+J52-N52-O52 -> 298024.55 | Q52: =S51 -> 43441.462 | R52: =SUMIFS(Cash_Events!$I$6:$I$20,Cash_Events!$C$6:$C$20,"rAGMF",Cash_Events!$M$6:$M$20,A52) -> 0 | S52: =Q52+K52-R52 -> 44649.681 | T52: =P52+S52 -> 342674.23 | U52: =G52+T52 -> 1077674.2 | V52: =V51+L52 -> 527488 | W52: =W51+N52+O52+R52 -> 184813.77 | X52: =ROUND(V52-W52-T52,2) -> 0 | Y52: LENDER CUT-OFF - ties to amendment cl. 3.8
A53: =EOMONTH(A52,1) -> 46234 | B53: =A52 -> 46203 | C53: =A53-B53 -> 31 | D53: =IF(A53<=EOMONTH(Inputs!$B$18,-1),"Actual","Projection") -> Actual | E53: =G52 -> 735000 | F53: =SUMIFS(Cash_Events!$G$6:$G$20,Cash_Events!$C$6:$C$20,"rAGMF",Cash_Events!$M$6:$M$20,A53) -> 0 | G53: =E53-F53 -> 735000 | H53: =VLOOKUP(A53-1,Inputs!$A$40:$B$48,2,TRUE()) -> 0.0363225 | I53: =H53+Inputs!B10 -> 0.1038225 | J53: =SUMIFS(Daily!$G$6:$G$2400,Daily!$B$6:$B$2400,A53) -> 6481.084 | K53: =SUMIFS(Daily!$H$6:$H$2400,Daily!$B$6:$B$2400,A53) -> 1248.4932 | L53: =J53+K53 -> 7729.5772 | M53: =P52 -> 298024.55 | N53: =SUMIFS(Cash_Events!$H$6:$H$20,Cash_Events!$C$6:$C$20,"rAGMF",Cash_Events!$D$6:$D$20,"JV",Cash_Events!$M$6:$M$20,A53) -> 0 | O53: =SUMIFS(Cash_Events!$H$6:$H$20,Cash_Events!$C$6:$C$20,"rAGMF",Cash_Events!$D$6:$D$20,"800S",Cash_Events!$M$6:$M$20,A53) -> 0 | P53: =M53+J53-N53-O53 -> 304505.64 | Q53: =S52 -> 44649.681 | R53: =SUMIFS(Cash_Events!$I$6:$I$20,Cash_Events!$C$6:$C$20,"rAGMF",Cash_Events!$M$6:$M$20,A53) -> 0 | S53: =Q53+K53-R53 -> 45898.175 | T53: =P53+S53 -> 350403.81 | U53: =G53+T53 -> 1085403.8 | V53: =V52+L53 -> 535217.58 | W53: =W52+N53+O53+R53 -> 184813.77 | X53: =ROUND(V53-W53-T53,2) -> 0
A54: =EOMONTH(A53,1) -> 46265 | B54: =A53 -> 46234 | C54: =A54-B54 -> 31 | D54: =IF(A54<=EOMONTH(Inputs!$B$18,-1),"Actual","Projection") -> Actual | E54: =G53 -> 735000 | F54: =SUMIFS(Cash_Events!$G$6:$G$20,Cash_Events!$C$6:$C$20,"rAGMF",Cash_Events!$M$6:$M$20,A54) -> 0 | G54: =E54-F54 -> 735000 | H54: =VLOOKUP(A54-1,Inputs!$A$40:$B$48,2,TRUE()) -> 0.0363225 | I54: =H54+Inputs!B10 -> 0.1038225 | J54: =SUMIFS(Daily!$G$6:$G$2400,Daily!$B$6:$B$2400,A54) -> 6481.084 | K54: =SUMIFS(Daily!$H$6:$H$2400,Daily!$B$6:$B$2400,A54) -> 1248.4932 | L54: =J54+K54 -> 7729.5772 | M54: =P53 -> 304505.64 | N54: =SUMIFS(Cash_Events!$H$6:$H$20,Cash_Events!$C$6:$C$20,"rAGMF",Cash_Events!$D$6:$D$20,"JV",Cash_Events!$M$6:$M$20,A54) -> 0 | O54: =SUMIFS(Cash_Events!$H$6:$H$20,Cash_Events!$C$6:$C$20,"rAGMF",Cash_Events!$D$6:$D$20,"800S",Cash_Events!$M$6:$M$20,A54) -> 0 | P54: =M54+J54-N54-O54 -> 310986.72 | Q54: =S53 -> 45898.175 | R54: =SUMIFS(Cash_Events!$I$6:$I$20,Cash_Events!$C$6:$C$20,"rAGMF",Cash_Events!$M$6:$M$20,A54) -> 0 | S54: =Q54+K54-R54 -> 47146.668 | T54: =P54+S54 -> 358133.39 | U54: =G54+T54 -> 1093133.4 | V54: =V53+L54 -> 542947.16 | W54: =W53+N54+O54+R54 -> 184813.77 | X54: =ROUND(V54-W54-T54,2) -> 0
A55: =EOMONTH(A54,1) -> 46295 | B55: =A54 -> 46265 | C55: =A55-B55 -> 30 | D55: =IF(A55<=EOMONTH(Inputs!$B$18,-1),"Actual","Projection") -> Actual | E55: =G54 -> 735000 | F55: =SUMIFS(Cash_Events!$G$6:$G$20,Cash_Events!$C$6:$C$20,"rAGMF",Cash_Events!$M$6:$M$20,A55) -> 0 | G55: =E55-F55 -> 735000 | H55: =VLOOKUP(A55-1,Inputs!$A$40:$B$48,2,TRUE()) -> 0.0363225 | I55: =H55+Inputs!B10 -> 0.1038225 | J55: =SUMIFS(Daily!$G$6:$G$2400,Daily!$B$6:$B$2400,A55) -> 6272.0168 | K55: =SUMIFS(Daily!$H$6:$H$2400,Daily!$B$6:$B$2400,A55) -> 1208.2192 | L55: =J55+K55 -> 7480.236 | M55: =P54 -> 310986.72 | N55: =SUMIFS(Cash_Events!$H$6:$H$20,Cash_Events!$C$6:$C$20,"rAGMF",Cash_Events!$D$6:$D$20,"JV",Cash_Events!$M$6:$M$20,A55) -> 0 | O55: =SUMIFS(Cash_Events!$H$6:$H$20,Cash_Events!$C$6:$C$20,"rAGMF",Cash_Events!$D$6:$D$20,"800S",Cash_Events!$M$6:$M$20,A55) -> 0 | P55: =M55+J55-N55-O55 -> 317258.74 | Q55: =S54 -> 47146.668 | R55: =SUMIFS(Cash_Events!$I$6:$I$20,Cash_Events!$C$6:$C$20,"rAGMF",Cash_Events!$M$6:$M$20,A55) -> 0 | S55: =Q55+K55-R55 -> 48354.887 | T55: =P55+S55 -> 365613.62 | U55: =G55+T55 -> 1100613.6 | V55: =V54+L55 -> 550427.39 | W55: =W54+N55+O55+R55 -> 184813.77 | X55: =ROUND(V55-W55-T55,2) -> 0 | Y55: Coupon missed 09/09/2026 (amendment: due 15/09/2026)
A56: =EOMONTH(A55,1) -> 46326 | B56: =A55 -> 46295 | C56: =A56-B56 -> 31 | D56: =IF(A56<=EOMONTH(Inputs!$B$18,-1),"Actual","Projection") -> Projection | E56: =G55 -> 735000 | F56: =SUMIFS(Cash_Events!$G$6:$G$20,Cash_Events!$C$6:$C$20,"rAGMF",Cash_Events!$M$6:$M$20,A56) -> 0 | G56: =E56-F56 -> 735000 | H56: =VLOOKUP(A56-1,Inputs!$A$40:$B$48,2,TRUE()) -> 0.0363225 | I56: =H56+Inputs!B10 -> 0.1038225 | J56: =SUMIFS(Daily!$G$6:$G$2400,Daily!$B$6:$B$2400,A56) -> 6481.084 | K56: =SUMIFS(Daily!$H$6:$H$2400,Daily!$B$6:$B$2400,A56) -> 1248.4932 | L56: =J56+K56 -> 7729.5772 | M56: =P55 -> 317258.74 | N56: =SUMIFS(Cash_Events!$H$6:$H$20,Cash_Events!$C$6:$C$20,"rAGMF",Cash_Events!$D$6:$D$20,"JV",Cash_Events!$M$6:$M$20,A56) -> 0 | O56: =SUMIFS(Cash_Events!$H$6:$H$20,Cash_Events!$C$6:$C$20,"rAGMF",Cash_Events!$D$6:$D$20,"800S",Cash_Events!$M$6:$M$20,A56) -> 0 | P56: =M56+J56-N56-O56 -> 323739.82 | Q56: =S55 -> 48354.887 | R56: =SUMIFS(Cash_Events!$I$6:$I$20,Cash_Events!$C$6:$C$20,"rAGMF",Cash_Events!$M$6:$M$20,A56) -> 0 | S56: =Q56+K56-R56 -> 49603.38 | T56: =P56+S56 -> 373343.2 | U56: =G56+T56 -> 1108343.2 | V56: =V55+L56 -> 558156.97 | W56: =W55+N56+O56+R56 -> 184813.77 | X56: =ROUND(V56-W56-T56,2) -> 0
A57: =EOMONTH(A56,1) -> 46356 | B57: =A56 -> 46326 | C57: =A57-B57 -> 30 | D57: =IF(A57<=EOMONTH(Inputs!$B$18,-1),"Actual","Projection") -> Projection | E57: =G56 -> 735000 | F57: =SUMIFS(Cash_Events!$G$6:$G$20,Cash_Events!$C$6:$C$20,"rAGMF",Cash_Events!$M$6:$M$20,A57) -> 0 | G57: =E57-F57 -> 735000 | H57: =VLOOKUP(A57-1,Inputs!$A$40:$B$48,2,TRUE()) -> 0.0363225 | I57: =H57+Inputs!B10 -> 0.1038225 | J57: =SUMIFS(Daily!$G$6:$G$2400,Daily!$B$6:$B$2400,A57) -> 6272.0168 | K57: =SUMIFS(Daily!$H$6:$H$2400,Daily!$B$6:$B$2400,A57) -> 1208.2192 | L57: =J57+K57 -> 7480.236 | M57: =P56 -> 323739.82 | N57: =SUMIFS(Cash_Events!$H$6:$H$20,Cash_Events!$C$6:$C$20,"rAGMF",Cash_Events!$D$6:$D$20,"JV",Cash_Events!$M$6:$M$20,A57) -> 0 | O57: =SUMIFS(Cash_Events!$H$6:$H$20,Cash_Events!$C$6:$C$20,"rAGMF",Cash_Events!$D$6:$D$20,"800S",Cash_Events!$M$6:$M$20,A57) -> 0 | P57: =M57+J57-N57-O57 -> 330011.84 | Q57: =S56 -> 49603.38 | R57: =SUMIFS(Cash_Events!$I$6:$I$20,Cash_Events!$C$6:$C$20,"rAGMF",Cash_Events!$M$6:$M$20,A57) -> 0 | S57: =Q57+K57-R57 -> 50811.599 | T57: =P57+S57 -> 380823.44 | U57: =G57+T57 -> 1115823.4 | V57: =V56+L57 -> 565637.21 | W57: =W56+N57+O57+R57 -> 184813.77 | X57: =ROUND(V57-W57-T57,2) -> 0
A58: =EOMONTH(A57,1) -> 46387 | B58: =A57 -> 46356 | C58: =A58-B58 -> 31 | D58: =IF(A58<=EOMONTH(Inputs!$B$18,-1),"Actual","Projection") -> Projection | E58: =G57 -> 735000 | F58: =SUMIFS(Cash_Events!$G$6:$G$20,Cash_Events!$C$6:$C$20,"rAGMF",Cash_Events!$M$6:$M$20,A58) -> 0 | G58: =E58-F58 -> 735000 | H58: =VLOOKUP(A58-1,Inputs!$A$40:$B$48,2,TRUE()) -> 0.0363225 | I58: =H58+Inputs!B10 -> 0.1038225 | J58: =SUMIFS(Daily!$G$6:$G$2400,Daily!$B$6:$B$2400,A58) -> 6481.084 | K58: =SUMIFS(Daily!$H$6:$H$2400,Daily!$B$6:$B$2400,A58) -> 1248.4932 | L58: =J58+K58 -> 7729.5772 | M58: =P57 -> 330011.84 | N58: =SUMIFS(Cash_Events!$H$6:$H$20,Cash_Events!$C$6:$C$20,"rAGMF",Cash_Events!$D$6:$D$20,"JV",Cash_Events!$M$6:$M$20,A58) -> 0 | O58: =SUMIFS(Cash_Events!$H$6:$H$20,Cash_Events!$C$6:$C$20,"rAGMF",Cash_Events!$D$6:$D$20,"800S",Cash_Events!$M$6:$M$20,A58) -> 0 | P58: =M58+J58-N58-O58 -> 336492.92 | Q58: =S57 -> 50811.599 | R58: =SUMIFS(Cash_Events!$I$6:$I$20,Cash_Events!$C$6:$C$20,"rAGMF",Cash_Events!$M$6:$M$20,A58) -> 0 | S58: =Q58+K58-R58 -> 52060.092 | T58: =P58+S58 -> 388553.01 | U58: =G58+T58 -> 1123553 | V58: =V57+L58 -> 573366.78 | W58: =W57+N58+O58+R58 -> 184813.77 | X58: =ROUND(V58-W58-T58,2) -> 0
A59: =EOMONTH(A58,1) -> 46418 | B59: =A58 -> 46387 | C59: =A59-B59 -> 31 | D59: =IF(A59<=EOMONTH(Inputs!$B$18,-1),"Actual","Projection") -> Projection | E59: =G58 -> 735000 | F59: =SUMIFS(Cash_Events!$G$6:$G$20,Cash_Events!$C$6:$C$20,"rAGMF",Cash_Events!$M$6:$M$20,A59) -> 0 | G59: =E59-F59 -> 735000 | H59: =VLOOKUP(A59-1,Inputs!$A$40:$B$48,2,TRUE()) -> 0.0363225 | I59: =H59+Inputs!B10 -> 0.1038225 | J59: =SUMIFS(Daily!$G$6:$G$2400,Daily!$B$6:$B$2400,A59) -> 6481.084 | K59: =SUMIFS(Daily!$H$6:$H$2400,Daily!$B$6:$B$2400,A59) -> 1248.4932 | L59: =J59+K59 -> 7729.5772 | M59: =P58 -> 336492.92 | N59: =SUMIFS(Cash_Events!$H$6:$H$20,Cash_Events!$C$6:$C$20,"rAGMF",Cash_Events!$D$6:$D$20,"JV",Cash_Events!$M$6:$M$20,A59) -> 0 | O59: =SUMIFS(Cash_Events!$H$6:$H$20,Cash_Events!$C$6:$C$20,"rAGMF",Cash_Events!$D$6:$D$20,"800S",Cash_Events!$M$6:$M$20,A59) -> 0 | P59: =M59+J59-N59-O59 -> 342974.01 | Q59: =S58 -> 52060.092 | R59: =SUMIFS(Cash_Events!$I$6:$I$20,Cash_Events!$C$6:$C$20,"rAGMF",Cash_Events!$M$6:$M$20,A59) -> 0 | S59: =Q59+K59-R59 -> 53308.586 | T59: =P59+S59 -> 396282.59 | U59: =G59+T59 -> 1131282.6 | V59: =V58+L59 -> 581096.36 | W59: =W58+N59+O59+R59 -> 184813.77 | X59: =ROUND(V59-W59-T59,2) -> 0
A60: =EOMONTH(A59,1) -> 46446 | B60: =A59 -> 46418 | C60: =A60-B60 -> 28 | D60: =IF(A60<=EOMONTH(Inputs!$B$18,-1),"Actual","Projection") -> Projection | E60: =G59 -> 735000 | F60: =SUMIFS(Cash_Events!$G$6:$G$20,Cash_Events!$C$6:$C$20,"rAGMF",Cash_Events!$M$6:$M$20,A60) -> 0 | G60: =E60-F60 -> 735000 | H60: =VLOOKUP(A60-1,Inputs!$A$40:$B$48,2,TRUE()) -> 0.0363225 | I60: =H60+Inputs!B10 -> 0.1038225 | J60: =SUMIFS(Daily!$G$6:$G$2400,Daily!$B$6:$B$2400,A60) -> 5853.8823 | K60: =SUMIFS(Daily!$H$6:$H$2400,Daily!$B$6:$B$2400,A60) -> 1127.6712 | L60: =J60+K60 -> 6981.5536 | M60: =P59 -> 342974.01 | N60: =SUMIFS(Cash_Events!$H$6:$H$20,Cash_Events!$C$6:$C$20,"rAGMF",Cash_Events!$D$6:$D$20,"JV",Cash_Events!$M$6:$M$20,A60) -> 0 | O60: =SUMIFS(Cash_Events!$H$6:$H$20,Cash_Events!$C$6:$C$20,"rAGMF",Cash_Events!$D$6:$D$20,"800S",Cash_Events!$M$6:$M$20,A60) -> 0 | P60: =M60+J60-N60-O60 -> 348827.89 | Q60: =S59 -> 53308.586 | R60: =SUMIFS(Cash_Events!$I$6:$I$20,Cash_Events!$C$6:$C$20,"rAGMF",Cash_Events!$M$6:$M$20,A60) -> 0 | S60: =Q60+K60-R60 -> 54436.257 | T60: =P60+S60 -> 403264.14 | U60: =G60+T60 -> 1138264.1 | V60: =V59+L60 -> 588077.91 | W60: =W59+N60+O60+R60 -> 184813.77 | X60: =ROUND(V60-W60-T60,2) -> 0
A61: =EOMONTH(A60,1) -> 46477 | B61: =A60 -> 46446 | C61: =A61-B61 -> 31 | D61: =IF(A61<=EOMONTH(Inputs!$B$18,-1),"Actual","Projection") -> Projection | E61: =G60 -> 735000 | F61: =SUMIFS(Cash_Events!$G$6:$G$20,Cash_Events!$C$6:$C$20,"rAGMF",Cash_Events!$M$6:$M$20,A61) -> 0 | G61: =E61-F61 -> 735000 | H61: =VLOOKUP(A61-1,Inputs!$A$40:$B$48,2,TRUE()) -> 0.0363225 | I61: =H61+Inputs!B10 -> 0.1038225 | J61: =SUMIFS(Daily!$G$6:$G$2400,Daily!$B$6:$B$2400,A61) -> 6481.084 | K61: =SUMIFS(Daily!$H$6:$H$2400,Daily!$B$6:$B$2400,A61) -> 1248.4932 | L61: =J61+K61 -> 7729.5772 | M61: =P60 -> 348827.89 | N61: =SUMIFS(Cash_Events!$H$6:$H$20,Cash_Events!$C$6:$C$20,"rAGMF",Cash_Events!$D$6:$D$20,"JV",Cash_Events!$M$6:$M$20,A61) -> 0 | O61: =SUMIFS(Cash_Events!$H$6:$H$20,Cash_Events!$C$6:$C$20,"rAGMF",Cash_Events!$D$6:$D$20,"800S",Cash_Events!$M$6:$M$20,A61) -> 0 | P61: =M61+J61-N61-O61 -> 355308.97 | Q61: =S60 -> 54436.257 | R61: =SUMIFS(Cash_Events!$I$6:$I$20,Cash_Events!$C$6:$C$20,"rAGMF",Cash_Events!$M$6:$M$20,A61) -> 0 | S61: =Q61+K61-R61 -> 55684.75 | T61: =P61+S61 -> 410993.72 | U61: =G61+T61 -> 1145993.7 | V61: =V60+L61 -> 595807.49 | W61: =W60+N61+O61+R61 -> 184813.77 | X61: =ROUND(V61-W61-T61,2) -> 0
A62: =EOMONTH(A61,1) -> 46507 | B62: =A61 -> 46477 | C62: =A62-B62 -> 30 | D62: =IF(A62<=EOMONTH(Inputs!$B$18,-1),"Actual","Projection") -> Projection | E62: =G61 -> 735000 | F62: =SUMIFS(Cash_Events!$G$6:$G$20,Cash_Events!$C$6:$C$20,"rAGMF",Cash_Events!$M$6:$M$20,A62) -> 0 | G62: =E62-F62 -> 735000 | H62: =VLOOKUP(A62-1,Inputs!$A$40:$B$48,2,TRUE()) -> 0.0363225 | I62: =H62+Inputs!B10 -> 0.1038225 | J62: =SUMIFS(Daily!$G$6:$G$2400,Daily!$B$6:$B$2400,A62) -> 6272.0168 | K62: =SUMIFS(Daily!$H$6:$H$2400,Daily!$B$6:$B$2400,A62) -> 1208.2192 | L62: =J62+K62 -> 7480.236 | M62: =P61 -> 355308.97 | N62: =SUMIFS(Cash_Events!$H$6:$H$20,Cash_Events!$C$6:$C$20,"rAGMF",Cash_Events!$D$6:$D$20,"JV",Cash_Events!$M$6:$M$20,A62) -> 0 | O62: =SUMIFS(Cash_Events!$H$6:$H$20,Cash_Events!$C$6:$C$20,"rAGMF",Cash_Events!$D$6:$D$20,"800S",Cash_Events!$M$6:$M$20,A62) -> 0 | P62: =M62+J62-N62-O62 -> 361580.99 | Q62: =S61 -> 55684.75 | R62: =SUMIFS(Cash_Events!$I$6:$I$20,Cash_Events!$C$6:$C$20,"rAGMF",Cash_Events!$M$6:$M$20,A62) -> 0 | S62: =Q62+K62-R62 -> 56892.969 | T62: =P62+S62 -> 418473.96 | U62: =G62+T62 -> 1153474 | V62: =V61+L62 -> 603287.73 | W62: =W61+N62+O62+R62 -> 184813.77 | X62: =ROUND(V62-W62-T62,2) -> 0
A63: =EOMONTH(A62,1) -> 46538 | B63: =A62 -> 46507 | C63: =A63-B63 -> 31 | D63: =IF(A63<=EOMONTH(Inputs!$B$18,-1),"Actual","Projection") -> Projection | E63: =G62 -> 735000 | F63: =SUMIFS(Cash_Events!$G$6:$G$20,Cash_Events!$C$6:$C$20,"rAGMF",Cash_Events!$M$6:$M$20,A63) -> 0 | G63: =E63-F63 -> 735000 | H63: =VLOOKUP(A63-1,Inputs!$A$40:$B$48,2,TRUE()) -> 0.0363225 | I63: =H63+Inputs!B10 -> 0.1038225 | J63: =SUMIFS(Daily!$G$6:$G$2400,Daily!$B$6:$B$2400,A63) -> 6481.084 | K63: =SUMIFS(Daily!$H$6:$H$2400,Daily!$B$6:$B$2400,A63) -> 1248.4932 | L63: =J63+K63 -> 7729.5772 | M63: =P62 -> 361580.99 | N63: =SUMIFS(Cash_Events!$H$6:$H$20,Cash_Events!$C$6:$C$20,"rAGMF",Cash_Events!$D$6:$D$20,"JV",Cash_Events!$M$6:$M$20,A63) -> 0 | O63: =SUMIFS(Cash_Events!$H$6:$H$20,Cash_Events!$C$6:$C$20,"rAGMF",Cash_Events!$D$6:$D$20,"800S",Cash_Events!$M$6:$M$20,A63) -> 0 | P63: =M63+J63-N63-O63 -> 368062.07 | Q63: =S62 -> 56892.969 | R63: =SUMIFS(Cash_Events!$I$6:$I$20,Cash_Events!$C$6:$C$20,"rAGMF",Cash_Events!$M$6:$M$20,A63) -> 0 | S63: =Q63+K63-R63 -> 58141.462 | T63: =P63+S63 -> 426203.53 | U63: =G63+T63 -> 1161203.5 | V63: =V62+L63 -> 611017.3 | W63: =W62+N63+O63+R63 -> 184813.77 | X63: =ROUND(V63-W63-T63,2) -> 0
A64: =EOMONTH(A63,1) -> 46568 | B64: =A63 -> 46538 | C64: =A64-B64 -> 30 | D64: =IF(A64<=EOMONTH(Inputs!$B$18,-1),"Actual","Projection") -> Projection | E64: =G63 -> 735000 | F64: =SUMIFS(Cash_Events!$G$6:$G$20,Cash_Events!$C$6:$C$20,"rAGMF",Cash_Events!$M$6:$M$20,A64) -> 0 | G64: =E64-F64 -> 735000 | H64: =VLOOKUP(A64-1,Inputs!$A$40:$B$48,2,TRUE()) -> 0.0363225 | I64: =H64+Inputs!B10 -> 0.1038225 | J64: =SUMIFS(Daily!$G$6:$G$2400,Daily!$B$6:$B$2400,A64) -> 6272.0168 | K64: =SUMIFS(Daily!$H$6:$H$2400,Daily!$B$6:$B$2400,A64) -> 1208.2192 | L64: =J64+K64 -> 7480.236 | M64: =P63 -> 368062.07 | N64: =SUMIFS(Cash_Events!$H$6:$H$20,Cash_Events!$C$6:$C$20,"rAGMF",Cash_Events!$D$6:$D$20,"JV",Cash_Events!$M$6:$M$20,A64) -> 0 | O64: =SUMIFS(Cash_Events!$H$6:$H$20,Cash_Events!$C$6:$C$20,"rAGMF",Cash_Events!$D$6:$D$20,"800S",Cash_Events!$M$6:$M$20,A64) -> 0 | P64: =M64+J64-N64-O64 -> 374334.09 | Q64: =S63 -> 58141.462 | R64: =SUMIFS(Cash_Events!$I$6:$I$20,Cash_Events!$C$6:$C$20,"rAGMF",Cash_Events!$M$6:$M$20,A64) -> 0 | S64: =Q64+K64-R64 -> 59349.681 | T64: =P64+S64 -> 433683.77 | U64: =G64+T64 -> 1168683.8 | V64: =V63+L64 -> 618497.54 | W64: =W63+N64+O64+R64 -> 184813.77 | X64: =ROUND(V64-W64-T64,2) -> 0
A65: =EOMONTH(A64,1) -> 46599 | B65: =A64 -> 46568 | C65: =A65-B65 -> 31 | D65: =IF(A65<=EOMONTH(Inputs!$B$18,-1),"Actual","Projection") -> Projection | E65: =G64 -> 735000 | F65: =SUMIFS(Cash_Events!$G$6:$G$20,Cash_Events!$C$6:$C$20,"rAGMF",Cash_Events!$M$6:$M$20,A65) -> 0 | G65: =E65-F65 -> 735000 | H65: =VLOOKUP(A65-1,Inputs!$A$40:$B$48,2,TRUE()) -> 0.0363225 | I65: =H65+Inputs!B10 -> 0.1038225 | J65: =SUMIFS(Daily!$G$6:$G$2400,Daily!$B$6:$B$2400,A65) -> 6481.084 | K65: =SUMIFS(Daily!$H$6:$H$2400,Daily!$B$6:$B$2400,A65) -> 1248.4932 | L65: =J65+K65 -> 7729.5772 | M65: =P64 -> 374334.09 | N65: =SUMIFS(Cash_Events!$H$6:$H$20,Cash_Events!$C$6:$C$20,"rAGMF",Cash_Events!$D$6:$D$20,"JV",Cash_Events!$M$6:$M$20,A65) -> 0 | O65: =SUMIFS(Cash_Events!$H$6:$H$20,Cash_Events!$C$6:$C$20,"rAGMF",Cash_Events!$D$6:$D$20,"800S",Cash_Events!$M$6:$M$20,A65) -> 0 | P65: =M65+J65-N65-O65 -> 380815.17 | Q65: =S64 -> 59349.681 | R65: =SUMIFS(Cash_Events!$I$6:$I$20,Cash_Events!$C$6:$C$20,"rAGMF",Cash_Events!$M$6:$M$20,A65) -> 0 | S65: =Q65+K65-R65 -> 60598.175 | T65: =P65+S65 -> 441413.35 | U65: =G65+T65 -> 1176413.3 | V65: =V64+L65 -> 626227.12 | W65: =W64+N65+O65+R65 -> 184813.77 | X65: =ROUND(V65-W65-T65,2) -> 0
A66: =EOMONTH(A65,1) -> 46630 | B66: =A65 -> 46599 | C66: =A66-B66 -> 31 | D66: =IF(A66<=EOMONTH(Inputs!$B$18,-1),"Actual","Projection") -> Projection | E66: =G65 -> 735000 | F66: =SUMIFS(Cash_Events!$G$6:$G$20,Cash_Events!$C$6:$C$20,"rAGMF",Cash_Events!$M$6:$M$20,A66) -> 0 | G66: =E66-F66 -> 735000 | H66: =VLOOKUP(A66-1,Inputs!$A$40:$B$48,2,TRUE()) -> 0.0363225 | I66: =H66+Inputs!B10 -> 0.1038225 | J66: =SUMIFS(Daily!$G$6:$G$2400,Daily!$B$6:$B$2400,A66) -> 6481.084 | K66: =SUMIFS(Daily!$H$6:$H$2400,Daily!$B$6:$B$2400,A66) -> 1248.4932 | L66: =J66+K66 -> 7729.5772 | M66: =P65 -> 380815.17 | N66: =SUMIFS(Cash_Events!$H$6:$H$20,Cash_Events!$C$6:$C$20,"rAGMF",Cash_Events!$D$6:$D$20,"JV",Cash_Events!$M$6:$M$20,A66) -> 0 | O66: =SUMIFS(Cash_Events!$H$6:$H$20,Cash_Events!$C$6:$C$20,"rAGMF",Cash_Events!$D$6:$D$20,"800S",Cash_Events!$M$6:$M$20,A66) -> 0 | P66: =M66+J66-N66-O66 -> 387296.26 | Q66: =S65 -> 60598.175 | R66: =SUMIFS(Cash_Events!$I$6:$I$20,Cash_Events!$C$6:$C$20,"rAGMF",Cash_Events!$M$6:$M$20,A66) -> 0 | S66: =Q66+K66-R66 -> 61846.668 | T66: =P66+S66 -> 449142.93 | U66: =G66+T66 -> 1184142.9 | V66: =V65+L66 -> 633956.7 | W66: =W65+N66+O66+R66 -> 184813.77 | X66: =ROUND(V66-W66-T66,2) -> 0
A67: =EOMONTH(A66,1) -> 46660 | B67: =A66 -> 46630 | C67: =A67-B67 -> 30 | D67: =IF(A67<=EOMONTH(Inputs!$B$18,-1),"Actual","Projection") -> Projection | E67: =G66 -> 735000 | F67: =SUMIFS(Cash_Events!$G$6:$G$20,Cash_Events!$C$6:$C$20,"rAGMF",Cash_Events!$M$6:$M$20,A67) -> 0 | G67: =E67-F67 -> 735000 | H67: =VLOOKUP(A67-1,Inputs!$A$40:$B$48,2,TRUE()) -> 0.0363225 | I67: =H67+Inputs!B10 -> 0.1038225 | J67: =SUMIFS(Daily!$G$6:$G$2400,Daily!$B$6:$B$2400,A67) -> 6272.0168 | K67: =SUMIFS(Daily!$H$6:$H$2400,Daily!$B$6:$B$2400,A67) -> 1208.2192 | L67: =J67+K67 -> 7480.236 | M67: =P66 -> 387296.26 | N67: =SUMIFS(Cash_Events!$H$6:$H$20,Cash_Events!$C$6:$C$20,"rAGMF",Cash_Events!$D$6:$D$20,"JV",Cash_Events!$M$6:$M$20,A67) -> 0 | O67: =SUMIFS(Cash_Events!$H$6:$H$20,Cash_Events!$C$6:$C$20,"rAGMF",Cash_Events!$D$6:$D$20,"800S",Cash_Events!$M$6:$M$20,A67) -> 0 | P67: =M67+J67-N67-O67 -> 393568.27 | Q67: =S66 -> 61846.668 | R67: =SUMIFS(Cash_Events!$I$6:$I$20,Cash_Events!$C$6:$C$20,"rAGMF",Cash_Events!$M$6:$M$20,A67) -> 0 | S67: =Q67+K67-R67 -> 63054.887 | T67: =P67+S67 -> 456623.16 | U67: =G67+T67 -> 1191623.2 | V67: =V66+L67 -> 641436.93 | W67: =W66+N67+O67+R67 -> 184813.77 | X67: =ROUND(V67-W67-T67,2) -> 0
A68: =EOMONTH(A67,1) -> 46691 | B68: =A67 -> 46660 | C68: =A68-B68 -> 31 | D68: =IF(A68<=EOMONTH(Inputs!$B$18,-1),"Actual","Projection") -> Projection | E68: =G67 -> 735000 | F68: =SUMIFS(Cash_Events!$G$6:$G$20,Cash_Events!$C$6:$C$20,"rAGMF",Cash_Events!$M$6:$M$20,A68) -> 0 | G68: =E68-F68 -> 735000 | H68: =VLOOKUP(A68-1,Inputs!$A$40:$B$48,2,TRUE()) -> 0.0363225 | I68: =H68+Inputs!B10 -> 0.1038225 | J68: =SUMIFS(Daily!$G$6:$G$2400,Daily!$B$6:$B$2400,A68) -> 6481.084 | K68: =SUMIFS(Daily!$H$6:$H$2400,Daily!$B$6:$B$2400,A68) -> 1248.4932 | L68: =J68+K68 -> 7729.5772 | M68: =P67 -> 393568.27 | N68: =SUMIFS(Cash_Events!$H$6:$H$20,Cash_Events!$C$6:$C$20,"rAGMF",Cash_Events!$D$6:$D$20,"JV",Cash_Events!$M$6:$M$20,A68) -> 0 | O68: =SUMIFS(Cash_Events!$H$6:$H$20,Cash_Events!$C$6:$C$20,"rAGMF",Cash_Events!$D$6:$D$20,"800S",Cash_Events!$M$6:$M$20,A68) -> 0 | P68: =M68+J68-N68-O68 -> 400049.36 | Q68: =S67 -> 63054.887 | R68: =SUMIFS(Cash_Events!$I$6:$I$20,Cash_Events!$C$6:$C$20,"rAGMF",Cash_Events!$M$6:$M$20,A68) -> 0 | S68: =Q68+K68-R68 -> 64303.38 | T68: =P68+S68 -> 464352.74 | U68: =G68+T68 -> 1199352.7 | V68: =V67+L68 -> 649166.51 | W68: =W67+N68+O68+R68 -> 184813.77 | X68: =ROUND(V68-W68-T68,2) -> 0
A69: =EOMONTH(A68,1) -> 46721 | B69: =A68 -> 46691 | C69: =A69-B69 -> 30 | D69: =IF(A69<=EOMONTH(Inputs!$B$18,-1),"Actual","Projection") -> Projection | E69: =G68 -> 735000 | F69: =SUMIFS(Cash_Events!$G$6:$G$20,Cash_Events!$C$6:$C$20,"rAGMF",Cash_Events!$M$6:$M$20,A69) -> 0 | G69: =E69-F69 -> 735000 | H69: =VLOOKUP(A69-1,Inputs!$A$40:$B$48,2,TRUE()) -> 0.0363225 | I69: =H69+Inputs!B10 -> 0.1038225 | J69: =SUMIFS(Daily!$G$6:$G$2400,Daily!$B$6:$B$2400,A69) -> 6272.0168 | K69: =SUMIFS(Daily!$H$6:$H$2400,Daily!$B$6:$B$2400,A69) -> 1208.2192 | L69: =J69+K69 -> 7480.236 | M69: =P68 -> 400049.36 | N69: =SUMIFS(Cash_Events!$H$6:$H$20,Cash_Events!$C$6:$C$20,"rAGMF",Cash_Events!$D$6:$D$20,"JV",Cash_Events!$M$6:$M$20,A69) -> 0 | O69: =SUMIFS(Cash_Events!$H$6:$H$20,Cash_Events!$C$6:$C$20,"rAGMF",Cash_Events!$D$6:$D$20,"800S",Cash_Events!$M$6:$M$20,A69) -> 0 | P69: =M69+J69-N69-O69 -> 406321.38 | Q69: =S68 -> 64303.38 | R69: =SUMIFS(Cash_Events!$I$6:$I$20,Cash_Events!$C$6:$C$20,"rAGMF",Cash_Events!$M$6:$M$20,A69) -> 0 | S69: =Q69+K69-R69 -> 65511.599 | T69: =P69+S69 -> 471832.97 | U69: =G69+T69 -> 1206833 | V69: =V68+L69 -> 656646.74 | W69: =W68+N69+O69+R69 -> 184813.77 | X69: =ROUND(V69-W69-T69,2) -> 0
A70: =EOMONTH(A69,1) -> 46752 | B70: =A69 -> 46721 | C70: =A70-B70 -> 31 | D70: =IF(A70<=EOMONTH(Inputs!$B$18,-1),"Actual","Projection") -> Projection | E70: =G69 -> 735000 | F70: =SUMIFS(Cash_Events!$G$6:$G$20,Cash_Events!$C$6:$C$20,"rAGMF",Cash_Events!$M$6:$M$20,A70) -> 0 | G70: =E70-F70 -> 735000 | H70: =VLOOKUP(A70-1,Inputs!$A$40:$B$48,2,TRUE()) -> 0.0363225 | I70: =H70+Inputs!B10 -> 0.1038225 | J70: =SUMIFS(Daily!$G$6:$G$2400,Daily!$B$6:$B$2400,A70) -> 6481.084 | K70: =SUMIFS(Daily!$H$6:$H$2400,Daily!$B$6:$B$2400,A70) -> 1248.4932 | L70: =J70+K70 -> 7729.5772 | M70: =P69 -> 406321.38 | N70: =SUMIFS(Cash_Events!$H$6:$H$20,Cash_Events!$C$6:$C$20,"rAGMF",Cash_Events!$D$6:$D$20,"JV",Cash_Events!$M$6:$M$20,A70) -> 0 | O70: =SUMIFS(Cash_Events!$H$6:$H$20,Cash_Events!$C$6:$C$20,"rAGMF",Cash_Events!$D$6:$D$20,"800S",Cash_Events!$M$6:$M$20,A70) -> 0 | P70: =M70+J70-N70-O70 -> 412802.46 | Q70: =S69 -> 65511.599 | R70: =SUMIFS(Cash_Events!$I$6:$I$20,Cash_Events!$C$6:$C$20,"rAGMF",Cash_Events!$M$6:$M$20,A70) -> 0 | S70: =Q70+K70-R70 -> 66760.092 | T70: =P70+S70 -> 479562.55 | U70: =G70+T70 -> 1214562.6 | V70: =V69+L70 -> 664376.32 | W70: =W69+N70+O70+R70 -> 184813.77 | X70: =ROUND(V70-W70-T70,2) -> 0
A71: =EOMONTH(A70,1) -> 46783 | B71: =A70 -> 46752 | C71: =A71-B71 -> 31 | D71: =IF(A71<=EOMONTH(Inputs!$B$18,-1),"Actual","Projection") -> Projection | E71: =G70 -> 735000 | F71: =SUMIFS(Cash_Events!$G$6:$G$20,Cash_Events!$C$6:$C$20,"rAGMF",Cash_Events!$M$6:$M$20,A71) -> 0 | G71: =E71-F71 -> 735000 | H71: =VLOOKUP(A71-1,Inputs!$A$40:$B$48,2,TRUE()) -> 0.0363225 | I71: =H71+Inputs!B10 -> 0.1038225 | J71: =SUMIFS(Daily!$G$6:$G$2400,Daily!$B$6:$B$2400,A71) -> 6463.9473 | K71: =SUMIFS(Daily!$H$6:$H$2400,Daily!$B$6:$B$2400,A71) -> 1245.192 | L71: =J71+K71 -> 7709.1394 | M71: =P70 -> 412802.46 | N71: =SUMIFS(Cash_Events!$H$6:$H$20,Cash_Events!$C$6:$C$20,"rAGMF",Cash_Events!$D$6:$D$20,"JV",Cash_Events!$M$6:$M$20,A71) -> 0 | O71: =SUMIFS(Cash_Events!$H$6:$H$20,Cash_Events!$C$6:$C$20,"rAGMF",Cash_Events!$D$6:$D$20,"800S",Cash_Events!$M$6:$M$20,A71) -> 0 | P71: =M71+J71-N71-O71 -> 419266.41 | Q71: =S70 -> 66760.092 | R71: =SUMIFS(Cash_Events!$I$6:$I$20,Cash_Events!$C$6:$C$20,"rAGMF",Cash_Events!$M$6:$M$20,A71) -> 0 | S71: =Q71+K71-R71 -> 68005.284 | T71: =P71+S71 -> 487271.69 | U71: =G71+T71 -> 1222271.7 | V71: =V70+L71 -> 672085.46 | W71: =W70+N71+O71+R71 -> 184813.77 | X71: =ROUND(V71-W71-T71,2) -> 0
A72: =EOMONTH(A71,1) -> 46812 | B72: =A71 -> 46783 | C72: =A72-B72 -> 29 | D72: =IF(A72<=EOMONTH(Inputs!$B$18,-1),"Actual","Projection") -> Projection | E72: =G71 -> 735000 | F72: =SUMIFS(Cash_Events!$G$6:$G$20,Cash_Events!$C$6:$C$20,"rAGMF",Cash_Events!$M$6:$M$20,A72) -> 0 | G72: =E72-F72 -> 735000 | H72: =VLOOKUP(A72-1,Inputs!$A$40:$B$48,2,TRUE()) -> 0.0363225 | I72: =H72+Inputs!B10 -> 0.1038225 | J72: =SUMIFS(Daily!$G$6:$G$2400,Daily!$B$6:$B$2400,A72) -> 6046.3841 | K72: =SUMIFS(Daily!$H$6:$H$2400,Daily!$B$6:$B$2400,A72) -> 1164.7541 | L72: =J72+K72 -> 7211.1382 | M72: =P71 -> 419266.41 | N72: =SUMIFS(Cash_Events!$H$6:$H$20,Cash_Events!$C$6:$C$20,"rAGMF",Cash_Events!$D$6:$D$20,"JV",Cash_Events!$M$6:$M$20,A72) -> 0 | O72: =SUMIFS(Cash_Events!$H$6:$H$20,Cash_Events!$C$6:$C$20,"rAGMF",Cash_Events!$D$6:$D$20,"800S",Cash_Events!$M$6:$M$20,A72) -> 0 | P72: =M72+J72-N72-O72 -> 425312.79 | Q72: =S71 -> 68005.284 | R72: =SUMIFS(Cash_Events!$I$6:$I$20,Cash_Events!$C$6:$C$20,"rAGMF",Cash_Events!$M$6:$M$20,A72) -> 0 | S72: =Q72+K72-R72 -> 69170.038 | T72: =P72+S72 -> 494482.83 | U72: =G72+T72 -> 1229482.8 | V72: =V71+L72 -> 679296.6 | W72: =W71+N72+O72+R72 -> 184813.77 | X72: =ROUND(V72-W72-T72,2) -> 0
A73: =EOMONTH(A72,1) -> 46843 | B73: =A72 -> 46812 | C73: =A73-B73 -> 31 | D73: =IF(A73<=EOMONTH(Inputs!$B$18,-1),"Actual","Projection") -> Projection | E73: =G72 -> 735000 | F73: =SUMIFS(Cash_Events!$G$6:$G$20,Cash_Events!$C$6:$C$20,"rAGMF",Cash_Events!$M$6:$M$20,A73) -> 0 | G73: =E73-F73 -> 735000 | H73: =VLOOKUP(A73-1,Inputs!$A$40:$B$48,2,TRUE()) -> 0.0363225 | I73: =H73+Inputs!B10 -> 0.1038225 | J73: =SUMIFS(Daily!$G$6:$G$2400,Daily!$B$6:$B$2400,A73) -> 6463.3761 | K73: =SUMIFS(Daily!$H$6:$H$2400,Daily!$B$6:$B$2400,A73) -> 1245.082 | L73: =J73+K73 -> 7708.4581 | M73: =P72 -> 425312.79 | N73: =SUMIFS(Cash_Events!$H$6:$H$20,Cash_Events!$C$6:$C$20,"rAGMF",Cash_Events!$D$6:$D$20,"JV",Cash_Events!$M$6:$M$20,A73) -> 0 | O73: =SUMIFS(Cash_Events!$H$6:$H$20,Cash_Events!$C$6:$C$20,"rAGMF",Cash_Events!$D$6:$D$20,"800S",Cash_Events!$M$6:$M$20,A73) -> 0 | P73: =M73+J73-N73-O73 -> 431776.17 | Q73: =S72 -> 69170.038 | R73: =SUMIFS(Cash_Events!$I$6:$I$20,Cash_Events!$C$6:$C$20,"rAGMF",Cash_Events!$M$6:$M$20,A73) -> 0 | S73: =Q73+K73-R73 -> 70415.12 | T73: =P73+S73 -> 502191.29 | U73: =G73+T73 -> 1237191.3 | V73: =V72+L73 -> 687005.06 | W73: =W72+N73+O73+R73 -> 184813.77 | X73: =ROUND(V73-W73-T73,2) -> 0
A74: =EOMONTH(A73,1) -> 46873 | B74: =A73 -> 46843 | C74: =A74-B74 -> 30 | D74: =IF(A74<=EOMONTH(Inputs!$B$18,-1),"Actual","Projection") -> Projection | E74: =G73 -> 735000 | F74: =SUMIFS(Cash_Events!$G$6:$G$20,Cash_Events!$C$6:$C$20,"rAGMF",Cash_Events!$M$6:$M$20,A74) -> 0 | G74: =E74-F74 -> 735000 | H74: =VLOOKUP(A74-1,Inputs!$A$40:$B$48,2,TRUE()) -> 0.0363225 | I74: =H74+Inputs!B10 -> 0.1038225 | J74: =SUMIFS(Daily!$G$6:$G$2400,Daily!$B$6:$B$2400,A74) -> 6254.8801 | K74: =SUMIFS(Daily!$H$6:$H$2400,Daily!$B$6:$B$2400,A74) -> 1204.918 | L74: =J74+K74 -> 7459.7982 | M74: =P73 -> 431776.17 | N74: =SUMIFS(Cash_Events!$H$6:$H$20,Cash_Events!$C$6:$C$20,"rAGMF",Cash_Events!$D$6:$D$20,"JV",Cash_Events!$M$6:$M$20,A74) -> 0 | O74: =SUMIFS(Cash_Events!$H$6:$H$20,Cash_Events!$C$6:$C$20,"rAGMF",Cash_Events!$D$6:$D$20,"800S",Cash_Events!$M$6:$M$20,A74) -> 0 | P74: =M74+J74-N74-O74 -> 438031.05 | Q74: =S73 -> 70415.12 | R74: =SUMIFS(Cash_Events!$I$6:$I$20,Cash_Events!$C$6:$C$20,"rAGMF",Cash_Events!$M$6:$M$20,A74) -> 0 | S74: =Q74+K74-R74 -> 71620.038 | T74: =P74+S74 -> 509651.09 | U74: =G74+T74 -> 1244651.1 | V74: =V73+L74 -> 694464.86 | W74: =W73+N74+O74+R74 -> 184813.77 | X74: =ROUND(V74-W74-T74,2) -> 0
A75: =EOMONTH(A74,1) -> 46904 | B75: =A74 -> 46873 | C75: =A75-B75 -> 31 | D75: =IF(A75<=EOMONTH(Inputs!$B$18,-1),"Actual","Projection") -> Projection | E75: =G74 -> 735000 | F75: =SUMIFS(Cash_Events!$G$6:$G$20,Cash_Events!$C$6:$C$20,"rAGMF",Cash_Events!$M$6:$M$20,A75) -> 0 | G75: =E75-F75 -> 735000 | H75: =VLOOKUP(A75-1,Inputs!$A$40:$B$48,2,TRUE()) -> 0.0363225 | I75: =H75+Inputs!B10 -> 0.1038225 | J75: =SUMIFS(Daily!$G$6:$G$2400,Daily!$B$6:$B$2400,A75) -> 6463.3761 | K75: =SUMIFS(Daily!$H$6:$H$2400,Daily!$B$6:$B$2400,A75) -> 1245.082 | L75: =J75+K75 -> 7708.4581 | M75: =P74 -> 438031.05 | N75: =SUMIFS(Cash_Events!$H$6:$H$20,Cash_Events!$C$6:$C$20,"rAGMF",Cash_Events!$D$6:$D$20,"JV",Cash_Events!$M$6:$M$20,A75) -> 0 | O75: =SUMIFS(Cash_Events!$H$6:$H$20,Cash_Events!$C$6:$C$20,"rAGMF",Cash_Events!$D$6:$D$20,"800S",Cash_Events!$M$6:$M$20,A75) -> 0 | P75: =M75+J75-N75-O75 -> 444494.42 | Q75: =S74 -> 71620.038 | R75: =SUMIFS(Cash_Events!$I$6:$I$20,Cash_Events!$C$6:$C$20,"rAGMF",Cash_Events!$M$6:$M$20,A75) -> 0 | S75: =Q75+K75-R75 -> 72865.12 | T75: =P75+S75 -> 517359.54 | U75: =G75+T75 -> 1252359.5 | V75: =V74+L75 -> 702173.31 | W75: =W74+N75+O75+R75 -> 184813.77 | X75: =ROUND(V75-W75-T75,2) -> 0
A76: =EOMONTH(A75,1) -> 46934 | B76: =A75 -> 46904 | C76: =A76-B76 -> 30 | D76: =IF(A76<=EOMONTH(Inputs!$B$18,-1),"Actual","Projection") -> Projection | E76: =G75 -> 735000 | F76: =SUMIFS(Cash_Events!$G$6:$G$20,Cash_Events!$C$6:$C$20,"rAGMF",Cash_Events!$M$6:$M$20,A76) -> 0 | G76: =E76-F76 -> 735000 | H76: =VLOOKUP(A76-1,Inputs!$A$40:$B$48,2,TRUE()) -> 0.0363225 | I76: =H76+Inputs!B10 -> 0.1038225 | J76: =SUMIFS(Daily!$G$6:$G$2400,Daily!$B$6:$B$2400,A76) -> 6254.8801 | K76: =SUMIFS(Daily!$H$6:$H$2400,Daily!$B$6:$B$2400,A76) -> 1204.918 | L76: =J76+K76 -> 7459.7982 | M76: =P75 -> 444494.42 | N76: =SUMIFS(Cash_Events!$H$6:$H$20,Cash_Events!$C$6:$C$20,"rAGMF",Cash_Events!$D$6:$D$20,"JV",Cash_Events!$M$6:$M$20,A76) -> 0 | O76: =SUMIFS(Cash_Events!$H$6:$H$20,Cash_Events!$C$6:$C$20,"rAGMF",Cash_Events!$D$6:$D$20,"800S",Cash_Events!$M$6:$M$20,A76) -> 0 | P76: =M76+J76-N76-O76 -> 450749.3 | Q76: =S75 -> 72865.12 | R76: =SUMIFS(Cash_Events!$I$6:$I$20,Cash_Events!$C$6:$C$20,"rAGMF",Cash_Events!$M$6:$M$20,A76) -> 0 | S76: =Q76+K76-R76 -> 74070.038 | T76: =P76+S76 -> 524819.34 | U76: =G76+T76 -> 1259819.3 | V76: =V75+L76 -> 709633.11 | W76: =W75+N76+O76+R76 -> 184813.77 | X76: =ROUND(V76-W76-T76,2) -> 0
A77: =EOMONTH(A76,1) -> 46965 | B77: =A76 -> 46934 | C77: =A77-B77 -> 31 | D77: =IF(A77<=EOMONTH(Inputs!$B$18,-1),"Actual","Projection") -> Projection | E77: =G76 -> 735000 | F77: =SUMIFS(Cash_Events!$G$6:$G$20,Cash_Events!$C$6:$C$20,"rAGMF",Cash_Events!$M$6:$M$20,A77) -> 0 | G77: =E77-F77 -> 735000 | H77: =VLOOKUP(A77-1,Inputs!$A$40:$B$48,2,TRUE()) -> 0.0363225 | I77: =H77+Inputs!B10 -> 0.1038225 | J77: =SUMIFS(Daily!$G$6:$G$2400,Daily!$B$6:$B$2400,A77) -> 6463.3761 | K77: =SUMIFS(Daily!$H$6:$H$2400,Daily!$B$6:$B$2400,A77) -> 1245.082 | L77: =J77+K77 -> 7708.4581 | M77: =P76 -> 450749.3 | N77: =SUMIFS(Cash_Events!$H$6:$H$20,Cash_Events!$C$6:$C$20,"rAGMF",Cash_Events!$D$6:$D$20,"JV",Cash_Events!$M$6:$M$20,A77) -> 0 | O77: =SUMIFS(Cash_Events!$H$6:$H$20,Cash_Events!$C$6:$C$20,"rAGMF",Cash_Events!$D$6:$D$20,"800S",Cash_Events!$M$6:$M$20,A77) -> 0 | P77: =M77+J77-N77-O77 -> 457212.68 | Q77: =S76 -> 74070.038 | R77: =SUMIFS(Cash_Events!$I$6:$I$20,Cash_Events!$C$6:$C$20,"rAGMF",Cash_Events!$M$6:$M$20,A77) -> 0 | S77: =Q77+K77-R77 -> 75315.12 | T77: =P77+S77 -> 532527.8 | U77: =G77+T77 -> 1267527.8 | V77: =V76+L77 -> 717341.57 | W77: =W76+N77+O77+R77 -> 184813.77 | X77: =ROUND(V77-W77-T77,2) -> 0
A78: =EOMONTH(A77,1) -> 46996 | B78: =A77 -> 46965 | C78: =A78-B78 -> 31 | D78: =IF(A78<=EOMONTH(Inputs!$B$18,-1),"Actual","Projection") -> Projection | E78: =G77 -> 735000 | F78: =SUMIFS(Cash_Events!$G$6:$G$20,Cash_Events!$C$6:$C$20,"rAGMF",Cash_Events!$M$6:$M$20,A78) -> 0 | G78: =E78-F78 -> 735000 | H78: =VLOOKUP(A78-1,Inputs!$A$40:$B$48,2,TRUE()) -> 0.0363225 | I78: =H78+Inputs!B10 -> 0.1038225 | J78: =SUMIFS(Daily!$G$6:$G$2400,Daily!$B$6:$B$2400,A78) -> 6463.3761 | K78: =SUMIFS(Daily!$H$6:$H$2400,Daily!$B$6:$B$2400,A78) -> 1245.082 | L78: =J78+K78 -> 7708.4581 | M78: =P77 -> 457212.68 | N78: =SUMIFS(Cash_Events!$H$6:$H$20,Cash_Events!$C$6:$C$20,"rAGMF",Cash_Events!$D$6:$D$20,"JV",Cash_Events!$M$6:$M$20,A78) -> 0 | O78: =SUMIFS(Cash_Events!$H$6:$H$20,Cash_Events!$C$6:$C$20,"rAGMF",Cash_Events!$D$6:$D$20,"800S",Cash_Events!$M$6:$M$20,A78) -> 0 | P78: =M78+J78-N78-O78 -> 463676.06 | Q78: =S77 -> 75315.12 | R78: =SUMIFS(Cash_Events!$I$6:$I$20,Cash_Events!$C$6:$C$20,"rAGMF",Cash_Events!$M$6:$M$20,A78) -> 0 | S78: =Q78+K78-R78 -> 76560.202 | T78: =P78+S78 -> 540236.26 | U78: =G78+T78 -> 1275236.3 | V78: =V77+L78 -> 725050.03 | W78: =W77+N78+O78+R78 -> 184813.77 | X78: =ROUND(V78-W78-T78,2) -> 0
A79: =EOMONTH(A78,1) -> 47026 | B79: =A78 -> 46996 | C79: =A79-B79 -> 30 | D79: =IF(A79<=EOMONTH(Inputs!$B$18,-1),"Actual","Projection") -> Projection | E79: =G78 -> 735000 | F79: =SUMIFS(Cash_Events!$G$6:$G$20,Cash_Events!$C$6:$C$20,"rAGMF",Cash_Events!$M$6:$M$20,A79) -> 0 | G79: =E79-F79 -> 735000 | H79: =VLOOKUP(A79-1,Inputs!$A$40:$B$48,2,TRUE()) -> 0.0363225 | I79: =H79+Inputs!B10 -> 0.1038225 | J79: =SUMIFS(Daily!$G$6:$G$2400,Daily!$B$6:$B$2400,A79) -> 6254.8801 | K79: =SUMIFS(Daily!$H$6:$H$2400,Daily!$B$6:$B$2400,A79) -> 1204.918 | L79: =J79+K79 -> 7459.7982 | M79: =P78 -> 463676.06 | N79: =SUMIFS(Cash_Events!$H$6:$H$20,Cash_Events!$C$6:$C$20,"rAGMF",Cash_Events!$D$6:$D$20,"JV",Cash_Events!$M$6:$M$20,A79) -> 0 | O79: =SUMIFS(Cash_Events!$H$6:$H$20,Cash_Events!$C$6:$C$20,"rAGMF",Cash_Events!$D$6:$D$20,"800S",Cash_Events!$M$6:$M$20,A79) -> 0 | P79: =M79+J79-N79-O79 -> 469930.94 | Q79: =S78 -> 76560.202 | R79: =SUMIFS(Cash_Events!$I$6:$I$20,Cash_Events!$C$6:$C$20,"rAGMF",Cash_Events!$M$6:$M$20,A79) -> 0 | S79: =Q79+K79-R79 -> 77765.12 | T79: =P79+S79 -> 547696.06 | U79: =G79+T79 -> 1282696.1 | V79: =V78+L79 -> 732509.83 | W79: =W78+N79+O79+R79 -> 184813.77 | X79: =ROUND(V79-W79-T79,2) -> 0
A80: =EOMONTH(A79,1) -> 47057 | B80: =A79 -> 47026 | C80: =A80-B80 -> 31 | D80: =IF(A80<=EOMONTH(Inputs!$B$18,-1),"Actual","Projection") -> Projection | E80: =G79 -> 735000 | F80: =SUMIFS(Cash_Events!$G$6:$G$20,Cash_Events!$C$6:$C$20,"rAGMF",Cash_Events!$M$6:$M$20,A80) -> 0 | G80: =E80-F80 -> 735000 | H80: =VLOOKUP(A80-1,Inputs!$A$40:$B$48,2,TRUE()) -> 0.0363225 | I80: =H80+Inputs!B10 -> 0.1038225 | J80: =SUMIFS(Daily!$G$6:$G$2400,Daily!$B$6:$B$2400,A80) -> 6463.3761 | K80: =SUMIFS(Daily!$H$6:$H$2400,Daily!$B$6:$B$2400,A80) -> 1245.082 | L80: =J80+K80 -> 7708.4581 | M80: =P79 -> 469930.94 | N80: =SUMIFS(Cash_Events!$H$6:$H$20,Cash_Events!$C$6:$C$20,"rAGMF",Cash_Events!$D$6:$D$20,"JV",Cash_Events!$M$6:$M$20,A80) -> 0 | O80: =SUMIFS(Cash_Events!$H$6:$H$20,Cash_Events!$C$6:$C$20,"rAGMF",Cash_Events!$D$6:$D$20,"800S",Cash_Events!$M$6:$M$20,A80) -> 0 | P80: =M80+J80-N80-O80 -> 476394.31 | Q80: =S79 -> 77765.12 | R80: =SUMIFS(Cash_Events!$I$6:$I$20,Cash_Events!$C$6:$C$20,"rAGMF",Cash_Events!$M$6:$M$20,A80) -> 0 | S80: =Q80+K80-R80 -> 79010.202 | T80: =P80+S80 -> 555404.51 | U80: =G80+T80 -> 1290404.5 | V80: =V79+L80 -> 740218.28 | W80: =W79+N80+O80+R80 -> 184813.77 | X80: =ROUND(V80-W80-T80,2) -> 0
A81: =EOMONTH(A80,1) -> 47087 | B81: =A80 -> 47057 | C81: =A81-B81 -> 30 | D81: =IF(A81<=EOMONTH(Inputs!$B$18,-1),"Actual","Projection") -> Projection | E81: =G80 -> 735000 | F81: =SUMIFS(Cash_Events!$G$6:$G$20,Cash_Events!$C$6:$C$20,"rAGMF",Cash_Events!$M$6:$M$20,A81) -> 0 | G81: =E81-F81 -> 735000 | H81: =VLOOKUP(A81-1,Inputs!$A$40:$B$48,2,TRUE()) -> 0.0363225 | I81: =H81+Inputs!B10 -> 0.1038225 | J81: =SUMIFS(Daily!$G$6:$G$2400,Daily!$B$6:$B$2400,A81) -> 6254.8801 | K81: =SUMIFS(Daily!$H$6:$H$2400,Daily!$B$6:$B$2400,A81) -> 1204.918 | L81: =J81+K81 -> 7459.7982 | M81: =P80 -> 476394.31 | N81: =SUMIFS(Cash_Events!$H$6:$H$20,Cash_Events!$C$6:$C$20,"rAGMF",Cash_Events!$D$6:$D$20,"JV",Cash_Events!$M$6:$M$20,A81) -> 0 | O81: =SUMIFS(Cash_Events!$H$6:$H$20,Cash_Events!$C$6:$C$20,"rAGMF",Cash_Events!$D$6:$D$20,"800S",Cash_Events!$M$6:$M$20,A81) -> 0 | P81: =M81+J81-N81-O81 -> 482649.19 | Q81: =S80 -> 79010.202 | R81: =SUMIFS(Cash_Events!$I$6:$I$20,Cash_Events!$C$6:$C$20,"rAGMF",Cash_Events!$M$6:$M$20,A81) -> 0 | S81: =Q81+K81-R81 -> 80215.12 | T81: =P81+S81 -> 562864.31 | U81: =G81+T81 -> 1297864.3 | V81: =V80+L81 -> 747678.08 | W81: =W80+N81+O81+R81 -> 184813.77 | X81: =ROUND(V81-W81-T81,2) -> 0
A82: =EOMONTH(A81,1) -> 47118 | B82: =A81 -> 47087 | C82: =A82-B82 -> 31 | D82: =IF(A82<=EOMONTH(Inputs!$B$18,-1),"Actual","Projection") -> Projection | E82: =G81 -> 735000 | F82: =SUMIFS(Cash_Events!$G$6:$G$20,Cash_Events!$C$6:$C$20,"rAGMF",Cash_Events!$M$6:$M$20,A82) -> 0 | G82: =E82-F82 -> 735000 | H82: =VLOOKUP(A82-1,Inputs!$A$40:$B$48,2,TRUE()) -> 0.0363225 | I82: =H82+Inputs!B10 -> 0.1038225 | J82: =SUMIFS(Daily!$G$6:$G$2400,Daily!$B$6:$B$2400,A82) -> 6463.3761 | K82: =SUMIFS(Daily!$H$6:$H$2400,Daily!$B$6:$B$2400,A82) -> 1245.082 | L82: =J82+K82 -> 7708.4581 | M82: =P81 -> 482649.19 | N82: =SUMIFS(Cash_Events!$H$6:$H$20,Cash_Events!$C$6:$C$20,"rAGMF",Cash_Events!$D$6:$D$20,"JV",Cash_Events!$M$6:$M$20,A82) -> 0 | O82: =SUMIFS(Cash_Events!$H$6:$H$20,Cash_Events!$C$6:$C$20,"rAGMF",Cash_Events!$D$6:$D$20,"800S",Cash_Events!$M$6:$M$20,A82) -> 0 | P82: =M82+J82-N82-O82 -> 489112.57 | Q82: =S81 -> 80215.12 | R82: =SUMIFS(Cash_Events!$I$6:$I$20,Cash_Events!$C$6:$C$20,"rAGMF",Cash_Events!$M$6:$M$20,A82) -> 0 | S82: =Q82+K82-R82 -> 81460.202 | T82: =P82+S82 -> 570572.77 | U82: =G82+T82 -> 1305572.8 | V82: =V81+L82 -> 755386.54 | W82: =W81+N82+O82+R82 -> 184813.77 | X82: =ROUND(V82-W82-T82,2) -> 0
A83: =EOMONTH(A82,1) -> 47149 | B83: =A82 -> 47118 | C83: =A83-B83 -> 31 | D83: =IF(A83<=EOMONTH(Inputs!$B$18,-1),"Actual","Projection") -> Projection | E83: =G82 -> 735000 | F83: =SUMIFS(Cash_Events!$G$6:$G$20,Cash_Events!$C$6:$C$20,"rAGMF",Cash_Events!$M$6:$M$20,A83) -> 0 | G83: =E83-F83 -> 735000 | H83: =VLOOKUP(A83-1,Inputs!$A$40:$B$48,2,TRUE()) -> 0.0363225 | I83: =H83+Inputs!B10 -> 0.1038225 | J83: =SUMIFS(Daily!$G$6:$G$2400,Daily!$B$6:$B$2400,A83) -> 6480.5128 | K83: =SUMIFS(Daily!$H$6:$H$2400,Daily!$B$6:$B$2400,A83) -> 1248.3831 | L83: =J83+K83 -> 7728.8959 | M83: =P82 -> 489112.57 | N83: =SUMIFS(Cash_Events!$H$6:$H$20,Cash_Events!$C$6:$C$20,"rAGMF",Cash_Events!$D$6:$D$20,"JV",Cash_Events!$M$6:$M$20,A83) -> 0 | O83: =SUMIFS(Cash_Events!$H$6:$H$20,Cash_Events!$C$6:$C$20,"rAGMF",Cash_Events!$D$6:$D$20,"800S",Cash_Events!$M$6:$M$20,A83) -> 0 | P83: =M83+J83-N83-O83 -> 495593.08 | Q83: =S82 -> 81460.202 | R83: =SUMIFS(Cash_Events!$I$6:$I$20,Cash_Events!$C$6:$C$20,"rAGMF",Cash_Events!$M$6:$M$20,A83) -> 0 | S83: =Q83+K83-R83 -> 82708.586 | T83: =P83+S83 -> 578301.67 | U83: =G83+T83 -> 1313301.7 | V83: =V82+L83 -> 763115.44 | W83: =W82+N83+O83+R83 -> 184813.77 | X83: =ROUND(V83-W83-T83,2) -> 0
A84: =EOMONTH(A83,1) -> 47177 | B84: =A83 -> 47149 | C84: =A84-B84 -> 28 | D84: =IF(A84<=EOMONTH(Inputs!$B$18,-1),"Actual","Projection") -> Projection | E84: =G83 -> 735000 | F84: =SUMIFS(Cash_Events!$G$6:$G$20,Cash_Events!$C$6:$C$20,"rAGMF",Cash_Events!$M$6:$M$20,A84) -> 0 | G84: =E84-F84 -> 735000 | H84: =VLOOKUP(A84-1,Inputs!$A$40:$B$48,2,TRUE()) -> 0.0363225 | I84: =H84+Inputs!B10 -> 0.1038225 | J84: =SUMIFS(Daily!$G$6:$G$2400,Daily!$B$6:$B$2400,A84) -> 5853.8823 | K84: =SUMIFS(Daily!$H$6:$H$2400,Daily!$B$6:$B$2400,A84) -> 1127.6712 | L84: =J84+K84 -> 6981.5536 | M84: =P83 -> 495593.08 | N84: =SUMIFS(Cash_Events!$H$6:$H$20,Cash_Events!$C$6:$C$20,"rAGMF",Cash_Events!$D$6:$D$20,"JV",Cash_Events!$M$6:$M$20,A84) -> 0 | O84: =SUMIFS(Cash_Events!$H$6:$H$20,Cash_Events!$C$6:$C$20,"rAGMF",Cash_Events!$D$6:$D$20,"800S",Cash_Events!$M$6:$M$20,A84) -> 0 | P84: =M84+J84-N84-O84 -> 501446.96 | Q84: =S83 -> 82708.586 | R84: =SUMIFS(Cash_Events!$I$6:$I$20,Cash_Events!$C$6:$C$20,"rAGMF",Cash_Events!$M$6:$M$20,A84) -> 0 | S84: =Q84+K84-R84 -> 83836.257 | T84: =P84+S84 -> 585283.22 | U84: =G84+T84 -> 1320283.2 | V84: =V83+L84 -> 770096.99 | W84: =W83+N84+O84+R84 -> 184813.77 | X84: =ROUND(V84-W84-T84,2) -> 0
A85: =EOMONTH(A84,1) -> 47208 | B85: =A84 -> 47177 | C85: =A85-B85 -> 31 | D85: =IF(A85<=EOMONTH(Inputs!$B$18,-1),"Actual","Projection") -> Projection | E85: =G84 -> 735000 | F85: =SUMIFS(Cash_Events!$G$6:$G$20,Cash_Events!$C$6:$C$20,"rAGMF",Cash_Events!$M$6:$M$20,A85) -> 0 | G85: =E85-F85 -> 735000 | H85: =VLOOKUP(A85-1,Inputs!$A$40:$B$48,2,TRUE()) -> 0.0363225 | I85: =H85+Inputs!B10 -> 0.1038225 | J85: =SUMIFS(Daily!$G$6:$G$2400,Daily!$B$6:$B$2400,A85) -> 6481.084 | K85: =SUMIFS(Daily!$H$6:$H$2400,Daily!$B$6:$B$2400,A85) -> 1248.4932 | L85: =J85+K85 -> 7729.5772 | M85: =P84 -> 501446.96 | N85: =SUMIFS(Cash_Events!$H$6:$H$20,Cash_Events!$C$6:$C$20,"rAGMF",Cash_Events!$D$6:$D$20,"JV",Cash_Events!$M$6:$M$20,A85) -> 0 | O85: =SUMIFS(Cash_Events!$H$6:$H$20,Cash_Events!$C$6:$C$20,"rAGMF",Cash_Events!$D$6:$D$20,"800S",Cash_Events!$M$6:$M$20,A85) -> 0 | P85: =M85+J85-N85-O85 -> 507928.05 | Q85: =S84 -> 83836.257 | R85: =SUMIFS(Cash_Events!$I$6:$I$20,Cash_Events!$C$6:$C$20,"rAGMF",Cash_Events!$M$6:$M$20,A85) -> 0 | S85: =Q85+K85-R85 -> 85084.75 | T85: =P85+S85 -> 593012.8 | U85: =G85+T85 -> 1328012.8 | V85: =V84+L85 -> 777826.57 | W85: =W84+N85+O85+R85 -> 184813.77 | X85: =ROUND(V85-W85-T85,2) -> 0 | Y85: Lender guarantee projection date
A87: Total over life (to 31/03/2029) | F87: =SUM(F7:F85) -> 765000 | J87: =SUM(J7:J85) -> 684053.92 | K87: =SUM(K7:K85) -> 93772.65 | L87: =SUM(L7:L85) -> 777826.57 | N87: =SUM(N7:N85) -> 75648.08 | O87: =SUM(O7:O85) -> 100477.79 | R87: =SUM(R7:R85) -> 8687.9

Sheet FHL_Monthly
A1: FHL - Monthly Loan Life (drawdown 09/09/2022 to 31/03/2029)
A2: Actual = reconstructed to last month-end before reporting date; Projection = no further payments, lender method. Interest payable = lender's view of overdue amounts.
A4: Lender: | B4: =Inputs!C6 -> Financing for Healthier Lives DAC
A5: Shaded rows = projection. Blue band = lender cut-off 30/06/2026.
A6: Month end | B6: Accrual from | C6: Days | D6: Status | E6: Opening principal | F6: Principal repaid | G6: Closing principal | H6: 6M SOFR (period end) | I6: All-in rate | J6: Regular interest accrued | K6: Default interest accrued | L6: Total interest charge | M6: Opening regular interest payable | N6: Regular paid by JV | O6: Regular paid by 800S | P6: Closing regular interest payable | Q6: Opening default payable | R6: Default paid | S6: Closing default payable | T6: TOTAL INTEREST PAYABLE | U6: TOTAL EXPOSURE (principal + interest) | V6: Cumulative interest charged | W6: Cumulative interest paid | X6: Check (=0) | Y6: Events
A7: 44834 | B7: =Inputs!C8 -> 44813 | C7: =A7-B7 -> 21 | D7: =IF(A7<=EOMONTH(Inputs!$B$18,-1),"Actual","Projection") -> Actual | E7: =Inputs!C9 -> 1500000 | F7: =SUMIFS(Cash_Events!$G$6:$G$20,Cash_Events!$C$6:$C$20,"FHL",Cash_Events!$M$6:$M$20,A7) -> 0 | G7: =E7-F7 -> 1500000 | H7: =VLOOKUP(A7-1,Inputs!$F$40:$G$48,2,TRUE()) -> 0.034199996 | I7: =H7+Inputs!C10 -> 0.1017 | J7: =SUMIFS(Daily!$L$6:$L$2400,Daily!$B$6:$B$2400,A7) -> 8776.8489 | K7: =SUMIFS(Daily!$M$6:$M$2400,Daily!$B$6:$B$2400,A7) -> 0 | L7: =J7+K7 -> 8776.8489 | M7: 0 | N7: =SUMIFS(Cash_Events!$H$6:$H$20,Cash_Events!$C$6:$C$20,"FHL",Cash_Events!$D$6:$D$20,"JV",Cash_Events!$M$6:$M$20,A7) -> 0 | O7: =SUMIFS(Cash_Events!$H$6:$H$20,Cash_Events!$C$6:$C$20,"FHL",Cash_Events!$D$6:$D$20,"800S",Cash_Events!$M$6:$M$20,A7) -> 0 | P7: =M7+J7-N7-O7 -> 8776.8489 | Q7: 0 | R7: =SUMIFS(Cash_Events!$I$6:$I$20,Cash_Events!$C$6:$C$20,"FHL",Cash_Events!$M$6:$M$20,A7) -> 0 | S7: =Q7+K7-R7 -> 0 | T7: =P7+S7 -> 8776.8489 | U7: =G7+T7 -> 1508776.8 | V7: =L7 -> 8776.8489 | W7: =N7+O7+R7 -> 0 | X7: =ROUND(V7-W7-T7,2) -> 0 | Y7: Drawdown 09/09/2022
A8: =EOMONTH(A7,1) -> 44865 | B8: =A7 -> 44834 | C8: =A8-B8 -> 31 | D8: =IF(A8<=EOMONTH(Inputs!$B$18,-1),"Actual","Projection") -> Actual | E8: =G7 -> 1500000 | F8: =SUMIFS(Cash_Events!$G$6:$G$20,Cash_Events!$C$6:$C$20,"FHL",Cash_Events!$M$6:$M$20,A8) -> 0 | G8: =E8-F8 -> 1500000 | H8: =VLOOKUP(A8-1,Inputs!$F$40:$G$48,2,TRUE()) -> 0.034199996 | I8: =H8+Inputs!C10 -> 0.1017 | J8: =SUMIFS(Daily!$L$6:$L$2400,Daily!$B$6:$B$2400,A8) -> 12956.301 | K8: =SUMIFS(Daily!$M$6:$M$2400,Daily!$B$6:$B$2400,A8) -> 0 | L8: =J8+K8 -> 12956.301 | M8: =P7 -> 8776.8489 | N8: =SUMIFS(Cash_Events!$H$6:$H$20,Cash_Events!$C$6:$C$20,"FHL",Cash_Events!$D$6:$D$20,"JV",Cash_Events!$M$6:$M$20,A8) -> 0 | O8: =SUMIFS(Cash_Events!$H$6:$H$20,Cash_Events!$C$6:$C$20,"FHL",Cash_Events!$D$6:$D$20,"800S",Cash_Events!$M$6:$M$20,A8) -> 0 | P8: =M8+J8-N8-O8 -> 21733.15 | Q8: =S7 -> 0 | R8: =SUMIFS(Cash_Events!$I$6:$I$20,Cash_Events!$C$6:$C$20,"FHL",Cash_Events!$M$6:$M$20,A8) -> 0 | S8: =Q8+K8-R8 -> 0 | T8: =P8+S8 -> 21733.15 | U8: =G8+T8 -> 1521733.1 | V8: =V7+L8 -> 21733.15 | W8: =W7+N8+O8+R8 -> 0 | X8: =ROUND(V8-W8-T8,2) -> 0
A9: =EOMONTH(A8,1) -> 44895 | B9: =A8 -> 44865 | C9: =A9-B9 -> 30 | D9: =IF(A9<=EOMONTH(Inputs!$B$18,-1),"Actual","Projection") -> Actual | E9: =G8 -> 1500000 | F9: =SUMIFS(Cash_Events!$G$6:$G$20,Cash_Events!$C$6:$C$20,"FHL",Cash_Events!$M$6:$M$20,A9) -> 0 | G9: =E9-F9 -> 1500000 | H9: =VLOOKUP(A9-1,Inputs!$F$40:$G$48,2,TRUE()) -> 0.034199996 | I9: =H9+Inputs!C10 -> 0.1017 | J9: =SUMIFS(Daily!$L$6:$L$2400,Daily!$B$6:$B$2400,A9) -> 12538.356 | K9: =SUMIFS(Daily!$M$6:$M$2400,Daily!$B$6:$B$2400,A9) -> 0 | L9: =J9+K9 -> 12538.356 | M9: =P8 -> 21733.15 | N9: =SUMIFS(Cash_Events!$H$6:$H$20,Cash_Events!$C$6:$C$20,"FHL",Cash_Events!$D$6:$D$20,"JV",Cash_Events!$M$6:$M$20,A9) -> 0 | O9: =SUMIFS(Cash_Events!$H$6:$H$20,Cash_Events!$C$6:$C$20,"FHL",Cash_Events!$D$6:$D$20,"800S",Cash_Events!$M$6:$M$20,A9) -> 0 | P9: =M9+J9-N9-O9 -> 34271.505 | Q9: =S8 -> 0 | R9: =SUMIFS(Cash_Events!$I$6:$I$20,Cash_Events!$C$6:$C$20,"FHL",Cash_Events!$M$6:$M$20,A9) -> 0 | S9: =Q9+K9-R9 -> 0 | T9: =P9+S9 -> 34271.505 | U9: =G9+T9 -> 1534271.5 | V9: =V8+L9 -> 34271.505 | W9: =W8+N9+O9+R9 -> 0 | X9: =ROUND(V9-W9-T9,2) -> 0
A10: =EOMONTH(A9,1) -> 44926 | B10: =A9 -> 44895 | C10: =A10-B10 -> 31 | D10: =IF(A10<=EOMONTH(Inputs!$B$18,-1),"Actual","Projection") -> Actual | E10: =G9 -> 1500000 | F10: =SUMIFS(Cash_Events!$G$6:$G$20,Cash_Events!$C$6:$C$20,"FHL",Cash_Events!$M$6:$M$20,A10) -> 0 | G10: =E10-F10 -> 1500000 | H10: =VLOOKUP(A10-1,Inputs!$F$40:$G$48,2,TRUE()) -> 0.034199996 | I10: =H10+Inputs!C10 -> 0.1017 | J10: =SUMIFS(Daily!$L$6:$L$2400,Daily!$B$6:$B$2400,A10) -> 12956.301 | K10: =SUMIFS(Daily!$M$6:$M$2400,Daily!$B$6:$B$2400,A10) -> 0 | L10: =J10+K10 -> 12956.301 | M10: =P9 -> 34271.505 | N10: =SUMIFS(Cash_Events!$H$6:$H$20,Cash_Events!$C$6:$C$20,"FHL",Cash_Events!$D$6:$D$20,"JV",Cash_Events!$M$6:$M$20,A10) -> 0 | O10: =SUMIFS(Cash_Events!$H$6:$H$20,Cash_Events!$C$6:$C$20,"FHL",Cash_Events!$D$6:$D$20,"800S",Cash_Events!$M$6:$M$20,A10) -> 0 | P10: =M10+J10-N10-O10 -> 47227.806 | Q10: =S9 -> 0 | R10: =SUMIFS(Cash_Events!$I$6:$I$20,Cash_Events!$C$6:$C$20,"FHL",Cash_Events!$M$6:$M$20,A10) -> 0 | S10: =Q10+K10-R10 -> 0 | T10: =P10+S10 -> 47227.806 | U10: =G10+T10 -> 1547227.8 | V10: =V9+L10 -> 47227.806 | W10: =W9+N10+O10+R10 -> 0 | X10: =ROUND(V10-W10-T10,2) -> 0
A11: =EOMONTH(A10,1) -> 44957 | B11: =A10 -> 44926 | C11: =A11-B11 -> 31 | D11: =IF(A11<=EOMONTH(Inputs!$B$18,-1),"Actual","Projection") -> Actual | E11: =G10 -> 1500000 | F11: =SUMIFS(Cash_Events!$G$6:$G$20,Cash_Events!$C$6:$C$20,"FHL",Cash_Events!$M$6:$M$20,A11) -> 0 | G11: =E11-F11 -> 1500000 | H11: =VLOOKUP(A11-1,Inputs!$F$40:$G$48,2,TRUE()) -> 0.034199996 | I11: =H11+Inputs!C10 -> 0.1017 | J11: =SUMIFS(Daily!$L$6:$L$2400,Daily!$B$6:$B$2400,A11) -> 12956.301 | K11: =SUMIFS(Daily!$M$6:$M$2400,Daily!$B$6:$B$2400,A11) -> 0 | L11: =J11+K11 -> 12956.301 | M11: =P10 -> 47227.806 | N11: =SUMIFS(Cash_Events!$H$6:$H$20,Cash_Events!$C$6:$C$20,"FHL",Cash_Events!$D$6:$D$20,"JV",Cash_Events!$M$6:$M$20,A11) -> 0 | O11: =SUMIFS(Cash_Events!$H$6:$H$20,Cash_Events!$C$6:$C$20,"FHL",Cash_Events!$D$6:$D$20,"800S",Cash_Events!$M$6:$M$20,A11) -> 0 | P11: =M11+J11-N11-O11 -> 60184.107 | Q11: =S10 -> 0 | R11: =SUMIFS(Cash_Events!$I$6:$I$20,Cash_Events!$C$6:$C$20,"FHL",Cash_Events!$M$6:$M$20,A11) -> 0 | S11: =Q11+K11-R11 -> 0 | T11: =P11+S11 -> 60184.107 | U11: =G11+T11 -> 1560184.1 | V11: =V10+L11 -> 60184.107 | W11: =W10+N11+O11+R11 -> 0 | X11: =ROUND(V11-W11-T11,2) -> 0
A12: =EOMONTH(A11,1) -> 44985 | B12: =A11 -> 44957 | C12: =A12-B12 -> 28 | D12: =IF(A12<=EOMONTH(Inputs!$B$18,-1),"Actual","Projection") -> Actual | E12: =G11 -> 1500000 | F12: =SUMIFS(Cash_Events!$G$6:$G$20,Cash_Events!$C$6:$C$20,"FHL",Cash_Events!$M$6:$M$20,A12) -> 0 | G12: =E12-F12 -> 1500000 | H12: =VLOOKUP(A12-1,Inputs!$F$40:$G$48,2,TRUE()) -> 0.034199996 | I12: =H12+Inputs!C10 -> 0.1017 | J12: =SUMIFS(Daily!$L$6:$L$2400,Daily!$B$6:$B$2400,A12) -> 11702.465 | K12: =SUMIFS(Daily!$M$6:$M$2400,Daily!$B$6:$B$2400,A12) -> 0 | L12: =J12+K12 -> 11702.465 | M12: =P11 -> 60184.107 | N12: =SUMIFS(Cash_Events!$H$6:$H$20,Cash_Events!$C$6:$C$20,"FHL",Cash_Events!$D$6:$D$20,"JV",Cash_Events!$M$6:$M$20,A12) -> 0 | O12: =SUMIFS(Cash_Events!$H$6:$H$20,Cash_Events!$C$6:$C$20,"FHL",Cash_Events!$D$6:$D$20,"800S",Cash_Events!$M$6:$M$20,A12) -> 0 | P12: =M12+J12-N12-O12 -> 71886.572 | Q12: =S11 -> 0 | R12: =SUMIFS(Cash_Events!$I$6:$I$20,Cash_Events!$C$6:$C$20,"FHL",Cash_Events!$M$6:$M$20,A12) -> 0 | S12: =Q12+K12-R12 -> 0 | T12: =P12+S12 -> 71886.572 | U12: =G12+T12 -> 1571886.6 | V12: =V11+L12 -> 71886.572 | W12: =W11+N12+O12+R12 -> 0 | X12: =ROUND(V12-W12-T12,2) -> 0
A13: =EOMONTH(A12,1) -> 45016 | B13: =A12 -> 44985 | C13: =A13-B13 -> 31 | D13: =IF(A13<=EOMONTH(Inputs!$B$18,-1),"Actual","Projection") -> Actual | E13: =G12 -> 1500000 | F13: =SUMIFS(Cash_Events!$G$6:$G$20,Cash_Events!$C$6:$C$20,"FHL",Cash_Events!$M$6:$M$20,A13) -> 0 | G13: =E13-F13 -> 1500000 | H13: =VLOOKUP(A13-1,Inputs!$F$40:$G$48,2,TRUE()) -> 0.0522223 | I13: =H13+Inputs!C10 -> 0.1197223 | J13: =SUMIFS(Daily!$L$6:$L$2400,Daily!$B$6:$B$2400,A13) -> 14141.329 | K13: =SUMIFS(Daily!$M$6:$M$2400,Daily!$B$6:$B$2400,A13) -> 0 | L13: =J13+K13 -> 14141.329 | M13: =P12 -> 71886.572 | N13: =SUMIFS(Cash_Events!$H$6:$H$20,Cash_Events!$C$6:$C$20,"FHL",Cash_Events!$D$6:$D$20,"JV",Cash_Events!$M$6:$M$20,A13) -> 78155.75 | O13: =SUMIFS(Cash_Events!$H$6:$H$20,Cash_Events!$C$6:$C$20,"FHL",Cash_Events!$D$6:$D$20,"800S",Cash_Events!$M$6:$M$20,A13) -> 0 | P13: =M13+J13-N13-O13 -> 7872.1512 | Q13: =S12 -> 0 | R13: =SUMIFS(Cash_Events!$I$6:$I$20,Cash_Events!$C$6:$C$20,"FHL",Cash_Events!$M$6:$M$20,A13) -> 0 | S13: =Q13+K13-R13 -> 0 | T13: =P13+S13 -> 7872.1512 | U13: =G13+T13 -> 1507872.2 | V13: =V12+L13 -> 86027.901 | W13: =W12+N13+O13+R13 -> 78155.75 | X13: =ROUND(V13-W13-T13,2) -> 0 | Y13: Coupon 1 paid by JV 07/03/2023; reset 15/03
A14: =EOMONTH(A13,1) -> 45046 | B14: =A13 -> 45016 | C14: =A14-B14 -> 30 | D14: =IF(A14<=EOMONTH(Inputs!$B$18,-1),"Actual","Projection") -> Actual | E14: =G13 -> 1500000 | F14: =SUMIFS(Cash_Events!$G$6:$G$20,Cash_Events!$C$6:$C$20,"FHL",Cash_Events!$M$6:$M$20,A14) -> 0 | G14: =E14-F14 -> 1500000 | H14: =VLOOKUP(A14-1,Inputs!$F$40:$G$48,2,TRUE()) -> 0.0522223 | I14: =H14+Inputs!C10 -> 0.1197223 | J14: =SUMIFS(Daily!$L$6:$L$2400,Daily!$B$6:$B$2400,A14) -> 14760.284 | K14: =SUMIFS(Daily!$M$6:$M$2400,Daily!$B$6:$B$2400,A14) -> 0 | L14: =J14+K14 -> 14760.284 | M14: =P13 -> 7872.1512 | N14: =SUMIFS(Cash_Events!$H$6:$H$20,Cash_Events!$C$6:$C$20,"FHL",Cash_Events!$D$6:$D$20,"JV",Cash_Events!$M$6:$M$20,A14) -> 0 | O14: =SUMIFS(Cash_Events!$H$6:$H$20,Cash_Events!$C$6:$C$20,"FHL",Cash_Events!$D$6:$D$20,"800S",Cash_Events!$M$6:$M$20,A14) -> 0 | P14: =M14+J14-N14-O14 -> 22632.435 | Q14: =S13 -> 0 | R14: =SUMIFS(Cash_Events!$I$6:$I$20,Cash_Events!$C$6:$C$20,"FHL",Cash_Events!$M$6:$M$20,A14) -> 0 | S14: =Q14+K14-R14 -> 0 | T14: =P14+S14 -> 22632.435 | U14: =G14+T14 -> 1522632.4 | V14: =V13+L14 -> 100788.18 | W14: =W13+N14+O14+R14 -> 78155.75 | X14: =ROUND(V14-W14-T14,2) -> 0
A15: =EOMONTH(A14,1) -> 45077 | B15: =A14 -> 45046 | C15: =A15-B15 -> 31 | D15: =IF(A15<=EOMONTH(Inputs!$B$18,-1),"Actual","Projection") -> Actual | E15: =G14 -> 1500000 | F15: =SUMIFS(Cash_Events!$G$6:$G$20,Cash_Events!$C$6:$C$20,"FHL",Cash_Events!$M$6:$M$20,A15) -> 0 | G15: =E15-F15 -> 1500000 | H15: =VLOOKUP(A15-1,Inputs!$F$40:$G$48,2,TRUE()) -> 0.0522223 | I15: =H15+Inputs!C10 -> 0.1197223 | J15: =SUMIFS(Daily!$L$6:$L$2400,Daily!$B$6:$B$2400,A15) -> 15252.293 | K15: =SUMIFS(Daily!$M$6:$M$2400,Daily!$B$6:$B$2400,A15) -> 0 | L15: =J15+K15 -> 15252.293 | M15: =P14 -> 22632.435 | N15: =SUMIFS(Cash_Events!$H$6:$H$20,Cash_Events!$C$6:$C$20,"FHL",Cash_Events!$D$6:$D$20,"JV",Cash_Events!$M$6:$M$20,A15) -> 0 | O15: =SUMIFS(Cash_Events!$H$6:$H$20,Cash_Events!$C$6:$C$20,"FHL",Cash_Events!$D$6:$D$20,"800S",Cash_Events!$M$6:$M$20,A15) -> 0 | P15: =M15+J15-N15-O15 -> 37884.728 | Q15: =S14 -> 0 | R15: =SUMIFS(Cash_Events!$I$6:$I$20,Cash_Events!$C$6:$C$20,"FHL",Cash_Events!$M$6:$M$20,A15) -> 0 | S15: =Q15+K15-R15 -> 0 | T15: =P15+S15 -> 37884.728 | U15: =G15+T15 -> 1537884.7 | V15: =V14+L15 -> 116040.48 | W15: =W14+N15+O15+R15 -> 78155.75 | X15: =ROUND(V15-W15-T15,2) -> 0
A16: =EOMONTH(A15,1) -> 45107 | B16: =A15 -> 45077 | C16: =A16-B16 -> 30 | D16: =IF(A16<=EOMONTH(Inputs!$B$18,-1),"Actual","Projection") -> Actual | E16: =G15 -> 1500000 | F16: =SUMIFS(Cash_Events!$G$6:$G$20,Cash_Events!$C$6:$C$20,"FHL",Cash_Events!$M$6:$M$20,A16) -> 0 | G16: =E16-F16 -> 1500000 | H16: =VLOOKUP(A16-1,Inputs!$F$40:$G$48,2,TRUE()) -> 0.0522223 | I16: =H16+Inputs!C10 -> 0.1197223 | J16: =SUMIFS(Daily!$L$6:$L$2400,Daily!$B$6:$B$2400,A16) -> 14760.284 | K16: =SUMIFS(Daily!$M$6:$M$2400,Daily!$B$6:$B$2400,A16) -> 0 | L16: =J16+K16 -> 14760.284 | M16: =P15 -> 37884.728 | N16: =SUMIFS(Cash_Events!$H$6:$H$20,Cash_Events!$C$6:$C$20,"FHL",Cash_Events!$D$6:$D$20,"JV",Cash_Events!$M$6:$M$20,A16) -> 0 | O16: =SUMIFS(Cash_Events!$H$6:$H$20,Cash_Events!$C$6:$C$20,"FHL",Cash_Events!$D$6:$D$20,"800S",Cash_Events!$M$6:$M$20,A16) -> 0 | P16: =M16+J16-N16-O16 -> 52645.011 | Q16: =S15 -> 0 | R16: =SUMIFS(Cash_Events!$I$6:$I$20,Cash_Events!$C$6:$C$20,"FHL",Cash_Events!$M$6:$M$20,A16) -> 0 | S16: =Q16+K16-R16 -> 0 | T16: =P16+S16 -> 52645.011 | U16: =G16+T16 -> 1552645 | V16: =V15+L16 -> 130800.76 | W16: =W15+N16+O16+R16 -> 78155.75 | X16: =ROUND(V16-W16-T16,2) -> 0
A17: =EOMONTH(A16,1) -> 45138 | B17: =A16 -> 45107 | C17: =A17-B17 -> 31 | D17: =IF(A17<=EOMONTH(Inputs!$B$18,-1),"Actual","Projection") -> Actual | E17: =G16 -> 1500000 | F17: =SUMIFS(Cash_Events!$G$6:$G$20,Cash_Events!$C$6:$C$20,"FHL",Cash_Events!$M$6:$M$20,A17) -> 0 | G17: =E17-F17 -> 1500000 | H17: =VLOOKUP(A17-1,Inputs!$F$40:$G$48,2,TRUE()) -> 0.0522223 | I17: =H17+Inputs!C10 -> 0.1197223 | J17: =SUMIFS(Daily!$L$6:$L$2400,Daily!$B$6:$B$2400,A17) -> 15252.293 | K17: =SUMIFS(Daily!$M$6:$M$2400,Daily!$B$6:$B$2400,A17) -> 0 | L17: =J17+K17 -> 15252.293 | M17: =P16 -> 52645.011 | N17: =SUMIFS(Cash_Events!$H$6:$H$20,Cash_Events!$C$6:$C$20,"FHL",Cash_Events!$D$6:$D$20,"JV",Cash_Events!$M$6:$M$20,A17) -> 0 | O17: =SUMIFS(Cash_Events!$H$6:$H$20,Cash_Events!$C$6:$C$20,"FHL",Cash_Events!$D$6:$D$20,"800S",Cash_Events!$M$6:$M$20,A17) -> 0 | P17: =M17+J17-N17-O17 -> 67897.304 | Q17: =S16 -> 0 | R17: =SUMIFS(Cash_Events!$I$6:$I$20,Cash_Events!$C$6:$C$20,"FHL",Cash_Events!$M$6:$M$20,A17) -> 0 | S17: =Q17+K17-R17 -> 0 | T17: =P17+S17 -> 67897.304 | U17: =G17+T17 -> 1567897.3 | V17: =V16+L17 -> 146053.05 | W17: =W16+N17+O17+R17 -> 78155.75 | X17: =ROUND(V17-W17-T17,2) -> 0
A18: =EOMONTH(A17,1) -> 45169 | B18: =A17 -> 45138 | C18: =A18-B18 -> 31 | D18: =IF(A18<=EOMONTH(Inputs!$B$18,-1),"Actual","Projection") -> Actual | E18: =G17 -> 1500000 | F18: =SUMIFS(Cash_Events!$G$6:$G$20,Cash_Events!$C$6:$C$20,"FHL",Cash_Events!$M$6:$M$20,A18) -> 0 | G18: =E18-F18 -> 1500000 | H18: =VLOOKUP(A18-1,Inputs!$F$40:$G$48,2,TRUE()) -> 0.0522223 | I18: =H18+Inputs!C10 -> 0.1197223 | J18: =SUMIFS(Daily!$L$6:$L$2400,Daily!$B$6:$B$2400,A18) -> 15252.293 | K18: =SUMIFS(Daily!$M$6:$M$2400,Daily!$B$6:$B$2400,A18) -> 0 | L18: =J18+K18 -> 15252.293 | M18: =P17 -> 67897.304 | N18: =SUMIFS(Cash_Events!$H$6:$H$20,Cash_Events!$C$6:$C$20,"FHL",Cash_Events!$D$6:$D$20,"JV",Cash_Events!$M$6:$M$20,A18) -> 0 | O18: =SUMIFS(Cash_Events!$H$6:$H$20,Cash_Events!$C$6:$C$20,"FHL",Cash_Events!$D$6:$D$20,"800S",Cash_Events!$M$6:$M$20,A18) -> 0 | P18: =M18+J18-N18-O18 -> 83149.597 | Q18: =S17 -> 0 | R18: =SUMIFS(Cash_Events!$I$6:$I$20,Cash_Events!$C$6:$C$20,"FHL",Cash_Events!$M$6:$M$20,A18) -> 0 | S18: =Q18+K18-R18 -> 0 | T18: =P18+S18 -> 83149.597 | U18: =G18+T18 -> 1583149.6 | V18: =V17+L18 -> 161305.35 | W18: =W17+N18+O18+R18 -> 78155.75 | X18: =ROUND(V18-W18-T18,2) -> 0
A19: =EOMONTH(A18,1) -> 45199 | B19: =A18 -> 45169 | C19: =A19-B19 -> 30 | D19: =IF(A19<=EOMONTH(Inputs!$B$18,-1),"Actual","Projection") -> Actual | E19: =G18 -> 1500000 | F19: =SUMIFS(Cash_Events!$G$6:$G$20,Cash_Events!$C$6:$C$20,"FHL",Cash_Events!$M$6:$M$20,A19) -> 0 | G19: =E19-F19 -> 1500000 | H19: =VLOOKUP(A19-1,Inputs!$F$40:$G$48,2,TRUE()) -> 0.054735 | I19: =H19+Inputs!C10 -> 0.122235 | J19: =SUMIFS(Daily!$L$6:$L$2400,Daily!$B$6:$B$2400,A19) -> 14915.176 | K19: =SUMIFS(Daily!$M$6:$M$2400,Daily!$B$6:$B$2400,A19) -> 1232.8767 | L19: =J19+K19 -> 16148.053 | M19: =P18 -> 83149.597 | N19: =SUMIFS(Cash_Events!$H$6:$H$20,Cash_Events!$C$6:$C$20,"FHL",Cash_Events!$D$6:$D$20,"JV",Cash_Events!$M$6:$M$20,A19) -> 0 | O19: =SUMIFS(Cash_Events!$H$6:$H$20,Cash_Events!$C$6:$C$20,"FHL",Cash_Events!$D$6:$D$20,"800S",Cash_Events!$M$6:$M$20,A19) -> 0 | P19: =M19+J19-N19-O19 -> 98064.773 | Q19: =S18 -> 0 | R19: =SUMIFS(Cash_Events!$I$6:$I$20,Cash_Events!$C$6:$C$20,"FHL",Cash_Events!$M$6:$M$20,A19) -> 0 | S19: =Q19+K19-R19 -> 1232.8767 | T19: =P19+S19 -> 99297.65 | U19: =G19+T19 -> 1599297.7 | V19: =V18+L19 -> 177453.4 | W19: =W18+N19+O19+R19 -> 78155.75 | X19: =ROUND(V19-W19-T19,2) -> 0 | Y19: Coupon 2 missed 15/09/2023 - default interest starts
A20: =EOMONTH(A19,1) -> 45230 | B20: =A19 -> 45199 | C20: =A20-B20 -> 31 | D20: =IF(A20<=EOMONTH(Inputs!$B$18,-1),"Actual","Projection") -> Actual | E20: =G19 -> 1500000 | F20: =SUMIFS(Cash_Events!$G$6:$G$20,Cash_Events!$C$6:$C$20,"FHL",Cash_Events!$M$6:$M$20,A20) -> 0 | G20: =E20-F20 -> 1500000 | H20: =VLOOKUP(A20-1,Inputs!$F$40:$G$48,2,TRUE()) -> 0.054735 | I20: =H20+Inputs!C10 -> 0.122235 | J20: =SUMIFS(Daily!$L$6:$L$2400,Daily!$B$6:$B$2400,A20) -> 15572.404 | K20: =SUMIFS(Daily!$M$6:$M$2400,Daily!$B$6:$B$2400,A20) -> 2547.9452 | L20: =J20+K20 -> 18120.349 | M20: =P19 -> 98064.773 | N20: =SUMIFS(Cash_Events!$H$6:$H$20,Cash_Events!$C$6:$C$20,"FHL",Cash_Events!$D$6:$D$20,"JV",Cash_Events!$M$6:$M$20,A20) -> 0 | O20: =SUMIFS(Cash_Events!$H$6:$H$20,Cash_Events!$C$6:$C$20,"FHL",Cash_Events!$D$6:$D$20,"800S",Cash_Events!$M$6:$M$20,A20) -> 0 | P20: =M20+J20-N20-O20 -> 113637.18 | Q20: =S19 -> 1232.8767 | R20: =SUMIFS(Cash_Events!$I$6:$I$20,Cash_Events!$C$6:$C$20,"FHL",Cash_Events!$M$6:$M$20,A20) -> 0 | S20: =Q20+K20-R20 -> 3780.8219 | T20: =P20+S20 -> 117418 | U20: =G20+T20 -> 1617418 | V20: =V19+L20 -> 195573.75 | W20: =W19+N20+O20+R20 -> 78155.75 | X20: =ROUND(V20-W20-T20,2) -> 0
A21: =EOMONTH(A20,1) -> 45260 | B21: =A20 -> 45230 | C21: =A21-B21 -> 30 | D21: =IF(A21<=EOMONTH(Inputs!$B$18,-1),"Actual","Projection") -> Actual | E21: =G20 -> 1500000 | F21: =SUMIFS(Cash_Events!$G$6:$G$20,Cash_Events!$C$6:$C$20,"FHL",Cash_Events!$M$6:$M$20,A21) -> 0 | G21: =E21-F21 -> 1500000 | H21: =VLOOKUP(A21-1,Inputs!$F$40:$G$48,2,TRUE()) -> 0.054735 | I21: =H21+Inputs!C10 -> 0.122235 | J21: =SUMIFS(Daily!$L$6:$L$2400,Daily!$B$6:$B$2400,A21) -> 15070.068 | K21: =SUMIFS(Daily!$M$6:$M$2400,Daily!$B$6:$B$2400,A21) -> 2465.7534 | L21: =J21+K21 -> 17535.822 | M21: =P20 -> 113637.18 | N21: =SUMIFS(Cash_Events!$H$6:$H$20,Cash_Events!$C$6:$C$20,"FHL",Cash_Events!$D$6:$D$20,"JV",Cash_Events!$M$6:$M$20,A21) -> 0 | O21: =SUMIFS(Cash_Events!$H$6:$H$20,Cash_Events!$C$6:$C$20,"FHL",Cash_Events!$D$6:$D$20,"800S",Cash_Events!$M$6:$M$20,A21) -> 0 | P21: =M21+J21-N21-O21 -> 128707.25 | Q21: =S20 -> 3780.8219 | R21: =SUMIFS(Cash_Events!$I$6:$I$20,Cash_Events!$C$6:$C$20,"FHL",Cash_Events!$M$6:$M$20,A21) -> 0 | S21: =Q21+K21-R21 -> 6246.5753 | T21: =P21+S21 -> 134953.82 | U21: =G21+T21 -> 1634953.8 | V21: =V20+L21 -> 213109.57 | W21: =W20+N21+O21+R21 -> 78155.75 | X21: =ROUND(V21-W21-T21,2) -> 0
A22: =EOMONTH(A21,1) -> 45291 | B22: =A21 -> 45260 | C22: =A22-B22 -> 31 | D22: =IF(A22<=EOMONTH(Inputs!$B$18,-1),"Actual","Projection") -> Actual | E22: =G21 -> 1500000 | F22: =SUMIFS(Cash_Events!$G$6:$G$20,Cash_Events!$C$6:$C$20,"FHL",Cash_Events!$M$6:$M$20,A22) -> 0 | G22: =E22-F22 -> 1500000 | H22: =VLOOKUP(A22-1,Inputs!$F$40:$G$48,2,TRUE()) -> 0.054735 | I22: =H22+Inputs!C10 -> 0.122235 | J22: =SUMIFS(Daily!$L$6:$L$2400,Daily!$B$6:$B$2400,A22) -> 15572.404 | K22: =SUMIFS(Daily!$M$6:$M$2400,Daily!$B$6:$B$2400,A22) -> 2547.9452 | L22: =J22+K22 -> 18120.349 | M22: =P21 -> 128707.25 | N22: =SUMIFS(Cash_Events!$H$6:$H$20,Cash_Events!$C$6:$C$20,"FHL",Cash_Events!$D$6:$D$20,"JV",Cash_Events!$M$6:$M$20,A22) -> 0 | O22: =SUMIFS(Cash_Events!$H$6:$H$20,Cash_Events!$C$6:$C$20,"FHL",Cash_Events!$D$6:$D$20,"800S",Cash_Events!$M$6:$M$20,A22) -> 0 | P22: =M22+J22-N22-O22 -> 144279.65 | Q22: =S21 -> 6246.5753 | R22: =SUMIFS(Cash_Events!$I$6:$I$20,Cash_Events!$C$6:$C$20,"FHL",Cash_Events!$M$6:$M$20,A22) -> 0 | S22: =Q22+K22-R22 -> 8794.5205 | T22: =P22+S22 -> 153074.17 | U22: =G22+T22 -> 1653074.2 | V22: =V21+L22 -> 231229.92 | W22: =W21+N22+O22+R22 -> 78155.75 | X22: =ROUND(V22-W22-T22,2) -> 0
A23: =EOMONTH(A22,1) -> 45322 | B23: =A22 -> 45291 | C23: =A23-B23 -> 31 | D23: =IF(A23<=EOMONTH(Inputs!$B$18,-1),"Actual","Projection") -> Actual | E23: =G22 -> 1500000 | F23: =SUMIFS(Cash_Events!$G$6:$G$20,Cash_Events!$C$6:$C$20,"FHL",Cash_Events!$M$6:$M$20,A23) -> 0 | G23: =E23-F23 -> 1500000 | H23: =VLOOKUP(A23-1,Inputs!$F$40:$G$48,2,TRUE()) -> 0.054735 | I23: =H23+Inputs!C10 -> 0.122235 | J23: =SUMIFS(Daily!$L$6:$L$2400,Daily!$B$6:$B$2400,A23) -> 15531.229 | K23: =SUMIFS(Daily!$M$6:$M$2400,Daily!$B$6:$B$2400,A23) -> 2541.2082 | L23: =J23+K23 -> 18072.437 | M23: =P22 -> 144279.65 | N23: =SUMIFS(Cash_Events!$H$6:$H$20,Cash_Events!$C$6:$C$20,"FHL",Cash_Events!$D$6:$D$20,"JV",Cash_Events!$M$6:$M$20,A23) -> 0 | O23: =SUMIFS(Cash_Events!$H$6:$H$20,Cash_Events!$C$6:$C$20,"FHL",Cash_Events!$D$6:$D$20,"800S",Cash_Events!$M$6:$M$20,A23) -> 0 | P23: =M23+J23-N23-O23 -> 159810.88 | Q23: =S22 -> 8794.5205 | R23: =SUMIFS(Cash_Events!$I$6:$I$20,Cash_Events!$C$6:$C$20,"FHL",Cash_Events!$M$6:$M$20,A23) -> 0 | S23: =Q23+K23-R23 -> 11335.729 | T23: =P23+S23 -> 171146.61 | U23: =G23+T23 -> 1671146.6 | V23: =V22+L23 -> 249302.36 | W23: =W22+N23+O23+R23 -> 78155.75 | X23: =ROUND(V23-W23-T23,2) -> 0
A24: =EOMONTH(A23,1) -> 45351 | B24: =A23 -> 45322 | C24: =A24-B24 -> 29 | D24: =IF(A24<=EOMONTH(Inputs!$B$18,-1),"Actual","Projection") -> Actual | E24: =G23 -> 1500000 | F24: =SUMIFS(Cash_Events!$G$6:$G$20,Cash_Events!$C$6:$C$20,"FHL",Cash_Events!$M$6:$M$20,A24) -> 0 | G24: =E24-F24 -> 1500000 | H24: =VLOOKUP(A24-1,Inputs!$F$40:$G$48,2,TRUE()) -> 0.054735 | I24: =H24+Inputs!C10 -> 0.122235 | J24: =SUMIFS(Daily!$L$6:$L$2400,Daily!$B$6:$B$2400,A24) -> 14527.93 | K24: =SUMIFS(Daily!$M$6:$M$2400,Daily!$B$6:$B$2400,A24) -> 2377.0492 | L24: =J24+K24 -> 16904.98 | M24: =P23 -> 159810.88 | N24: =SUMIFS(Cash_Events!$H$6:$H$20,Cash_Events!$C$6:$C$20,"FHL",Cash_Events!$D$6:$D$20,"JV",Cash_Events!$M$6:$M$20,A24) -> 0 | O24: =SUMIFS(Cash_Events!$H$6:$H$20,Cash_Events!$C$6:$C$20,"FHL",Cash_Events!$D$6:$D$20,"800S",Cash_Events!$M$6:$M$20,A24) -> 0 | P24: =M24+J24-N24-O24 -> 174338.81 | Q24: =S23 -> 11335.729 | R24: =SUMIFS(Cash_Events!$I$6:$I$20,Cash_Events!$C$6:$C$20,"FHL",Cash_Events!$M$6:$M$20,A24) -> 0 | S24: =Q24+K24-R24 -> 13712.778 | T24: =P24+S24 -> 188051.59 | U24: =G24+T24 -> 1688051.6 | V24: =V23+L24 -> 266207.34 | W24: =W23+N24+O24+R24 -> 78155.75 | X24: =ROUND(V24-W24-T24,2) -> 0
A25: =EOMONTH(A24,1) -> 45382 | B25: =A24 -> 45351 | C25: =A25-B25 -> 31 | D25: =IF(A25<=EOMONTH(Inputs!$B$18,-1),"Actual","Projection") -> Actual | E25: =G24 -> 1500000 | F25: =SUMIFS(Cash_Events!$G$6:$G$20,Cash_Events!$C$6:$C$20,"FHL",Cash_Events!$M$6:$M$20,A25) -> 0 | G25: =E25-F25 -> 1500000 | H25: =VLOOKUP(A25-1,Inputs!$F$40:$G$48,2,TRUE()) -> 0.0525075 | I25: =H25+Inputs!C10 -> 0.1200075 | J25: =SUMIFS(Daily!$L$6:$L$2400,Daily!$B$6:$B$2400,A25) -> 15383.791 | K25: =SUMIFS(Daily!$M$6:$M$2400,Daily!$B$6:$B$2400,A25) -> 2540.9836 | L25: =J25+K25 -> 17924.775 | M25: =P24 -> 174338.81 | N25: =SUMIFS(Cash_Events!$H$6:$H$20,Cash_Events!$C$6:$C$20,"FHL",Cash_Events!$D$6:$D$20,"JV",Cash_Events!$M$6:$M$20,A25) -> 0 | O25: =SUMIFS(Cash_Events!$H$6:$H$20,Cash_Events!$C$6:$C$20,"FHL",Cash_Events!$D$6:$D$20,"800S",Cash_Events!$M$6:$M$20,A25) -> 0 | P25: =M25+J25-N25-O25 -> 189722.6 | Q25: =S24 -> 13712.778 | R25: =SUMIFS(Cash_Events!$I$6:$I$20,Cash_Events!$C$6:$C$20,"FHL",Cash_Events!$M$6:$M$20,A25) -> 0 | S25: =Q25+K25-R25 -> 16253.762 | T25: =P25+S25 -> 205976.36 | U25: =G25+T25 -> 1705976.4 | V25: =V24+L25 -> 284132.11 | W25: =W24+N25+O25+R25 -> 78155.75 | X25: =ROUND(V25-W25-T25,2) -> 0 | Y25: Coupon 3 missed 15/03/2024
A26: =EOMONTH(A25,1) -> 45412 | B26: =A25 -> 45382 | C26: =A26-B26 -> 30 | D26: =IF(A26<=EOMONTH(Inputs!$B$18,-1),"Actual","Projection") -> Actual | E26: =G25 -> 1500000 | F26: =SUMIFS(Cash_Events!$G$6:$G$20,Cash_Events!$C$6:$C$20,"FHL",Cash_Events!$M$6:$M$20,A26) -> 0 | G26: =E26-F26 -> 1500000 | H26: =VLOOKUP(A26-1,Inputs!$F$40:$G$48,2,TRUE()) -> 0.0525075 | I26: =H26+Inputs!C10 -> 0.1200075 | J26: =SUMIFS(Daily!$L$6:$L$2400,Daily!$B$6:$B$2400,A26) -> 14755.02 | K26: =SUMIFS(Daily!$M$6:$M$2400,Daily!$B$6:$B$2400,A26) -> 2459.0164 | L26: =J26+K26 -> 17214.037 | M26: =P25 -> 189722.6 | N26: =SUMIFS(Cash_Events!$H$6:$H$20,Cash_Events!$C$6:$C$20,"FHL",Cash_Events!$D$6:$D$20,"JV",Cash_Events!$M$6:$M$20,A26) -> 0 | O26: =SUMIFS(Cash_Events!$H$6:$H$20,Cash_Events!$C$6:$C$20,"FHL",Cash_Events!$D$6:$D$20,"800S",Cash_Events!$M$6:$M$20,A26) -> 0 | P26: =M26+J26-N26-O26 -> 204477.62 | Q26: =S25 -> 16253.762 | R26: =SUMIFS(Cash_Events!$I$6:$I$20,Cash_Events!$C$6:$C$20,"FHL",Cash_Events!$M$6:$M$20,A26) -> 0 | S26: =Q26+K26-R26 -> 18712.778 | T26: =P26+S26 -> 223190.4 | U26: =G26+T26 -> 1723190.4 | V26: =V25+L26 -> 301346.15 | W26: =W25+N26+O26+R26 -> 78155.75 | X26: =ROUND(V26-W26-T26,2) -> 0
A27: =EOMONTH(A26,1) -> 45443 | B27: =A26 -> 45412 | C27: =A27-B27 -> 31 | D27: =IF(A27<=EOMONTH(Inputs!$B$18,-1),"Actual","Projection") -> Actual | E27: =G26 -> 1500000 | F27: =SUMIFS(Cash_Events!$G$6:$G$20,Cash_Events!$C$6:$C$20,"FHL",Cash_Events!$M$6:$M$20,A27) -> 0 | G27: =E27-F27 -> 1500000 | H27: =VLOOKUP(A27-1,Inputs!$F$40:$G$48,2,TRUE()) -> 0.0525075 | I27: =H27+Inputs!C10 -> 0.1200075 | J27: =SUMIFS(Daily!$L$6:$L$2400,Daily!$B$6:$B$2400,A27) -> 15246.855 | K27: =SUMIFS(Daily!$M$6:$M$2400,Daily!$B$6:$B$2400,A27) -> 2540.9836 | L27: =J27+K27 -> 17787.838 | M27: =P26 -> 204477.62 | N27: =SUMIFS(Cash_Events!$H$6:$H$20,Cash_Events!$C$6:$C$20,"FHL",Cash_Events!$D$6:$D$20,"JV",Cash_Events!$M$6:$M$20,A27) -> 0 | O27: =SUMIFS(Cash_Events!$H$6:$H$20,Cash_Events!$C$6:$C$20,"FHL",Cash_Events!$D$6:$D$20,"800S",Cash_Events!$M$6:$M$20,A27) -> 0 | P27: =M27+J27-N27-O27 -> 219724.48 | Q27: =S26 -> 18712.778 | R27: =SUMIFS(Cash_Events!$I$6:$I$20,Cash_Events!$C$6:$C$20,"FHL",Cash_Events!$M$6:$M$20,A27) -> 0 | S27: =Q27+K27-R27 -> 21253.762 | T27: =P27+S27 -> 240978.24 | U27: =G27+T27 -> 1740978.2 | V27: =V26+L27 -> 319133.99 | W27: =W26+N27+O27+R27 -> 78155.75 | X27: =ROUND(V27-W27-T27,2) -> 0
A28: =EOMONTH(A27,1) -> 45473 | B28: =A27 -> 45443 | C28: =A28-B28 -> 30 | D28: =IF(A28<=EOMONTH(Inputs!$B$18,-1),"Actual","Projection") -> Actual | E28: =G27 -> 1500000 | F28: =SUMIFS(Cash_Events!$G$6:$G$20,Cash_Events!$C$6:$C$20,"FHL",Cash_Events!$M$6:$M$20,A28) -> 765000 | G28: =E28-F28 -> 735000 | H28: =VLOOKUP(A28-1,Inputs!$F$40:$G$48,2,TRUE()) -> 0.0525075 | I28: =H28+Inputs!C10 -> 0.1200075 | J28: =SUMIFS(Daily!$L$6:$L$2400,Daily!$B$6:$B$2400,A28) -> 14253.35 | K28: =SUMIFS(Daily!$M$6:$M$2400,Daily!$B$6:$B$2400,A28) -> 2375.4098 | L28: =J28+K28 -> 16628.76 | M28: =P27 -> 219724.48 | N28: =SUMIFS(Cash_Events!$H$6:$H$20,Cash_Events!$C$6:$C$20,"FHL",Cash_Events!$D$6:$D$20,"JV",Cash_Events!$M$6:$M$20,A28) -> 0 | O28: =SUMIFS(Cash_Events!$H$6:$H$20,Cash_Events!$C$6:$C$20,"FHL",Cash_Events!$D$6:$D$20,"800S",Cash_Events!$M$6:$M$20,A28) -> 98034.5 | P28: =M28+J28-N28-O28 -> 135943.33 | Q28: =S27 -> 21253.762 | R28: =SUMIFS(Cash_Events!$I$6:$I$20,Cash_Events!$C$6:$C$20,"FHL",Cash_Events!$M$6:$M$20,A28) -> 8476.64 | S28: =Q28+K28-R28 -> 15152.531 | T28: =P28+S28 -> 151095.86 | U28: =G28+T28 -> 886095.86 | V28: =V27+L28 -> 335762.75 | W28: =W27+N28+O28+R28 -> 184666.89 | X28: =ROUND(V28-W28-T28,2) -> 0 | Y28: 800S: interest 13/06 + principal 28/06/2024 (51%)
A29: =EOMONTH(A28,1) -> 45504 | B29: =A28 -> 45473 | C29: =A29-B29 -> 31 | D29: =IF(A29<=EOMONTH(Inputs!$B$18,-1),"Actual","Projection") -> Actual | E29: =G28 -> 735000 | F29: =SUMIFS(Cash_Events!$G$6:$G$20,Cash_Events!$C$6:$C$20,"FHL",Cash_Events!$M$6:$M$20,A29) -> 0 | G29: =E29-F29 -> 735000 | H29: =VLOOKUP(A29-1,Inputs!$F$40:$G$48,2,TRUE()) -> 0.0525075 | I29: =H29+Inputs!C10 -> 0.1200075 | J29: =SUMIFS(Daily!$L$6:$L$2400,Daily!$B$6:$B$2400,A29) -> 7470.9587 | K29: =SUMIFS(Daily!$M$6:$M$2400,Daily!$B$6:$B$2400,A29) -> 1245.082 | L29: =J29+K29 -> 8716.0407 | M29: =P28 -> 135943.33 | N29: =SUMIFS(Cash_Events!$H$6:$H$20,Cash_Events!$C$6:$C$20,"FHL",Cash_Events!$D$6:$D$20,"JV",Cash_Events!$M$6:$M$20,A29) -> 0 | O29: =SUMIFS(Cash_Events!$H$6:$H$20,Cash_Events!$C$6:$C$20,"FHL",Cash_Events!$D$6:$D$20,"800S",Cash_Events!$M$6:$M$20,A29) -> 0 | P29: =M29+J29-N29-O29 -> 143414.28 | Q29: =S28 -> 15152.531 | R29: =SUMIFS(Cash_Events!$I$6:$I$20,Cash_Events!$C$6:$C$20,"FHL",Cash_Events!$M$6:$M$20,A29) -> 0 | S29: =Q29+K29-R29 -> 16397.613 | T29: =P29+S29 -> 159811.9 | U29: =G29+T29 -> 894811.9 | V29: =V28+L29 -> 344478.79 | W29: =W28+N29+O29+R29 -> 184666.89 | X29: =ROUND(V29-W29-T29,2) -> 0
A30: =EOMONTH(A29,1) -> 45535 | B30: =A29 -> 45504 | C30: =A30-B30 -> 31 | D30: =IF(A30<=EOMONTH(Inputs!$B$18,-1),"Actual","Projection") -> Actual | E30: =G29 -> 735000 | F30: =SUMIFS(Cash_Events!$G$6:$G$20,Cash_Events!$C$6:$C$20,"FHL",Cash_Events!$M$6:$M$20,A30) -> 0 | G30: =E30-F30 -> 735000 | H30: =VLOOKUP(A30-1,Inputs!$F$40:$G$48,2,TRUE()) -> 0.0525075 | I30: =H30+Inputs!C10 -> 0.1200075 | J30: =SUMIFS(Daily!$L$6:$L$2400,Daily!$B$6:$B$2400,A30) -> 7470.9587 | K30: =SUMIFS(Daily!$M$6:$M$2400,Daily!$B$6:$B$2400,A30) -> 1245.082 | L30: =J30+K30 -> 8716.0407 | M30: =P29 -> 143414.28 | N30: =SUMIFS(Cash_Events!$H$6:$H$20,Cash_Events!$C$6:$C$20,"FHL",Cash_Events!$D$6:$D$20,"JV",Cash_Events!$M$6:$M$20,A30) -> 0 | O30: =SUMIFS(Cash_Events!$H$6:$H$20,Cash_Events!$C$6:$C$20,"FHL",Cash_Events!$D$6:$D$20,"800S",Cash_Events!$M$6:$M$20,A30) -> 0 | P30: =M30+J30-N30-O30 -> 150885.24 | Q30: =S29 -> 16397.613 | R30: =SUMIFS(Cash_Events!$I$6:$I$20,Cash_Events!$C$6:$C$20,"FHL",Cash_Events!$M$6:$M$20,A30) -> 0 | S30: =Q30+K30-R30 -> 17642.695 | T30: =P30+S30 -> 168527.94 | U30: =G30+T30 -> 903527.94 | V30: =V29+L30 -> 353194.83 | W30: =W29+N30+O30+R30 -> 184666.89 | X30: =ROUND(V30-W30-T30,2) -> 0
A31: =EOMONTH(A30,1) -> 45565 | B31: =A30 -> 45535 | C31: =A31-B31 -> 30 | D31: =IF(A31<=EOMONTH(Inputs!$B$18,-1),"Actual","Projection") -> Actual | E31: =G30 -> 735000 | F31: =SUMIFS(Cash_Events!$G$6:$G$20,Cash_Events!$C$6:$C$20,"FHL",Cash_Events!$M$6:$M$20,A31) -> 0 | G31: =E31-F31 -> 735000 | H31: =VLOOKUP(A31-1,Inputs!$F$40:$G$48,2,TRUE()) -> 0.0457048 | I31: =H31+Inputs!C10 -> 0.1132048 | J31: =SUMIFS(Daily!$L$6:$L$2400,Daily!$B$6:$B$2400,A31) -> 7038.7038 | K31: =SUMIFS(Daily!$M$6:$M$2400,Daily!$B$6:$B$2400,A31) -> 1204.918 | L31: =J31+K31 -> 8243.6218 | M31: =P30 -> 150885.24 | N31: =SUMIFS(Cash_Events!$H$6:$H$20,Cash_Events!$C$6:$C$20,"FHL",Cash_Events!$D$6:$D$20,"JV",Cash_Events!$M$6:$M$20,A31) -> 0 | O31: =SUMIFS(Cash_Events!$H$6:$H$20,Cash_Events!$C$6:$C$20,"FHL",Cash_Events!$D$6:$D$20,"800S",Cash_Events!$M$6:$M$20,A31) -> 0 | P31: =M31+J31-N31-O31 -> 157923.95 | Q31: =S30 -> 17642.695 | R31: =SUMIFS(Cash_Events!$I$6:$I$20,Cash_Events!$C$6:$C$20,"FHL",Cash_Events!$M$6:$M$20,A31) -> 0 | S31: =Q31+K31-R31 -> 18847.613 | T31: =P31+S31 -> 176771.56 | U31: =G31+T31 -> 911771.56 | V31: =V30+L31 -> 361438.45 | W31: =W30+N31+O31+R31 -> 184666.89 | X31: =ROUND(V31-W31-T31,2) -> 0 | Y31: Coupon missed 16/09/2024
A32: =EOMONTH(A31,1) -> 45596 | B32: =A31 -> 45565 | C32: =A32-B32 -> 31 | D32: =IF(A32<=EOMONTH(Inputs!$B$18,-1),"Actual","Projection") -> Actual | E32: =G31 -> 735000 | F32: =SUMIFS(Cash_Events!$G$6:$G$20,Cash_Events!$C$6:$C$20,"FHL",Cash_Events!$M$6:$M$20,A32) -> 0 | G32: =E32-F32 -> 735000 | H32: =VLOOKUP(A32-1,Inputs!$F$40:$G$48,2,TRUE()) -> 0.0457048 | I32: =H32+Inputs!C10 -> 0.1132048 | J32: =SUMIFS(Daily!$L$6:$L$2400,Daily!$B$6:$B$2400,A32) -> 7047.4628 | K32: =SUMIFS(Daily!$M$6:$M$2400,Daily!$B$6:$B$2400,A32) -> 1245.082 | L32: =J32+K32 -> 8292.5447 | M32: =P31 -> 157923.95 | N32: =SUMIFS(Cash_Events!$H$6:$H$20,Cash_Events!$C$6:$C$20,"FHL",Cash_Events!$D$6:$D$20,"JV",Cash_Events!$M$6:$M$20,A32) -> 0 | O32: =SUMIFS(Cash_Events!$H$6:$H$20,Cash_Events!$C$6:$C$20,"FHL",Cash_Events!$D$6:$D$20,"800S",Cash_Events!$M$6:$M$20,A32) -> 0 | P32: =M32+J32-N32-O32 -> 164971.41 | Q32: =S31 -> 18847.613 | R32: =SUMIFS(Cash_Events!$I$6:$I$20,Cash_Events!$C$6:$C$20,"FHL",Cash_Events!$M$6:$M$20,A32) -> 0 | S32: =Q32+K32-R32 -> 20092.695 | T32: =P32+S32 -> 185064.1 | U32: =G32+T32 -> 920064.1 | V32: =V31+L32 -> 369730.99 | W32: =W31+N32+O32+R32 -> 184666.89 | X32: =ROUND(V32-W32-T32,2) -> 0
A33: =EOMONTH(A32,1) -> 45626 | B33: =A32 -> 45596 | C33: =A33-B33 -> 30 | D33: =IF(A33<=EOMONTH(Inputs!$B$18,-1),"Actual","Projection") -> Actual | E33: =G32 -> 735000 | F33: =SUMIFS(Cash_Events!$G$6:$G$20,Cash_Events!$C$6:$C$20,"FHL",Cash_Events!$M$6:$M$20,A33) -> 0 | G33: =E33-F33 -> 735000 | H33: =VLOOKUP(A33-1,Inputs!$F$40:$G$48,2,TRUE()) -> 0.0457048 | I33: =H33+Inputs!C10 -> 0.1132048 | J33: =SUMIFS(Daily!$L$6:$L$2400,Daily!$B$6:$B$2400,A33) -> 6820.1252 | K33: =SUMIFS(Daily!$M$6:$M$2400,Daily!$B$6:$B$2400,A33) -> 1204.918 | L33: =J33+K33 -> 8025.0433 | M33: =P32 -> 164971.41 | N33: =SUMIFS(Cash_Events!$H$6:$H$20,Cash_Events!$C$6:$C$20,"FHL",Cash_Events!$D$6:$D$20,"JV",Cash_Events!$M$6:$M$20,A33) -> 0 | O33: =SUMIFS(Cash_Events!$H$6:$H$20,Cash_Events!$C$6:$C$20,"FHL",Cash_Events!$D$6:$D$20,"800S",Cash_Events!$M$6:$M$20,A33) -> 0 | P33: =M33+J33-N33-O33 -> 171791.53 | Q33: =S32 -> 20092.695 | R33: =SUMIFS(Cash_Events!$I$6:$I$20,Cash_Events!$C$6:$C$20,"FHL",Cash_Events!$M$6:$M$20,A33) -> 0 | S33: =Q33+K33-R33 -> 21297.613 | T33: =P33+S33 -> 193089.15 | U33: =G33+T33 -> 928089.15 | V33: =V32+L33 -> 377756.04 | W33: =W32+N33+O33+R33 -> 184666.89 | X33: =ROUND(V33-W33-T33,2) -> 0
A34: =EOMONTH(A33,1) -> 45657 | B34: =A33 -> 45626 | C34: =A34-B34 -> 31 | D34: =IF(A34<=EOMONTH(Inputs!$B$18,-1),"Actual","Projection") -> Actual | E34: =G33 -> 735000 | F34: =SUMIFS(Cash_Events!$G$6:$G$20,Cash_Events!$C$6:$C$20,"FHL",Cash_Events!$M$6:$M$20,A34) -> 0 | G34: =E34-F34 -> 735000 | H34: =VLOOKUP(A34-1,Inputs!$F$40:$G$48,2,TRUE()) -> 0.0457048 | I34: =H34+Inputs!C10 -> 0.1132048 | J34: =SUMIFS(Daily!$L$6:$L$2400,Daily!$B$6:$B$2400,A34) -> 7047.4628 | K34: =SUMIFS(Daily!$M$6:$M$2400,Daily!$B$6:$B$2400,A34) -> 1245.082 | L34: =J34+K34 -> 8292.5447 | M34: =P33 -> 171791.53 | N34: =SUMIFS(Cash_Events!$H$6:$H$20,Cash_Events!$C$6:$C$20,"FHL",Cash_Events!$D$6:$D$20,"JV",Cash_Events!$M$6:$M$20,A34) -> 0 | O34: =SUMIFS(Cash_Events!$H$6:$H$20,Cash_Events!$C$6:$C$20,"FHL",Cash_Events!$D$6:$D$20,"800S",Cash_Events!$M$6:$M$20,A34) -> 0 | P34: =M34+J34-N34-O34 -> 178839 | Q34: =S33 -> 21297.613 | R34: =SUMIFS(Cash_Events!$I$6:$I$20,Cash_Events!$C$6:$C$20,"FHL",Cash_Events!$M$6:$M$20,A34) -> 0 | S34: =Q34+K34-R34 -> 22542.695 | T34: =P34+S34 -> 201381.69 | U34: =G34+T34 -> 936381.69 | V34: =V33+L34 -> 386048.58 | W34: =W33+N34+O34+R34 -> 184666.89 | X34: =ROUND(V34-W34-T34,2) -> 0
A35: =EOMONTH(A34,1) -> 45688 | B35: =A34 -> 45657 | C35: =A35-B35 -> 31 | D35: =IF(A35<=EOMONTH(Inputs!$B$18,-1),"Actual","Projection") -> Actual | E35: =G34 -> 735000 | F35: =SUMIFS(Cash_Events!$G$6:$G$20,Cash_Events!$C$6:$C$20,"FHL",Cash_Events!$M$6:$M$20,A35) -> 0 | G35: =E35-F35 -> 735000 | H35: =VLOOKUP(A35-1,Inputs!$F$40:$G$48,2,TRUE()) -> 0.0457048 | I35: =H35+Inputs!C10 -> 0.1132048 | J35: =SUMIFS(Daily!$L$6:$L$2400,Daily!$B$6:$B$2400,A35) -> 7066.148 | K35: =SUMIFS(Daily!$M$6:$M$2400,Daily!$B$6:$B$2400,A35) -> 1248.3831 | L35: =J35+K35 -> 8314.5311 | M35: =P34 -> 178839 | N35: =SUMIFS(Cash_Events!$H$6:$H$20,Cash_Events!$C$6:$C$20,"FHL",Cash_Events!$D$6:$D$20,"JV",Cash_Events!$M$6:$M$20,A35) -> 0 | O35: =SUMIFS(Cash_Events!$H$6:$H$20,Cash_Events!$C$6:$C$20,"FHL",Cash_Events!$D$6:$D$20,"800S",Cash_Events!$M$6:$M$20,A35) -> 0 | P35: =M35+J35-N35-O35 -> 185905.15 | Q35: =S34 -> 22542.695 | R35: =SUMIFS(Cash_Events!$I$6:$I$20,Cash_Events!$C$6:$C$20,"FHL",Cash_Events!$M$6:$M$20,A35) -> 0 | S35: =Q35+K35-R35 -> 23791.078 | T35: =P35+S35 -> 209696.22 | U35: =G35+T35 -> 944696.22 | V35: =V34+L35 -> 394363.11 | W35: =W34+N35+O35+R35 -> 184666.89 | X35: =ROUND(V35-W35-T35,2) -> 0
A36: =EOMONTH(A35,1) -> 45716 | B36: =A35 -> 45688 | C36: =A36-B36 -> 28 | D36: =IF(A36<=EOMONTH(Inputs!$B$18,-1),"Actual","Projection") -> Actual | E36: =G35 -> 735000 | F36: =SUMIFS(Cash_Events!$G$6:$G$20,Cash_Events!$C$6:$C$20,"FHL",Cash_Events!$M$6:$M$20,A36) -> 0 | G36: =E36-F36 -> 735000 | H36: =VLOOKUP(A36-1,Inputs!$F$40:$G$48,2,TRUE()) -> 0.0457048 | I36: =H36+Inputs!C10 -> 0.1132048 | J36: =SUMIFS(Daily!$L$6:$L$2400,Daily!$B$6:$B$2400,A36) -> 6382.8898 | K36: =SUMIFS(Daily!$M$6:$M$2400,Daily!$B$6:$B$2400,A36) -> 1127.6712 | L36: =J36+K36 -> 7510.5611 | M36: =P35 -> 185905.15 | N36: =SUMIFS(Cash_Events!$H$6:$H$20,Cash_Events!$C$6:$C$20,"FHL",Cash_Events!$D$6:$D$20,"JV",Cash_Events!$M$6:$M$20,A36) -> 0 | O36: =SUMIFS(Cash_Events!$H$6:$H$20,Cash_Events!$C$6:$C$20,"FHL",Cash_Events!$D$6:$D$20,"800S",Cash_Events!$M$6:$M$20,A36) -> 0 | P36: =M36+J36-N36-O36 -> 192288.04 | Q36: =S35 -> 23791.078 | R36: =SUMIFS(Cash_Events!$I$6:$I$20,Cash_Events!$C$6:$C$20,"FHL",Cash_Events!$M$6:$M$20,A36) -> 0 | S36: =Q36+K36-R36 -> 24918.75 | T36: =P36+S36 -> 217206.78 | U36: =G36+T36 -> 952206.78 | V36: =V35+L36 -> 401873.67 | W36: =W35+N36+O36+R36 -> 184666.89 | X36: =ROUND(V36-W36-T36,2) -> 0
A37: =EOMONTH(A36,1) -> 45747 | B37: =A36 -> 45716 | C37: =A37-B37 -> 31 | D37: =IF(A37<=EOMONTH(Inputs!$B$18,-1),"Actual","Projection") -> Actual | E37: =G36 -> 735000 | F37: =SUMIFS(Cash_Events!$G$6:$G$20,Cash_Events!$C$6:$C$20,"FHL",Cash_Events!$M$6:$M$20,A37) -> 0 | G37: =E37-F37 -> 735000 | H37: =VLOOKUP(A37-1,Inputs!$F$40:$G$48,2,TRUE()) -> 0.0420238 | I37: =H37+Inputs!C10 -> 0.1095238 | J37: =SUMIFS(Daily!$L$6:$L$2400,Daily!$B$6:$B$2400,A37) -> 6962.9969 | K37: =SUMIFS(Daily!$M$6:$M$2400,Daily!$B$6:$B$2400,A37) -> 1248.4932 | L37: =J37+K37 -> 8211.4901 | M37: =P36 -> 192288.04 | N37: =SUMIFS(Cash_Events!$H$6:$H$20,Cash_Events!$C$6:$C$20,"FHL",Cash_Events!$D$6:$D$20,"JV",Cash_Events!$M$6:$M$20,A37) -> 0 | O37: =SUMIFS(Cash_Events!$H$6:$H$20,Cash_Events!$C$6:$C$20,"FHL",Cash_Events!$D$6:$D$20,"800S",Cash_Events!$M$6:$M$20,A37) -> 0 | P37: =M37+J37-N37-O37 -> 199251.03 | Q37: =S36 -> 24918.75 | R37: =SUMIFS(Cash_Events!$I$6:$I$20,Cash_Events!$C$6:$C$20,"FHL",Cash_Events!$M$6:$M$20,A37) -> 0 | S37: =Q37+K37-R37 -> 26167.243 | T37: =P37+S37 -> 225418.27 | U37: =G37+T37 -> 960418.27 | V37: =V36+L37 -> 410085.16 | W37: =W36+N37+O37+R37 -> 184666.89 | X37: =ROUND(V37-W37-T37,2) -> 0 | Y37: Coupon missed 17/03/2025
A38: =EOMONTH(A37,1) -> 45777 | B38: =A37 -> 45747 | C38: =A38-B38 -> 30 | D38: =IF(A38<=EOMONTH(Inputs!$B$18,-1),"Actual","Projection") -> Actual | E38: =G37 -> 735000 | F38: =SUMIFS(Cash_Events!$G$6:$G$20,Cash_Events!$C$6:$C$20,"FHL",Cash_Events!$M$6:$M$20,A38) -> 0 | G38: =E38-F38 -> 735000 | H38: =VLOOKUP(A38-1,Inputs!$F$40:$G$48,2,TRUE()) -> 0.0420238 | I38: =H38+Inputs!C10 -> 0.1095238 | J38: =SUMIFS(Daily!$L$6:$L$2400,Daily!$B$6:$B$2400,A38) -> 6616.4378 | K38: =SUMIFS(Daily!$M$6:$M$2400,Daily!$B$6:$B$2400,A38) -> 1208.2192 | L38: =J38+K38 -> 7824.657 | M38: =P37 -> 199251.03 | N38: =SUMIFS(Cash_Events!$H$6:$H$20,Cash_Events!$C$6:$C$20,"FHL",Cash_Events!$D$6:$D$20,"JV",Cash_Events!$M$6:$M$20,A38) -> 0 | O38: =SUMIFS(Cash_Events!$H$6:$H$20,Cash_Events!$C$6:$C$20,"FHL",Cash_Events!$D$6:$D$20,"800S",Cash_Events!$M$6:$M$20,A38) -> 0 | P38: =M38+J38-N38-O38 -> 205867.47 | Q38: =S37 -> 26167.243 | R38: =SUMIFS(Cash_Events!$I$6:$I$20,Cash_Events!$C$6:$C$20,"FHL",Cash_Events!$M$6:$M$20,A38) -> 0 | S38: =Q38+K38-R38 -> 27375.462 | T38: =P38+S38 -> 233242.93 | U38: =G38+T38 -> 968242.93 | V38: =V37+L38 -> 417909.82 | W38: =W37+N38+O38+R38 -> 184666.89 | X38: =ROUND(V38-W38-T38,2) -> 0
A39: =EOMONTH(A38,1) -> 45808 | B39: =A38 -> 45777 | C39: =A39-B39 -> 31 | D39: =IF(A39<=EOMONTH(Inputs!$B$18,-1),"Actual","Projection") -> Actual | E39: =G38 -> 735000 | F39: =SUMIFS(Cash_Events!$G$6:$G$20,Cash_Events!$C$6:$C$20,"FHL",Cash_Events!$M$6:$M$20,A39) -> 0 | G39: =E39-F39 -> 735000 | H39: =VLOOKUP(A39-1,Inputs!$F$40:$G$48,2,TRUE()) -> 0.0420238 | I39: =H39+Inputs!C10 -> 0.1095238 | J39: =SUMIFS(Daily!$L$6:$L$2400,Daily!$B$6:$B$2400,A39) -> 6836.9857 | K39: =SUMIFS(Daily!$M$6:$M$2400,Daily!$B$6:$B$2400,A39) -> 1248.4932 | L39: =J39+K39 -> 8085.4789 | M39: =P38 -> 205867.47 | N39: =SUMIFS(Cash_Events!$H$6:$H$20,Cash_Events!$C$6:$C$20,"FHL",Cash_Events!$D$6:$D$20,"JV",Cash_Events!$M$6:$M$20,A39) -> 0 | O39: =SUMIFS(Cash_Events!$H$6:$H$20,Cash_Events!$C$6:$C$20,"FHL",Cash_Events!$D$6:$D$20,"800S",Cash_Events!$M$6:$M$20,A39) -> 0 | P39: =M39+J39-N39-O39 -> 212704.46 | Q39: =S38 -> 27375.462 | R39: =SUMIFS(Cash_Events!$I$6:$I$20,Cash_Events!$C$6:$C$20,"FHL",Cash_Events!$M$6:$M$20,A39) -> 0 | S39: =Q39+K39-R39 -> 28623.955 | T39: =P39+S39 -> 241328.41 | U39: =G39+T39 -> 976328.41 | V39: =V38+L39 -> 425995.3 | W39: =W38+N39+O39+R39 -> 184666.89 | X39: =ROUND(V39-W39-T39,2) -> 0
A40: =EOMONTH(A39,1) -> 45838 | B40: =A39 -> 45808 | C40: =A40-B40 -> 30 | D40: =IF(A40<=EOMONTH(Inputs!$B$18,-1),"Actual","Projection") -> Actual | E40: =G39 -> 735000 | F40: =SUMIFS(Cash_Events!$G$6:$G$20,Cash_Events!$C$6:$C$20,"FHL",Cash_Events!$M$6:$M$20,A40) -> 0 | G40: =E40-F40 -> 735000 | H40: =VLOOKUP(A40-1,Inputs!$F$40:$G$48,2,TRUE()) -> 0.0420238 | I40: =H40+Inputs!C10 -> 0.1095238 | J40: =SUMIFS(Daily!$L$6:$L$2400,Daily!$B$6:$B$2400,A40) -> 6616.4378 | K40: =SUMIFS(Daily!$M$6:$M$2400,Daily!$B$6:$B$2400,A40) -> 1208.2192 | L40: =J40+K40 -> 7824.657 | M40: =P39 -> 212704.46 | N40: =SUMIFS(Cash_Events!$H$6:$H$20,Cash_Events!$C$6:$C$20,"FHL",Cash_Events!$D$6:$D$20,"JV",Cash_Events!$M$6:$M$20,A40) -> 0 | O40: =SUMIFS(Cash_Events!$H$6:$H$20,Cash_Events!$C$6:$C$20,"FHL",Cash_Events!$D$6:$D$20,"800S",Cash_Events!$M$6:$M$20,A40) -> 0 | P40: =M40+J40-N40-O40 -> 219320.89 | Q40: =S39 -> 28623.955 | R40: =SUMIFS(Cash_Events!$I$6:$I$20,Cash_Events!$C$6:$C$20,"FHL",Cash_Events!$M$6:$M$20,A40) -> 0 | S40: =Q40+K40-R40 -> 29832.174 | T40: =P40+S40 -> 249153.07 | U40: =G40+T40 -> 984153.07 | V40: =V39+L40 -> 433819.96 | W40: =W39+N40+O40+R40 -> 184666.89 | X40: =ROUND(V40-W40-T40,2) -> 0
A41: =EOMONTH(A40,1) -> 45869 | B41: =A40 -> 45838 | C41: =A41-B41 -> 31 | D41: =IF(A41<=EOMONTH(Inputs!$B$18,-1),"Actual","Projection") -> Actual | E41: =G40 -> 735000 | F41: =SUMIFS(Cash_Events!$G$6:$G$20,Cash_Events!$C$6:$C$20,"FHL",Cash_Events!$M$6:$M$20,A41) -> 0 | G41: =E41-F41 -> 735000 | H41: =VLOOKUP(A41-1,Inputs!$F$40:$G$48,2,TRUE()) -> 0.0420238 | I41: =H41+Inputs!C10 -> 0.1095238 | J41: =SUMIFS(Daily!$L$6:$L$2400,Daily!$B$6:$B$2400,A41) -> 6836.9857 | K41: =SUMIFS(Daily!$M$6:$M$2400,Daily!$B$6:$B$2400,A41) -> 1248.4932 | L41: =J41+K41 -> 8085.4789 | M41: =P40 -> 219320.89 | N41: =SUMIFS(Cash_Events!$H$6:$H$20,Cash_Events!$C$6:$C$20,"FHL",Cash_Events!$D$6:$D$20,"JV",Cash_Events!$M$6:$M$20,A41) -> 0 | O41: =SUMIFS(Cash_Events!$H$6:$H$20,Cash_Events!$C$6:$C$20,"FHL",Cash_Events!$D$6:$D$20,"800S",Cash_Events!$M$6:$M$20,A41) -> 0 | P41: =M41+J41-N41-O41 -> 226157.88 | Q41: =S40 -> 29832.174 | R41: =SUMIFS(Cash_Events!$I$6:$I$20,Cash_Events!$C$6:$C$20,"FHL",Cash_Events!$M$6:$M$20,A41) -> 0 | S41: =Q41+K41-R41 -> 31080.667 | T41: =P41+S41 -> 257238.55 | U41: =G41+T41 -> 992238.55 | V41: =V40+L41 -> 441905.44 | W41: =W40+N41+O41+R41 -> 184666.89 | X41: =ROUND(V41-W41-T41,2) -> 0
A42: =EOMONTH(A41,1) -> 45900 | B42: =A41 -> 45869 | C42: =A42-B42 -> 31 | D42: =IF(A42<=EOMONTH(Inputs!$B$18,-1),"Actual","Projection") -> Actual | E42: =G41 -> 735000 | F42: =SUMIFS(Cash_Events!$G$6:$G$20,Cash_Events!$C$6:$C$20,"FHL",Cash_Events!$M$6:$M$20,A42) -> 0 | G42: =E42-F42 -> 735000 | H42: =VLOOKUP(A42-1,Inputs!$F$40:$G$48,2,TRUE()) -> 0.0420238 | I42: =H42+Inputs!C10 -> 0.1095238 | J42: =SUMIFS(Daily!$L$6:$L$2400,Daily!$B$6:$B$2400,A42) -> 6836.9857 | K42: =SUMIFS(Daily!$M$6:$M$2400,Daily!$B$6:$B$2400,A42) -> 1248.4932 | L42: =J42+K42 -> 8085.4789 | M42: =P41 -> 226157.88 | N42: =SUMIFS(Cash_Events!$H$6:$H$20,Cash_Events!$C$6:$C$20,"FHL",Cash_Events!$D$6:$D$20,"JV",Cash_Events!$M$6:$M$20,A42) -> 0 | O42: =SUMIFS(Cash_Events!$H$6:$H$20,Cash_Events!$C$6:$C$20,"FHL",Cash_Events!$D$6:$D$20,"800S",Cash_Events!$M$6:$M$20,A42) -> 0 | P42: =M42+J42-N42-O42 -> 232994.86 | Q42: =S41 -> 31080.667 | R42: =SUMIFS(Cash_Events!$I$6:$I$20,Cash_Events!$C$6:$C$20,"FHL",Cash_Events!$M$6:$M$20,A42) -> 0 | S42: =Q42+K42-R42 -> 32329.161 | T42: =P42+S42 -> 265324.03 | U42: =G42+T42 -> 1000324 | V42: =V41+L42 -> 449990.92 | W42: =W41+N42+O42+R42 -> 184666.89 | X42: =ROUND(V42-W42-T42,2) -> 0
A43: =EOMONTH(A42,1) -> 45930 | B43: =A42 -> 45900 | C43: =A43-B43 -> 30 | D43: =IF(A43<=EOMONTH(Inputs!$B$18,-1),"Actual","Projection") -> Actual | E43: =G42 -> 735000 | F43: =SUMIFS(Cash_Events!$G$6:$G$20,Cash_Events!$C$6:$C$20,"FHL",Cash_Events!$M$6:$M$20,A43) -> 0 | G43: =E43-F43 -> 735000 | H43: =VLOOKUP(A43-1,Inputs!$F$40:$G$48,2,TRUE()) -> 0.0386433 | I43: =H43+Inputs!C10 -> 0.1061433 | J43: =SUMIFS(Daily!$L$6:$L$2400,Daily!$B$6:$B$2400,A43) -> 6514.3282 | K43: =SUMIFS(Daily!$M$6:$M$2400,Daily!$B$6:$B$2400,A43) -> 1208.2192 | L43: =J43+K43 -> 7722.5473 | M43: =P42 -> 232994.86 | N43: =SUMIFS(Cash_Events!$H$6:$H$20,Cash_Events!$C$6:$C$20,"FHL",Cash_Events!$D$6:$D$20,"JV",Cash_Events!$M$6:$M$20,A43) -> 0 | O43: =SUMIFS(Cash_Events!$H$6:$H$20,Cash_Events!$C$6:$C$20,"FHL",Cash_Events!$D$6:$D$20,"800S",Cash_Events!$M$6:$M$20,A43) -> 0 | P43: =M43+J43-N43-O43 -> 239509.19 | Q43: =S42 -> 32329.161 | R43: =SUMIFS(Cash_Events!$I$6:$I$20,Cash_Events!$C$6:$C$20,"FHL",Cash_Events!$M$6:$M$20,A43) -> 0 | S43: =Q43+K43-R43 -> 33537.38 | T43: =P43+S43 -> 273046.57 | U43: =G43+T43 -> 1008046.6 | V43: =V42+L43 -> 457713.46 | W43: =W42+N43+O43+R43 -> 184666.89 | X43: =ROUND(V43-W43-T43,2) -> 0 | Y43: Coupon missed 15/09/2025
A44: =EOMONTH(A43,1) -> 45961 | B44: =A43 -> 45930 | C44: =A44-B44 -> 31 | D44: =IF(A44<=EOMONTH(Inputs!$B$18,-1),"Actual","Projection") -> Actual | E44: =G43 -> 735000 | F44: =SUMIFS(Cash_Events!$G$6:$G$20,Cash_Events!$C$6:$C$20,"FHL",Cash_Events!$M$6:$M$20,A44) -> 0 | G44: =E44-F44 -> 735000 | H44: =VLOOKUP(A44-1,Inputs!$F$40:$G$48,2,TRUE()) -> 0.0386433 | I44: =H44+Inputs!C10 -> 0.1061433 | J44: =SUMIFS(Daily!$L$6:$L$2400,Daily!$B$6:$B$2400,A44) -> 6625.9592 | K44: =SUMIFS(Daily!$M$6:$M$2400,Daily!$B$6:$B$2400,A44) -> 1248.4932 | L44: =J44+K44 -> 7874.4523 | M44: =P43 -> 239509.19 | N44: =SUMIFS(Cash_Events!$H$6:$H$20,Cash_Events!$C$6:$C$20,"FHL",Cash_Events!$D$6:$D$20,"JV",Cash_Events!$M$6:$M$20,A44) -> 0 | O44: =SUMIFS(Cash_Events!$H$6:$H$20,Cash_Events!$C$6:$C$20,"FHL",Cash_Events!$D$6:$D$20,"800S",Cash_Events!$M$6:$M$20,A44) -> 0 | P44: =M44+J44-N44-O44 -> 246135.15 | Q44: =S43 -> 33537.38 | R44: =SUMIFS(Cash_Events!$I$6:$I$20,Cash_Events!$C$6:$C$20,"FHL",Cash_Events!$M$6:$M$20,A44) -> 0 | S44: =Q44+K44-R44 -> 34785.873 | T44: =P44+S44 -> 280921.02 | U44: =G44+T44 -> 1015921 | V44: =V43+L44 -> 465587.91 | W44: =W43+N44+O44+R44 -> 184666.89 | X44: =ROUND(V44-W44-T44,2) -> 0
A45: =EOMONTH(A44,1) -> 45991 | B45: =A44 -> 45961 | C45: =A45-B45 -> 30 | D45: =IF(A45<=EOMONTH(Inputs!$B$18,-1),"Actual","Projection") -> Actual | E45: =G44 -> 735000 | F45: =SUMIFS(Cash_Events!$G$6:$G$20,Cash_Events!$C$6:$C$20,"FHL",Cash_Events!$M$6:$M$20,A45) -> 0 | G45: =E45-F45 -> 735000 | H45: =VLOOKUP(A45-1,Inputs!$F$40:$G$48,2,TRUE()) -> 0.0386433 | I45: =H45+Inputs!C10 -> 0.1061433 | J45: =SUMIFS(Daily!$L$6:$L$2400,Daily!$B$6:$B$2400,A45) -> 6412.2185 | K45: =SUMIFS(Daily!$M$6:$M$2400,Daily!$B$6:$B$2400,A45) -> 1208.2192 | L45: =J45+K45 -> 7620.4377 | M45: =P44 -> 246135.15 | N45: =SUMIFS(Cash_Events!$H$6:$H$20,Cash_Events!$C$6:$C$20,"FHL",Cash_Events!$D$6:$D$20,"JV",Cash_Events!$M$6:$M$20,A45) -> 0 | O45: =SUMIFS(Cash_Events!$H$6:$H$20,Cash_Events!$C$6:$C$20,"FHL",Cash_Events!$D$6:$D$20,"800S",Cash_Events!$M$6:$M$20,A45) -> 0 | P45: =M45+J45-N45-O45 -> 252547.37 | Q45: =S44 -> 34785.873 | R45: =SUMIFS(Cash_Events!$I$6:$I$20,Cash_Events!$C$6:$C$20,"FHL",Cash_Events!$M$6:$M$20,A45) -> 0 | S45: =Q45+K45-R45 -> 35994.092 | T45: =P45+S45 -> 288541.46 | U45: =G45+T45 -> 1023541.5 | V45: =V44+L45 -> 473208.35 | W45: =W44+N45+O45+R45 -> 184666.89 | X45: =ROUND(V45-W45-T45,2) -> 0
A46: =EOMONTH(A45,1) -> 46022 | B46: =A45 -> 45991 | C46: =A46-B46 -> 31 | D46: =IF(A46<=EOMONTH(Inputs!$B$18,-1),"Actual","Projection") -> Actual | E46: =G45 -> 735000 | F46: =SUMIFS(Cash_Events!$G$6:$G$20,Cash_Events!$C$6:$C$20,"FHL",Cash_Events!$M$6:$M$20,A46) -> 0 | G46: =E46-F46 -> 735000 | H46: =VLOOKUP(A46-1,Inputs!$F$40:$G$48,2,TRUE()) -> 0.0386433 | I46: =H46+Inputs!C10 -> 0.1061433 | J46: =SUMIFS(Daily!$L$6:$L$2400,Daily!$B$6:$B$2400,A46) -> 6625.9592 | K46: =SUMIFS(Daily!$M$6:$M$2400,Daily!$B$6:$B$2400,A46) -> 1248.4932 | L46: =J46+K46 -> 7874.4523 | M46: =P45 -> 252547.37 | N46: =SUMIFS(Cash_Events!$H$6:$H$20,Cash_Events!$C$6:$C$20,"FHL",Cash_Events!$D$6:$D$20,"JV",Cash_Events!$M$6:$M$20,A46) -> 0 | O46: =SUMIFS(Cash_Events!$H$6:$H$20,Cash_Events!$C$6:$C$20,"FHL",Cash_Events!$D$6:$D$20,"800S",Cash_Events!$M$6:$M$20,A46) -> 0 | P46: =M46+J46-N46-O46 -> 259173.33 | Q46: =S45 -> 35994.092 | R46: =SUMIFS(Cash_Events!$I$6:$I$20,Cash_Events!$C$6:$C$20,"FHL",Cash_Events!$M$6:$M$20,A46) -> 0 | S46: =Q46+K46-R46 -> 37242.585 | T46: =P46+S46 -> 296415.91 | U46: =G46+T46 -> 1031415.9 | V46: =V45+L46 -> 481082.8 | W46: =W45+N46+O46+R46 -> 184666.89 | X46: =ROUND(V46-W46-T46,2) -> 0
